Workbook

Sheet Purchases
C2: LC Purchase- Usuance Interest Calculation for the month of Apr'26 | I2: Amount in INR
C3: Party Name | D3: Bank Name | E3: Agreed Usuance ROI % | F3: Total BOE Value | G3: Total Interest Charged by Bank | H3: Total Charges (As per Auditor) | I3: Excess/(Short) (Incl. Penal Charge if any) | J3: Management's Remarks | K3: Auditor's Remarks
C4: TATA STEEL LIMITED | E4: 0.076 | F4: =SUMIF($E$10:$E$13,$C$4,N:N) -> 0 | G4: =SUMIF($E$10:$E$13,$C$4,J11:J13) -> 0 | H4: =SUMIF($E$10:$E$14,$C$4,P10:P13) -> 0 | I4: =G4-H4 -> 0
C5: JINDAL STEEL ODISHA LIMITED | D5: UCO Bank | E5: 0.072 | F5: =SUMIFS(O:O,D:D,D5,E:E,C5) -> 2271779.2 | G5: =SUMIFS(M:M,D:D,D5,E:E,C5) -> 42555.69 | H5: =SUMIFS(S:S,D:D,D5,E:E,C5) -> 42555.296 | I5: =G5-H5 -> 0.39449096
C6: JINDAL STEEL ODISHA LIMITED | D6: ICICI Bank | E6: 0.072 | F6: =SUMIFS(O:O,D:D,D6,E:E,C6) -> 641100.75 | G6: =SUMIFS(M:M,D:D,D6,E:E,C6) -> 12010.04 | H6: =SUMIFS(S:S,D:D,D6,E:E,C6) -> 12009.178 | I6: =G6-H6 -> 0.86229479
C7: Total | F7: =SUM(F4:F5) -> 2271779.2 | G7: =SUM(G4:G5) -> 42555.69 | H7: =SUM(H4:H5) -> 42555.296 | I7: =SUM(I4:I5) -> 0.39449096
F9: As per BOE | P9: As per Auditor's calculation | U9: ROI Calculation | X9: SAP | Y9: Difference
C10: Vendor BOE No. | D10: Bank Name | E10: Vendor Name | F10: BOE Date | G10: Invoice Amount / Material Basic (including GST) | H10: Material Basic (excluding GST) | I10: GST on Material Basic | J10: Interest Amount (Excl. GST) | K10: GST on Interest. | L10: TDS u-s 194A | M10: Total Interest (Inc GST) | N10: TDS u-s 194Q | O10: Total BOE Amount | P10: Interest Amount (Excl. GST) | Q10: GST on Interest. | R10: TDS u-s 194A | S10: Total Interest (Inc GST) | T10: TDS u-s 194Q | U10: Int Rate Charged by Bank | V10: Agreed Rate | W10: Difference | X10: Interest as per SAP | Y10: BOE Vs SAP | Z10: BOE Vs Auditor Calculation | AA10: Auditor Remarks
B11: 2027/01 | C11: 102901 | D11: UCO Bank | E11: JINDAL STEEL ODISHA LIMITED | F11: 18.03.2026 | G11: 1559243 | H11: =G11/1.18 -> 1321392.4 | I11: =H11*0.18 -> 237850.63 | J11: 27682 | K11: 4983 | L11: 2768.19 | M11: =J11+K11-L11 -> 29896.81 | N11: 1321.39 | O11: =SUM(H11:L11,N11) -> 1595997.6 | P11: =G11*U11*90/365 -> 27681.903 | Q11: =P11*0.18 -> 4982.7426 | R11: =P11*0.1 -> 2768.1903 | S11: =P11+Q11-R11 -> 29896.455 | T11: =H11*0.1% -> 1321.3924 | U11: 0.072 | V11: 0.072 | W11: =U11-V11 -> 0 | X11: =SUMIFS(SAP!H:H,SAP!P:P, "BOE",SAP!R:R,Purchases!C11,SAP!V:V,Purchases!B11) -> 27682.2 | Y11: =ROUND(J11-X11,0) -> 0 | Z11: =ROUND(J11-P11,0) -> 0 | AA11: OK
B12: 2027/01 | C12: 103010 | D12: UCO Bank | E12: JINDAL STEEL ODISHA LIMITED | F12: 01.04.2026 | G12: 660219 | H12: =G12/1.18 -> 559507.63 | I12: =H12*0.18 -> 100711.37 | J12: 11721 | K12: 2110 | L12: 1172.12 | M12: =J12+K12-L12 -> 12658.88 | N12: 559.51 | O12: =SUM(H12:L12,N12) -> 675781.63 | P12: =G12*U12*90/365 -> 11721.148 | Q12: =P12*0.18 -> 2109.8067 | R12: =P12*0.1 -> 1172.1148 | S12: =P12+Q12-R12 -> 12658.84 | T12: =H12*0.1% -> 559.50763 | U12: 0.072 | V12: 0.072 | W12: =U12-V12 -> 0 | X12: =SUMIFS(SAP!H:H,SAP!P:P, "BOE",SAP!R:R,Purchases!C12,SAP!V:V,Purchases!B12) -> 11721.19 | Y12: =ROUND(J12-X12,0) -> 0 | Z12: =ROUND(J12-P12,0) -> 0 | AA12: OK
B13: 2027/01 | C13: 103011 | D13: ICICI Bank | E13: JINDAL STEEL ODISHA LIMITED | F13: 01.04.2026 | G13: 626336 | H13: =G13/1.18 -> 530793.22 | I13: =H13*0.18 -> 95542.78 | J13: 11120 | K13: 2002 | L13: 1111.96 | M13: =J13+K13-L13 -> 12010.04 | N13: 530.79 | O13: =SUM(H13:L13,N13) -> 641100.75 | P13: =G13*U13*90/365 -> 11119.609 | Q13: =P13*0.18 -> 2001.5296 | R13: =P13*0.1 -> 1111.9609 | S13: =P13+Q13-R13 -> 12009.178 | T13: =H13*0.1% -> 530.79322 | U13: 0.072 | V13: 0.072 | W13: =U13-V13 -> 0 | X13: =SUMIFS(SAP!H:H,SAP!P:P, "BOE",SAP!R:R,Purchases!C13,SAP!V:V,Purchases!B13) -> 11119.49 | Y13: =ROUND(J13-X13,0) -> 1 | Z13: =ROUND(J13-P13,0) -> 0 | AA13: OK
C14: TOTAL | G14: =SUM(G11:G13) -> 2845798 | H14: =SUM(H11:H13) -> 2411693.2 | I14: =SUM(I11:I13) -> 434104.78 | J14: =SUM(J11:J13) -> 50523 | K14: =SUM(K11:K13) -> 9095 | L14: =SUM(L11:L13) -> 5052.27 | M14: =SUM(M11:M13) -> 54565.73 | N14: =SUM(N11:N13) -> 2411.69 | ... T14: =SUM(T11:T13) -> 2411.6932 | W14: =SUM(W11:W13) -> 0 | X14: =SUM(X11:X13) -> 50522.88 | Y14: =SUM(Y11:Y13) -> 1

Sheet Sales
J1: Amount in INR
E2: Particulars | F2: Bank Name | G2: Bill Discounted | H2: Total Interest Expenses ( As per Bank Advice) | I2: Total Interest Expenses ( As per Auditor) | J2: Excess/(Short)
E3: Export Bill Discounted | F3: HDFC | G3: =SUMIFS(O:O,C:C,"Export",D:D,F3) -> 5.2962473e+08 | H3: =SUMIFS(W:W,C:C,"Export",D:D,F3) -> 4021172.8 | I3: =SUMIFS(AD:AD,C:C,"Export",D:D,F3) -> 4020447.9 | J3: =H3-I3 -> 724.85969
E4: Domestic Bill Discounted | F4: HDFC | G4: =SUMIFS(O:O,C:C,"Domestic",D:D,F4) -> 0 | H4: =SUMIFS(W:W,C:C,"DOMESTIC",D:D,F4) -> 0 | I4: =SUMIFS(AD:AD,C:C,"DOMESTIC",D:D,F4) -> 0 | J4: =H4-I4 -> 0
E5: Export Bill Discounted | F5: Kotak | G5: =SUMIFS(O:O,C:C,"Export",D:D,F5) -> 0 | H5: =SUMIFS(W:W,C:C,"Export",D:D,F5) -> 0 | I5: =SUMIFS(AD:AD,C:C,"Export",D:D,F5) -> 0 | J5: =H5-I5 -> 0
E6: Domestic Bill Discounted | F6: Kotak | G6: =SUMIFS(O:O,C:C,"Domestic",D:D,F6) -> 17921042 | H6: =SUMIFS(W:W,C:C,"DOMESTIC",D:D,F6) -> 246280.77 | I6: =SUMIFS(AD:AD,C:C,"DOMESTIC",D:D,F6) -> 246280.77 | J6: =H6-I6 -> 0.0018
E7: Interest Credited | G7: 0 | H7: =SUMIFS(SAP!H:H,SAP!P:P, "Intt Recd",SAP!V:V, "2027/01") -> -53786.75 | I7: =H7 -> -53786.75 | J7: =H7-I7 -> 0
E8: Penal Interest | G8: 0 | H8: =SUMIFS(SAP!H:H,SAP!P:P, "Penal interest",SAP!V:V, "2027/01") -> 59626.4 | I8: =H8 -> 59626.4 | J8: =H8-I8 -> 0
E9: Total | F9: Total | G9: =SUM(G3:G8) -> 5.4754577e+08 | H9: =SUM(H3:H8) -> 4273293.2 | I9: =SUM(I3:I8) -> 4272568.4 | J9: =SUM(J3:J8) -> 724.86149
O11: As per Bank | Z11: As per Auditor
C12: Sales Type | D12: Bank | E12: Customer Name | F12: Discounting Date | G12: Reference No | H12: Invoice No. | I12: Start Date | J12: End Date | K12: No. of days | L12: Bill Discounted Value (Euro) | M12: Currency | N12: Exchange Rate | O12: Bill Discounted Value (INR) | P12: Discounting Interest | Q12: Bill Comm | R12: Courier Postage | S12: FX Conversion | T12: Handling Charges | U12: GST | V12: Total Chgs as per Bank | W12: Total Chgs as per Bank (Excl GST) | X12: Total Charges Booked in SAP (Excl GST) | Y12: Difference (S-T) | Z12: ROI% (As per LC Advice) | AA12: Penal Interest % | AB12: Interest Calculated (INR) | AC12: Commission Calculated | AD12: Total Charges Calculated | AE12: Excess(Shortfall) (S-Z) | AF12: Interest Remarks | AG12: Management Remarks | AH12: Auditors' Remarks
B13: 2027/01 | C13: Export | D13: HDFC | E13: PAGOUNI SA | F13: 06-APR-2026 | G13: 469BC89260860007 | H13: 5400514061 | I13: 06-APR-2026 | J13: 17-JUL-2026 | K13: =J13-I13 -> 102 | L13: 274518.42 | M13: EUR | N13: 107.36 | O13: =L13*N13 -> 29472298 | P13: 351388.21 | S13: 33972.3 | U13: 6115.02 | V13: 357503.23 | W13: =SUM(P13:R13) -> 351388.21 | X13: =SUMIFS(SAP!H:H,SAP!L:L,Sales!G13,SAP!V:V,Sales!B13) -> 351388.21 | Y13: =ROUND(W13-X13,0) -> 0 | Z13: 4.208 | AA13: 6.208 | AB13: =O13*Z13%*K13/360 -> 351388.38 | AC13: =Q13+R13 -> 0 | AD13: =AB13+AC13 -> 351388.38 | AE13: =ROUND(W13-AD13,0) -> 0 | AF13: OK | AH13: =IF(AF13="Excess","Clarification Required"," ")
B14: 2027/01 | C14: Export | D14: HDFC | E14: KAMARIDAS GLOBAL WIRE ABEE | F14: 02-APR-2026 | G14: 469BC89260890006 | H14: 5400514062 | I14: 02-APR-2026 | J14: 23-JUN-2026 | K14: =J14-I14+1 -> 83 | L14: 155026.8 | M14: EUR | N14: 107.15 | O14: =L14*N14 -> 16611122 | P14: 137791.86 | S14: 21111.12 | U14: 3800 | V14: 141591.86 | W14: =SUM(P14:R14) -> 137791.86 | X14: =SUMIFS(SAP!H:H,SAP!L:L,Sales!G14,SAP!V:V,Sales!B14) -> 137791.86 | Y14: =ROUND(W14-X14,0) -> 0 | Z14: 3.579 | AA14: 5.579 | AB14: =O14*Z14%*K14/360 -> 137068.05 | AC14: =Q14+R14 -> 0 | AD14: =AB14+AC14 -> 137068.05 | AE14: =ROUND(W14-AD14,0) -> 724 | AF14: =IF(AE14>0,"Excess","Shortfall") -> Excess | AH14: =IF(AF14="Excess","Clarification Required"," ") -> Clarification Required
B15: 2027/01 | C15: Export | D15: HDFC | E15: LATTONEDIL S P A MILANO | F15: 13-APR-2026 | G15: 469BC89261030001 | H15: 5400514090 | I15: 13-APR-2026 | J15: 05-JUN-2026 | K15: =J15-I15 -> 53 | L15: 20892.97 | M15: EUR | N15: 108.96 | O15: =L15*N15 -> 2276498 | P15: 12394.2 | Q15: 2000 | R15: 2500 | S15: 6776.5 | U15: 1219.78 | V15: 13613.98 | W15: =SUM(P15:R15) -> 16894.2 | X15: =SUMIFS(SAP!H:H,SAP!L:L,Sales!G15,SAP!V:V,Sales!B15,SAP!P:P, "lc sales") -> 16894.2 | Y15: =ROUND(W15-X15,0) -> 0 | Z15: 3.698 | AA15: 5.698 | AB15: =O15*Z15%*K15/360 -> 12393.888 | AC15: =Q15+R15 -> 4500 | AD15: =AB15+AC15 -> 16893.888 | AE15: =ROUND(W15-AD15,0) -> 0 | AF15: OK | AH15: =IF(AF15="Excess","Clarification Required"," ")
B16: 2027/01 | C16: Export | D16: HDFC | E16: LATTONEDIL S P A MILANO | F16: 13-APR-2026 | G16: 469BC89261030003 | H16: 5400514093 | I16: 13-APR-2026 | J16: 08-JUN-2026 | K16: =J16-I16 -> 56 | L16: 19508.37 | M16: EUR | N16: 108.96 | O16: =L16*N16 -> 2125632 | P16: 12227.49 | Q16: 2000 | R16: 2500 | S16: 6625.63 | U16: 1192.62 | V16: 13420.11 | W16: =SUM(P16:R16) -> 16727.49 | X16: =SUMIFS(SAP!H:H,SAP!L:L,Sales!G16,SAP!V:V,Sales!B16,SAP!P:P, "lc sales") -> 16727.49 | Y16: =ROUND(W16-X16,0) -> 0 | Z16: 3.698 | AA16: 5.698 | AB16: =O16*Z16%*K16/360 -> 12227.58 | AC16: =Q16+R16 -> 4500 | AD16: =AB16+AC16 -> 16727.58 | AE16: =ROUND(W16-AD16,0) -> 0 | AF16: OK | AH16: =IF(AF16="Excess","Clarification Required"," ")
B17: 2027/01 | C17: Export | D17: HDFC | E17: IDROCENTRO SPA | F17: 16-APR-2026 | G17: 469BC89261030011 | H17: 5400514072 | I17: 16-APR-2026 | J17: 18-JUN-2026 | K17: =J17-I17 -> 63 | L17: 224967.27 | M17: EUR | N17: 109.8725 | O17: =L17*N17 -> 24717716 | P17: 161907.02 | Q17: 2000 | R17: 2500 | S17: 29217.72 | U17: 5259.18 | V17: 167166.2 | W17: =SUM(P17:R17) -> 166407.02 | X17: =SUMIFS(SAP!H:H,SAP!L:L,Sales!G17,SAP!V:V,Sales!B17) -> 166407.02 | Y17: =ROUND(W17-X17,0) -> 0 | Z17: 3.743 | AA17: 5.743 | AB17: =O17*Z17%*K17/360 -> 161907.22 | AC17: =Q17+R17 -> 4500 | AD17: =AB17+AC17 -> 166407.22 | AE17: =ROUND(W17-AD17,0) -> 0 | AF17: OK | AH17: =IF(AF17="Excess","Clarification Required"," ")
B18: 2027/01 | C18: Export | D18: HDFC | E18: LATTONEDIL S P A MILANO | F18: 16-APR-2026 | G18: 469BC89261030007 | H18: 5400514083 | I18: 16-APR-2026 | J18: 04-JUN-2026 | K18: =J18-I18 -> 49 | L18: 112383.45 | M18: EUR | N18: 109.8725 | O18: =L18*N18 -> 12347851 | P18: 62907.5 | Q18: 2000 | R18: 2500 | S18: 16847.85 | U18: 3032.62 | V18: 65940.12 | W18: =SUM(P18:R18) -> 67407.5 | X18: =SUMIFS(SAP!H:H,SAP!L:L,Sales!G18,SAP!V:V,Sales!B18) -> 67407.5 | Y18: =ROUND(W18-X18,0) -> 0 | Z18: 3.743 | AA18: 5.743 | AB18: =O18*Z18%*K18/360 -> 62907.84 | AC18: =Q18+R18 -> 4500 | AD18: =AB18+AC18 -> 67407.84 | AE18: =ROUND(W18-AD18,0) -> 0 | AF18: OK | AH18: =IF(AF18="Excess","Clarification Required"," ")
B19: 2027/01 | C19: Export | D19: HDFC | E19: IDROCENTRO SPA | F19: 16-APR-2026 | G19: 469BC89261030010 | H19: 5400154078 | I19: 16-APR-2026 | J19: 22-JUN-2026 | K19: =J19-I19 -> 67 | L19: 82889.55 | M19: EUR | N19: 109.8725 | O19: =L19*N19 -> 9107282.1 | P19: 63442.58 | Q19: 2000 | R19: 2500 | S19: 13607.28 | U19: 2449.32 | V19: 65891.9 | W19: =SUM(P19:R19) -> 67942.58 | X19: =SUMIFS(SAP!H:H,SAP!L:L,Sales!G19,SAP!V:V,Sales!B19) -> 67942.58 | Y19: =ROUND(W19-X19,0) -> 0 | Z19: 3.743 | AA19: 5.743 | AB19: =O19*Z19%*K19/360 -> 63442.592 | AC19: =Q19+R19 -> 4500 | AD19: =AB19+AC19 -> 67942.592 | AE19: =ROUND(W19-AD19,0) -> 0 | AF19: OK | AH19: =IF(AF19="Excess","Clarification Required"," ")
B20: 2027/01 | C20: Export | D20: HDFC | E20: LATTONEDIL ROMANIA SRL | F20: 16-APR-2026 | G20: 469BC89261060001 | H20: 5400514079 | I20: 16-APR-2026 | J20: 01-JUN-2026 | K20: =J20-I20 -> 46 | L20: 211833.14 | M20: EUR | N20: 109.8725 | O20: =L20*N20 -> 23274637 | P20: 111316.22 | Q20: 2000 | R20: 2500 | S20: 27774.64 | U20: 4999.44 | V20: 116315.66 | W20: =SUM(P20:R20) -> 115816.22 | X20: =SUMIFS(SAP!H:H,SAP!L:L,Sales!G20,SAP!V:V,Sales!B20) -> 115816.22 | Y20: =ROUND(W20-X20,0) -> 0 | Z20: 3.743 | AA20: 5.743 | AB20: =O20*Z20%*K20/360 -> 111316.12 | AC20: =Q20+R20 -> 4500 | AD20: =AB20+AC20 -> 115816.12 | AE20: =ROUND(W20-AD20,0) -> 0 | AF20: OK | AH20: =IF(AF20="Excess","Clarification Required"," ")
B21: 2027/01 | C21: Export | D21: HDFC | E21: ISOLPACK S P A | F21: 16-APR-2026 | G21: 469BC89261060002 | H21: 5400514081 | I21: 16-APR-2026 | J21: 03-JUL-2026 | K21: =J21-I21 -> 78 | L21: 78515.47 | M21: EUR | N21: 109.8725 | O21: =L21*N21 -> 8626691 | P21: 69961.31 | Q21: 2000 | R21: 2500 | S21: 13126.69 | U21: 2362.8 | V21: 72324.11 | W21: =SUM(P21:R21) -> 74461.31 | X21: =SUMIFS(SAP!H:H,SAP!L:L,Sales!G21,SAP!V:V,Sales!B21) -> 74461.31 | Y21: =ROUND(W21-X21,0) -> 0 | Z21: 3.743 | AA21: 5.743 | AB21: =O21*Z21%*K21/360 -> 69961.026 | AC21: =Q21+R21 -> 4500 | AD21: =AB21+AC21 -> 74461.026 | AE21: =ROUND(W21-AD21,0) -> 0 | AF21: OK | AH21: =IF(AF21="Excess","Clarification Required"," ")
B22: 2027/01 | C22: Export | D22: HDFC | E22: ISOLPACK SPA SIGLABILE CERIA ISOLPA | F22: 16-APR-2026 | G22: 469BC89261060003 | H22: 5400514086 | I22: 16-APR-2026 | J22: 03-JUL-2026 | K22: =J22-I22 -> 78 | L22: 407974.55 | M22: EUR | N22: 109.8725 | O22: =L22*N22 -> 44825184 | P22: 363525.25 | Q22: 2000 | R22: 2500 | S22: 49325.18 | U22: 8878.54 | V22: 372403.79 | W22: =SUM(P22:R22) -> 368025.25 | X22: =SUMIFS(SAP!H:H,SAP!L:L,Sales!G22,SAP!V:V,Sales!B22) -> 368025.25 | Y22: =ROUND(W22-X22,0) -> 0 | Z22: 3.743 | AA22: 5.743 | AB22: =O22*Z22%*K22/360 -> 363524.77 | AC22: =Q22+R22 -> 4500 | AD22: =AB22+AC22 -> 368024.77 | AE22: =ROUND(W22-AD22,0) -> 0 | AF22: OK | AH22: =IF(AF22="Excess","Clarification Required"," ")
B23: 2027/01 | C23: Export | D23: HDFC | E23: BRAVO INTERNATIONAL RO SRL | F23: 20-APR-2026 | G23: 469BC89261100007 | H23: 5400514068 | I23: 20-APR-2026 | J23: 01-JUL-2026 | K23: =J23-I23 -> 72 | L23: 89033.33 | M23: EUR | N23: 109.5808 | O23: =L23*N23 -> 9756343.5 | P23: 72275.11 | Q23: 4500 | U23: 0 | V23: 72275.11 | W23: =SUM(P23:R23) -> 76775.11 | X23: =SUMIFS(SAP!H:H,SAP!L:L,Sales!G23,SAP!V:V,Sales!B23) -> 76775.11 | Y23: =ROUND(W23-X23,0) -> 0 | Z23: 3.704 | AA23: 5.704 | AB23: =O23*Z23%*K23/360 -> 72274.993 | AC23: =Q23+R23 -> 4500 | AD23: =AB23+AC23 -> 76774.993 | AE23: =ROUND(W23-AD23,0) -> 0 | AF23: OK | AH23: =IF(AF23="Excess","Clarification Required"," ")
B24: 2027/01 | C24: Export | D24: HDFC | E24: TOPANEL PRODUCTION PANELS SA | F24: 20-APR-2026 | G24: 469BC89261100005 | H24: 5400514104 | I24: 20-APR-2026 | J24: 07-JUL-2026 | K24: =J24-I24 -> 78 | L24: 134807.2 | M24: EUR | N24: 109.5808 | O24: =L24*N24 -> 14772281 | P24: 118552.18 | Q24: 4500 | U24: 0 | V24: 118552.18 | W24: =SUM(P24:R24) -> 123052.18 | X24: =SUMIFS(SAP!H:H,SAP!L:L,Sales!G24,SAP!V:V,Sales!B24) -> 123052.18 | Y24: =ROUND(W24-X24,0) -> 0 | Z24: 3.704 | AA24: 5.704 | AB24: =O24*Z24%*K24/360 -> 118552.48 | AC24: =Q24+R24 -> 4500 | AD24: =AB24+AC24 -> 123052.48 | AE24: =ROUND(W24-AD24,0) -> 0 | AF24: OK | AH24: =IF(AF24="Excess","Clarification Required"," ")
B25: 2027/01 | C25: Export | D25: HDFC | E25: TOPANEL PRODUCTION PANELS SA | F25: 20-APR-2026 | G25: 469BC89261100004 | H25: 5400514067 | I25: 20-APR-2026 | J25: 01-JUL-2026 | K25: =J25-I25 -> 72 | L25: 132199.52 | M25: EUR | N25: 109.5808 | O25: =L25*N25 -> 14486529 | P25: 107315.76 | Q25: 4500 | U25: 0 | V25: 107315.76 | W25: =SUM(P25:R25) -> 111815.76 | X25: =SUMIFS(SAP!H:H,SAP!L:L,Sales!G25,SAP!V:V,Sales!B25) -> 111815.76 | Y25: =ROUND(W25-X25,0) -> 0 | Z25: 3.704 | AA25: 5.704 | AB25: =O25*Z25%*K25/360 -> 107316.21 | AC25: =Q25+R25 -> 4500 | AD25: =AB25+AC25 -> 111816.21 | AE25: =ROUND(W25-AD25,0) -> 0 | AF25: OK | AH25: =IF(AF25="Excess","Clarification Required"," ")
B26: 2027/01 | C26: Export | D26: HDFC | E26: LATTONEDIL ROMANIA SRL | F26: 20-APR-2026 | G26: 469BC89261100002 | H26: 5400514065 | I26: 20-APR-2026 | J26: 01-JUN-2026 | K26: =J26-I26 -> 42 | L26: 120378.52 | M26: EUR | N26: 109.5808 | O26: =L26*N26 -> 13191175 | P26: 57003.93 | Q26: 4500 | U26: 0 | V26: 57003.93 | W26: =SUM(P26:R26) -> 61503.93 | X26: =SUMIFS(SAP!H:H,SAP!L:L,Sales!G26,SAP!V:V,Sales!B26) -> 61503.93 | Y26: =ROUND(W26-X26,0) -> 0 | Z26: 3.704 | AA26: 5.704 | AB26: =O26*Z26%*K26/360 -> 57003.462 | AC26: =Q26+R26 -> 4500 | AD26: =AB26+AC26 -> 61503.462 | AE26: =ROUND(W26-AD26,0) -> 0 | AF26: OK | AH26: =IF(AF26="Excess","Clarification Required"," ")
B27: 2027/01 | C27: Export | D27: HDFC | E27: BRAVO INTERNATIONAL RO SRL | F27: 21-APR-2026 | G27: 469BC89261110006 | H27: 5400514098 | I27: 21-APR-2026 | J27: 07-JUL-2026 | K27: =J27-I27 -> 77 | L27: 63932.31 | M27: EUR | N27: 109.5395 | O27: =L27*N27 -> 7003113.3 | P27: 55481.76 | Q27: 2000 | R27: 2500 | U27: 810 | V27: 55481.76 | W27: =SUM(P27:R27) -> 59981.76 | X27: =SUMIFS(SAP!H:H,SAP!L:L,Sales!G27,SAP!V:V,Sales!B27) -> 59981.76 | Y27: =ROUND(W27-X27,0) -> 0 | Z27: 3.704 | AA27: 5.704 | AB27: =O27*Z27%*K27/360 -> 55481.776 | AC27: =Q27+R27 -> 4500 | AD27: =AB27+AC27 -> 59981.776 | AE27: =ROUND(W27-AD27,0) -> 0 | AF27: OK | AH27: =IF(AF27="Excess","Clarification Required"," ")
B28: 2027/01 | C28: Export | D28: HDFC | E28: TOPANEL PRODUCTION PANELS SA | F28: 21-APR-2026 | G28: 469BC89261110008 | H28: 5400514066 | I28: 21-APR-2026 | J28: 31-JUL-2026 | K28: =J28-I28 -> 101 | L28: 89772.92 | M28: EUR | N28: 109.5395 | O28: =L28*N28 -> 9833680.8 | P28: 114908.03 | Q28: 2000 | R28: 2500 | U28: 810 | V28: 114908.03 | W28: =SUM(P28:R28) -> 119408.03 | X28: =SUMIFS(SAP!H:H,SAP!L:L,Sales!G28,SAP!V:V,Sales!B28) -> 119408.03 | Y28: =ROUND(W28-X28,0) -> 0 | Z28: 4.165 | AA28: 6.165 | AB28: =O28*Z28%*K28/360 -> 114907.93 | AC28: =Q28+R28 -> 4500 | AD28: =AB28+AC28 -> 119407.93 | AE28: =ROUND(W28-AD28,0) -> 0 | AF28: OK | AH28: =IF(AF28="Excess","Clarification Required"," ")
B29: 2027/01 | C29: Export | D29: HDFC | E29: SC TERASTEEL SA | F29: 21-APR-2026 | G29: 469BC89261110009 | H29: 5400514096 | I29: 21-APR-2026 | J29: 07-JUL-2026 | K29: =J29-I29 -> 77 | L29: 36362.07 | M29: EUR | N29: 109.5395 | O29: =L29*N29 -> 3983083 | P29: 31556.14 | Q29: 2000 | R29: 2500 | U29: 810 | V29: 31556.14 | W29: =SUM(P29:R29) -> 36056.14 | X29: =SUMIFS(SAP!H:H,SAP!L:L,Sales!G29,SAP!V:V,Sales!B29) -> 36056.14 | Y29: =ROUND(W29-X29,0) -> 0 | Z29: 3.704 | AA29: 5.704 | AB29: =O29*Z29%*K29/360 -> 31555.754 | AC29: =Q29+R29 -> 4500 | AD29: =AB29+AC29 -> 36055.754 | AE29: =ROUND(W29-AD29,0) -> 0 | AF29: OK | AH29: =IF(AF29="Excess","Clarification Required"," ")
B30: 2027/01 | C30: Export | D30: HDFC | E30: INGROS COPERTURE S R L | F30: 23-APR-2026 | G30: 469BC89261130001 | H30: 5400514092 | I30: 24-APR-2026 | J30: 20-JUL-2026 | K30: =J30-I30 -> 87 | L30: 78392.41 | M30: EUR | N30: 109.98 | O30: =L30*N30 -> 8621597.3 | P30: 76278.83 | Q30: 2000 | R30: 2500 | S30: 13121.6 | U30: 2361.88 | V30: 78640.71 | W30: =SUM(P30:R30) -> 80778.83 | X30: =SUMIFS(SAP!H:H,SAP!L:L,Sales!G30,SAP!V:V,Sales!B30) -> 80778.83 | Y30: =ROUND(W30-X30,0) -> 0 | Z30: 3.661 | AA30: 5.661 | AB30: =O30*Z30%*K30/360 -> 76278.863 | AC30: =Q30+R30 -> 4500 | AD30: =AB30+AC30 -> 80778.863 | AE30: =ROUND(W30-AD30,0) -> 0 | AF30: OK | AH30: =IF(AF30="Excess","Clarification Required"," ")
B31: 2027/01 | C31: Export | D31: HDFC | E31: TOPANEL PRODUCTION PANELS SA | F31: 23-APR-2026 | G31: 469BC89261130003 | H31: 5400514121 | I31: 28-APR-2026 | J31: 16-JUL-2026 | K31: =J31-I31 -> 79 | L31: 198877.3 | M31: EUR | N31: 110.515 | O31: =L31*N31 -> 21978925 | P31: 176672.59 | Q31: 2000 | R31: 2500 | S31: 26478.93 | U31: 4766.2 | V31: 181438.79 | W31: =SUM(P31:R31) -> 181172.59 | X31: =SUMIFS(SAP!H:H,SAP!L:L,Sales!G31,SAP!V:V,Sales!B31) -> 181172.59 | Y31: =ROUND(W31-X31,0) -> 0 | Z31: 3.663 | AA31: 5.663 | AB31: =O31*Z31%*K31/360 -> 176672.09 | AC31: =Q31+R31 -> 4500 | AD31: =AB31+AC31 -> 181172.09 | AE31: =ROUND(W31-AD31,0) -> 0 | AF31: OK | AH31: =IF(AF31="Excess","Clarification Required"," ")
B32: 2027/01 | C32: Export | D32: HDFC | E32: ISOLPACK SPA SIGLABILE CERIA ISOLPA | F32: 24-APR-2026 | G32: 469BC89261140003 | H32: 5400514087 | I32: 24-APR-2026 | J32: 20-JUL-2026 | K32: =J32-I32 -> 87 | L32: 123770.74 | M32: EUR | N32: 109.98 | O32: =L32*N32 -> 13612306 | P32: =117138.6+3296.18 -> 120434.78 | Q32: 2000 | R32: 2500 | S32: 17739.86 | U32: 3193.18 | V32: 120331.78 | W32: =SUM(P32:R32) -> 124934.78 | X32: =SUMIFS(SAP!H:H,SAP!L:L,Sales!G32,SAP!V:V,Sales!B32) -> 124934.78 | Y32: =ROUND(W32-X32,0) -> 0 | Z32: 3.661 | AA32: 5.661 | AB32: =O32*Z32%*K32/360 -> 120433.74 | AC32: =Q32+R32 -> 4500 | AD32: =AB32+AC32 -> 124933.74 | AE32: 0 | AF32: OK | AH32: =IF(AF32="Excess","Clarification Required"," ")
B33: 2027/01 | C33: Export | D33: HDFC | E33: ITALPANNELLI IBERICA SA | F33: 24-APR-2026 | G33: 469BC89261140007 | H33: 5400514113 | I33: 24-APR-2026 | J33: 17-JUL-2026 | K33: =J33-I33 -> 84 | L33: 595198.71 | M33: EUR | N33: 109.98 | O33: =L33*N33 -> 65459954 | P33: 559181.21 | Q33: 2000 | R33: 2500 | S33: 60000 | U33: 10800 | V33: 569981.21 | W33: =SUM(P33:R33) -> 563681.21 | X33: =SUMIFS(SAP!H:H,SAP!L:L,Sales!G33,SAP!V:V,Sales!B33) -> 563681.21 | Y33: =ROUND(W33-X33,0) -> 0 | Z33: 3.661 | AA33: 5.661 | AB33: =O33*Z33%*K33/360 -> 559180.75 | AC33: =Q33+R33 -> 4500 | AD33: =AB33+AC33 -> 563680.75 | AE33: =ROUND(W33-AD33,0) -> 0 | AF33: OK | AH33: =IF(AF33="Excess","Clarification Required"," ")
B34: 2027/01 | C34: Export | D34: HDFC | E34: KAMARIDIS GLOBAL WIRE ABEE | F34: 24-APR-2026 | G34: 469BC89261140008 | H34: 5400514094 | I34: 24-APR-2026 | J34: 20-JUL-2026 | K34: =J34-I34 -> 87 | L34: 121261.37 | M34: EUR | N34: 109.98 | O34: =L34*N34 -> 13336325 | P34: 117992.04 | Q34: 2000 | R34: 2500 | S34: 17836.33 | U34: 3210.54 | V34: 121202.58 | W34: =SUM(P34:R34) -> 122492.04 | X34: =SUMIFS(SAP!H:H,SAP!L:L,Sales!G34,SAP!V:V,Sales!B34) -> 122492.04 | Y34: =ROUND(W34-X34,0) -> 0 | Z34: 3.661 | AA34: 5.661 | AB34: =O34*Z34%*K34/360 -> 117992.03 | AC34: =Q34+R34 -> 4500 | AD34: =AB34+AC34 -> 122492.03 | AE34: =ROUND(W34-AD34,0) -> 0 | AF34: OK | AH34: =IF(AF34="Excess","Clarification Required"," ")
B35: 2027/01 | C35: Export | D35: HDFC | E35: LATTONEDIL S P A MILANO | F35: 24-APR-2026 | G35: 469BC89261140009 | H35: 5400514116 | I35: 24-APR-2026 | J35: 19-JUN-2026 | K35: =J35-I35 -> 56 | L35: 143980.48 | M35: EUR | N35: 109.98 | O35: =L35*N35 -> 15834973 | P35: 90178.1 | Q35: 2000 | R35: 2500 | S35: 20334.97 | U35: 3660.3 | V35: 93838.4 | W35: =SUM(P35:R35) -> 94678.1 | X35: =SUMIFS(SAP!H:H,SAP!L:L,Sales!G35,SAP!V:V,Sales!B35) -> 94678.1 | Y35: =ROUND(W35-X35,0) -> 0 | Z35: 3.661 | AA35: 5.661 | AB35: =O35*Z35%*K35/360 -> 90178.413 | AC35: =Q35+R35 -> 4500 | AD35: =AB35+AC35 -> 94678.413 | AE35: =ROUND(W35-AD35,0) -> 0 | AF35: OK | AH35: =IF(AF35="Excess","Clarification Required"," ")
B36: 2027/01 | C36: Export | D36: HDFC | E36: KAMARIDIS GLOBAL WIRE ABEE | F36: 27-APR-2026 | G36: 469BC89261170007 | H36: 5400514119 | I36: 28-APR-2026 | J36: 20-JUL-2026 | K36: =J36-I36 -> 83 | L36: 152902.86 | M36: EUR | N36: 110.515 | O36: =L36*N36 -> 16898060 | P36: 142708.02 | Q36: 2000 | R36: 2500 | S36: 21398.06 | U36: 3851.66 | V36: 146559.68 | W36: =SUM(P36:R36) -> 147208.02 | X36: =SUMIFS(SAP!H:H,SAP!L:L,Sales!G36,SAP!V:V,Sales!B36) -> 147208.02 | Y36: =ROUND(W36-X36,0) -> 0 | Z36: 3.663 | AA36: 5.663 | AB36: =O36*Z36%*K36/360 -> 142708.34 | AC36: =Q36+R36 -> 4500 | AD36: =AB36+AC36 -> 147208.34 | AE36: =ROUND(W36-AD36,0) -> 0 | AF36: OK | AH36: =IF(AF36="Excess","Clarification Required"," ")
B37: 2027/01 | C37: Export | D37: HDFC | E37: LATTONEDIL S P A MILANO | F37: 24-APR-2026 | G37: 469BC89261140010 | H37: 5400514118 | I37: 28-APR-2026 | J37: 19-JUN-2026 | K37: =J37-I37 -> 52 | L37: 67278.72 | M37: EUR | N37: 110.515 | O37: =L37*N37 -> 7435307.7 | P37: 39340.02 | Q37: 2000 | R37: 2500 | S37: 11935.31 | U37: 2148.36 | V37: 41488.38 | W37: =SUM(P37:R37) -> 43840.02 | X37: =SUMIFS(SAP!H:H,SAP!L:L,Sales!G37,SAP!V:V,Sales!B37) -> 43840.02 | Y37: =ROUND(W37-X37,0) -> 0 | Z37: 3.663 | AA37: 5.663 | AB37: =O37*Z37%*K37/360 -> 39340.213 | AC37: =Q37+R37 -> 4500 | AD37: =AB37+AC37 -> 43840.213 | AE37: =ROUND(W37-AD37,0) -> 0 | AF37: OK | AH37: =IF(AF37="Excess","Clarification Required"," ")
B38: 2027/01 | C38: Export | D38: HDFC | E38: IDROCENTRO SPA | F38: 28-APR-2026 | G38: 469BC89261180001 | H38: 5400514075 | I38: 28-APR-2026 | J38: 19-JUN-2026 | K38: =J38-I38 -> 52 | L38: 409750.63 | M38: EUR | N38: 110.515 | O38: =L38*N38 -> 45283591 | P38: 239595.41 | Q38: 2000 | R38: 2500 | S38: 49783.59 | U38: 8961.04 | V38: 248556.45 | W38: =SUM(P38:R38) -> 244095.41 | X38: =SUMIFS(SAP!H:H,SAP!L:L,Sales!G38,SAP!V:V,Sales!B38) -> 244095.41 | Y38: =ROUND(W38-X38,0) -> 0 | Z38: 3.663 | AA38: 5.663 | AB38: =O38*Z38%*K38/360 -> 239595.48 | AC38: =Q38+R38 -> 4500 | AD38: =AB38+AC38 -> 244095.48 | AE38: =ROUND(W38-AD38,0) -> 0 | AF38: OK | AH38: =IF(AF38="Excess","Clarification Required"," ")
B39: 2027/01 | C39: Export | D39: HDFC | E39: LATTONEDIL S P A MILANO | F39: 30-APR-2026 | G39: 469BC89261200004 | H39: 5400514115 | I39: 30-APR-2026 | J39: 19-JUN-2026 | K39: =J39-I39 -> 50 | L39: 397529.59 | M39: EUR | N39: 110.91 | O39: =L39*N39 -> 44090007 | P39: 223511.38 | Q39: 2000 | R39: 2500 | S39: 48590.01 | U39: 8746.2 | V39: 232257.58 | W39: =SUM(P39:R39) -> 228011.38 | X39: =SUMIFS(SAP!H:H,SAP!L:L,Sales!G39,SAP!V:V,Sales!B39) -> 228011.38 | Y39: =ROUND(W39-X39,0) -> 0 | Z39: 3.65 | AA39: 5.65 | AB39: =O39*Z39%*K39/360 -> 223511.84 | AC39: =Q39+R39 -> 4500 | AD39: =AB39+AC39 -> 228011.84 | AE39: =ROUND(W39-AD39,0) -> 0 | AF39: OK | AH39: =IF(AF39="Excess","Clarification Required"," ")
B40: 2027/01 | C40: Export | D40: HDFC | E40: LATTONEDIL ROMANIA SRL | F40: 46129 | G40: 469BC89261070001 | H40: 5400514099 | I40: 46129 | J40: 46178 | K40: =J40-I40 -> 49 | L40: 123340.16 | M40: EUR | N40: 109.41 | O40: =L40*N40 -> 13494647 | P40: 68695.26 | Q40: 2000 | R40: 2500 | U40: =P40*0.18+Q40*0.18+R40*0.18 -> 13175.147 | V40: 232257.58 | W40: =SUM(P40:R40) -> 73195.26 | X40: =SUMIFS(SAP!H:H,SAP!L:L,Sales!G40,SAP!V:V,Sales!B40,SAP!P:P, "sales") -> 73195.26 | Y40: =ROUND(W40-X40,0) -> 0 | Z40: 3.74 | AA40: 5.74 | AB40: =O40*Z40%*K40/360 -> 68695.25 | AC40: =Q40+R40 -> 4500 | AD40: =AB40+AC40 -> 73195.25 | AE40: =ROUND(W40-AD40,0) -> 0 | AF40: OK | AH40: =IF(AF40="Excess","Clarification Required"," ")
B41: 2027/01 | C41: Export | D41: HDFC | E41: BRAVO INTERNATIONAL RO SRL | F41: 46129 | G41: 469BC89261070002 | H41: 5400514095 | I41: 46129 | J41: 46210 | K41: =J41-I41 -> 81 | L41: 44029.98 | M41: EUR | N41: 109.41 | O41: =L41*N41 -> 4817320.1 | P41: 40537.5 | Q41: 2000 | R41: 2500 | U41: =P41*0.18+Q41*0.18+R41*0.18 -> 8106.75 | V41: 232257.58 | W41: =SUM(P41:R41) -> 45037.5 | X41: =SUMIFS(SAP!H:H,SAP!L:L,Sales!G41,SAP!V:V,Sales!B41) -> 45037.5 | Y41: =ROUND(W41-X41,0) -> 0 | Z41: 3.74 | AA41: 5.74 | AB41: =O41*Z41%*K41/360 -> 40537.749 | AC41: =Q41+R41 -> 4500 | AD41: =AB41+AC41 -> 45037.749 | AE41: =ROUND(W41-AD41,0) -> 0 | AF41: OK
B42: 2027/01 | C42: Export | D42: HDFC | E42: LATTONEDIL ROMANIA SRL | F42: 46132 | G42: 469BC89261100003 | H42: 5400514100 | I42: 46132 | J42: 46178 | K42: =J42-I42 -> 46 | L42: 20855.88 | M42: EUR | N42: 109.5808 | O42: =L42*N42 -> 2285404 | P42: 10816.72 | Q42: 2000 | R42: 2500 | U42: =P42*0.18+Q42*0.18+R42*0.18 -> 2757.0096 | V42: 232257.58 | W42: =SUM(P42:R42) -> 15316.72 | X42: =SUMIFS(SAP!H:H,SAP!L:L,Sales!G42,SAP!V:V,Sales!B42) -> 15316.72 | Y42: =ROUND(W42-X42,0) -> 0 | Z42: 3.704 | AA42: 5.704 | AB42: =O42*Z42%*K42/360 -> 10816.563 | AC42: =Q42+R42 -> 4500 | AD42: =AB42+AC42 -> 15316.563 | AE42: =ROUND(W42-AD42,0) -> 0 | AF42: OK
B43: 2027/01 | C43: Export | D43: HDFC | E43: TOPANEL PRODUCTION PANELS SA | F43: 46132 | G43: 469BC89261100006 | H43: 5400514105 | I43: 46132 | J43: 46210 | K43: =J43-I43 -> 78 | L43: 91851.82 | M43: EUR | N43: 109.5808 | O43: =L43*N43 -> 10065196 | P43: 80776.39 | Q43: 2000 | R43: 2500 | U43: =P43*0.18+Q43*0.18+R43*0.18 -> 15349.75 | V43: 232257.58 | W43: =SUM(P43:R43) -> 85276.39 | X43: =SUMIFS(SAP!H:H,SAP!L:L,Sales!G43,SAP!V:V,Sales!B43) -> 85276.39 | Y43: =ROUND(W43-X43,0) -> 0 | Z43: 3.704 | AA43: 5.704 | AB43: =O43*Z43%*K43/360 -> 80776.552 | AC43: =Q43+R43 -> 4500 | AD43: =AB43+AC43 -> 85276.552 | AE43: =ROUND(W43-AD43,0) -> 0 | AF43: OK
B44: 2027/01 | C44: Domestic | D44: KOTAK | E44: ISOLLOYD ENGINEERING TECHNO | F44: 46128 | G44: 0822BDO266053335 | I44: 46128 | J44: 46202 | K44: =J44-I44 -> 74 | L44: 0 | M44: INR | N44: 0 | O44: 8170745 | P44: 120927.03 | R44: 1250 | U44: 225 | V44: =SUM(P44:U44) -> 122402.03 | W44: =SUM(P44:T44) -> 122177.03 | X44: =SUMIFS(SAP!H:H,SAP!L:L,Sales!G44,SAP!V:V,Sales!B44,SAP!P:P, "LC Sales") -> 122177.03 | Y44: =ROUND(W44-X44,0) -> 0 | Z44: 7.3 | AA44: 7.3 | AB44: =O44*Z44%*K44/365 -> 120927.03 | AC44: =Q44+R44 -> 1250 | AD44: =AB44+AC44 -> 122177.03 | AE44: =ROUND(P44-AB44,0) -> 0 | AF44: OK | AH44: =IF(AF44="Excess","Clarification Required"," ")
B45: 2027/01 | C45: Domestic | D45: KOTAK | E45: ISOLLOYD ENGINEERING TECHNO | F45: 46128 | G45: 0822BDO266053336 | I45: 46128 | J45: 46191 | K45: =J45-I45 -> 63 | L45: 0 | M45: INR | N45: 0 | O45: 9750297 | P45: 122853.74 | R45: 1250 | U45: 225 | V45: =SUM(P45:U45) -> 124328.74 | W45: =SUM(P45:T45) -> 124103.74 | X45: =SUMIFS(SAP!H:H,SAP!L:L,Sales!G45,SAP!V:V,Sales!B45,SAP!P:P, "LC Sales") -> 124103.74 | Y45: =ROUND(W45-X45,0) -> 0 | Z45: 7.3 | AA45: 7.3 | AB45: =O45*Z45%*K45/365 -> 122853.74 | AC45: =Q45+R45 -> 1250 | AD45: =AB45+AC45 -> 124103.74 | AE45: =ROUND(P45-AB45,0) -> 0 | AF45: OK | AH45: =IF(AF45="Excess","Clarification Required"," ")
C46: TOTAL | L46: =SUM(L13:L45) -> 4824016.5 | N46: =SUM(N13:N45) -> 3399.4583 | O46: =SUM(O13:O45) -> 5.4754577e+08 | P46: =SUM(P13:P45) -> 4134453.6 | Q46: =SUM(Q13:Q45) -> 68000 | R46: =SUM(R13:R45) -> 65000 | S46: =SUM(S13:S45) -> 505603.57 | T46: =SUM(T13:T45) -> 0 | U46: =SUM(U13:U45) -> 133277.34 | ... AE46: =SUM(AE13:AE45) -> 724

Sheet Sheet4
A3: Reference No | B3: Sum of Net Amount | C3: Sales | D3: Sales amount | E3: Charges | F3: Amount | G3: Retirement | H3: Amount
A4: 014LCEX253590021 | B4: -1180 | C4: =VLOOKUP(A4,Sales!$G$12:$V$45,1,FALSE) -> #N/A
A5: 014LCEX260910002 | B5: -1770 | C5: =VLOOKUP(A5,Sales!$G$12:$V$45,1,FALSE) -> #N/A
A6: 014LCEX260920001 | B6: -1770 | C6: =VLOOKUP(A6,Sales!$G$12:$V$45,1,FALSE) -> #N/A
A7: 014LCEX260920018 | B7: -1770 | C7: =VLOOKUP(A7,Sales!$G$12:$V$45,1,FALSE) -> #N/A
A8: 014LCEX261010002 | B8: -1770 | C8: =VLOOKUP(A8,Sales!$G$12:$V$45,1,FALSE) -> #N/A
A9: 014LCEX261130002 | B9: -1770 | C9: =VLOOKUP(A9,Sales!$G$12:$V$45,1,FALSE) -> #N/A
A10: 014LCEX261180044 | B10: -1770 | C10: =VLOOKUP(A10,Sales!$G$12:$V$45,1,FALSE) -> #N/A
A11: 469BC04260090001 | B11: -2164595 | C11: =VLOOKUP(A11,Sales!$G$12:$V$45,1,FALSE) -> #N/A
A12: 469BC04260090002 | B12: -3422672 | C12: =VLOOKUP(A12,Sales!$G$12:$V$45,1,FALSE) -> #N/A
A13: 469BC04260150002 | B13: -2409160 | C13: =VLOOKUP(A13,Sales!$G$12:$V$45,1,FALSE) -> #N/A
A14: 469BC04260150003 | B14: -2592392 | C14: =VLOOKUP(A14,Sales!$G$12:$V$45,1,FALSE) -> #N/A
A15: 469BC04260150005 | B15: -2617891 | C15: =VLOOKUP(A15,Sales!$G$12:$V$45,1,FALSE) -> #N/A
... A96: 469LC03261070002 | B96: -13264.38 | C96: =VLOOKUP(A96,Sales!$G$12:$V$45,1,FALSE) -> #N/A
A97: Grand Total | B97: 3.0363347e+08

Sheet Sheet3
A1: Description | B1: Amount | C1: C.D.Falg | D1: Reference No | E1: Value Date | F1: Branch Name | G1: Net Amount | H1: LC Bank Description.1 | I1: Type | J1: Month
A2: CORRESPONDENT BANK CHARGES | B2: 12964.66 | C2: D | D2: 469BC89253450002 | E2: 46026 | F2: BHOWANIPORE | G2: -12964.66 | H2: CORRESPONDENT BANK CHARGES | I2: Sales | J2: 46138 | K2: =VLOOKUP(D2,Sales!$G$3:$G$45,1,FALSE) -> #N/A | M2: =VLOOKUP(D2,Charges!$D$8:$D$25,1,FALSE) -> #N/A | O2: =VLOOKUP(D2,Retirement!$F$12:$F$79,1,FALSE) -> 469BC89253450002 | Q2: 469BC89253450002
A3: CORRESPONDENT BANK CHARGES | B3: 12964.66 | C3: D | D3: 469BC89253430003 | E3: 46026 | F3: BHOWANIPORE | G3: -12964.66 | H3: CORRESPONDENT BANK CHARGES | I3: Sales | J3: 46138 | K3: =VLOOKUP(D3,Sales!$G$3:$G$45,1,FALSE) -> #N/A | M3: =VLOOKUP(D3,Charges!$D$8:$D$25,1,FALSE) -> #N/A | O3: =VLOOKUP(D3,Retirement!$F$12:$F$79,1,FALSE) -> 469BC89253430003 | Q3: 469BC89253430003
A4: CORRESPONDENT BANK CHARGES | B4: 12964.66 | C4: D | D4: 469BC89253390002 | E4: 46026 | F4: BHOWANIPORE | G4: -12964.66 | H4: CORRESPONDENT BANK CHARGES | I4: Sales | J4: 46138 | K4: =VLOOKUP(D4,Sales!$G$3:$G$45,1,FALSE) -> #N/A | M4: =VLOOKUP(D4,Charges!$D$8:$D$25,1,FALSE) -> #N/A | O4: =VLOOKUP(D4,Retirement!$F$12:$F$79,1,FALSE) -> 469BC89253390002 | Q4: 469BC89253390002
A5: CORRESPONDENT BANK CHARGES | B5: 12964.66 | C5: D | D5: 469BC89253390001 | E5: 46026 | F5: BHOWANIPORE | G5: -12964.66 | H5: CORRESPONDENT BANK CHARGES | I5: Sales | J5: 46138 | K5: =VLOOKUP(D5,Sales!$G$3:$G$45,1,FALSE) -> #N/A | M5: =VLOOKUP(D5,Charges!$D$8:$D$25,1,FALSE) -> #N/A | O5: =VLOOKUP(D5,Retirement!$F$12:$F$79,1,FALSE) -> 469BC89253390001 | Q5: 469BC89253390001
A6: CORRESPONDENT BANK CHARGES | B6: 12964.66 | C6: D | D6: 469BC89253430007 | E6: 46026 | F6: BHOWANIPORE | G6: -12964.66 | H6: CORRESPONDENT BANK CHARGES | I6: Sales | J6: 46138 | K6: =VLOOKUP(D6,Sales!$G$3:$G$45,1,FALSE) -> #N/A | M6: =VLOOKUP(D6,Charges!$D$8:$D$25,1,FALSE) -> #N/A | O6: =VLOOKUP(D6,Retirement!$F$12:$F$79,1,FALSE) -> 469BC89253430007 | Q6: 469BC89253430007
A7: CORRESPONDENT BANK CHARGES | B7: 12964.66 | C7: D | D7: 469BC89260350001 | E7: 46026 | F7: BHOWANIPORE | G7: -12964.66 | H7: CORRESPONDENT BANK CHARGES | I7: Sales | J7: 46138 | K7: =VLOOKUP(D7,Sales!$G$3:$G$45,1,FALSE) -> #N/A | M7: =VLOOKUP(D7,Charges!$D$8:$D$25,1,FALSE) -> #N/A | O7: =VLOOKUP(D7,Retirement!$F$12:$F$79,1,FALSE) -> 469BC89260350001 | Q7: 469BC89260350001
A8: CORRESPONDENT BANK CHARGES | B8: 15381.8 | C8: D | D8: 469BC89253460001 | E8: 46026 | F8: BHOWANIPORE | G8: -15381.8 | H8: CORRESPONDENT BANK CHARGES | I8: Sales | J8: 46138 | K8: =VLOOKUP(D8,Sales!$G$3:$G$45,1,FALSE) -> #N/A | M8: =VLOOKUP(D8,Charges!$D$8:$D$25,1,FALSE) -> #N/A | O8: =VLOOKUP(D8,Retirement!$F$12:$F$79,1,FALSE) -> 469BC89253460001 | Q8: 469BC89253460001
A9: GST ON COMMISSION AND CHARGE | B9: 45 | C9: D | D9: 469BC89253450002 | E9: 46057 | F9: BHOWANIPORE | G9: -45 | H9: GST ON COMMISSION AND CHARGE | I9: GST | J9: 46138 | K9: =VLOOKUP(D9,Sales!$G$3:$G$45,1,FALSE) -> #N/A | M9: =VLOOKUP(D9,Charges!$D$8:$D$25,1,FALSE) -> #N/A | O9: =VLOOKUP(D9,Retirement!$F$12:$F$79,1,FALSE) -> 469BC89253450002 | Q9: 469BC89253450002
A10: GST ON COMMISSION AND CHARGE | B10: 45 | C10: D | D10: 469BC89253390002 | E10: 46057 | F10: BHOWANIPORE | G10: -45 | H10: GST ON COMMISSION AND CHARGE | I10: GST | J10: 46138 | K10: =VLOOKUP(D10,Sales!$G$3:$G$45,1,FALSE) -> #N/A | M10: =VLOOKUP(D10,Charges!$D$8:$D$25,1,FALSE) -> #N/A | O10: =VLOOKUP(D10,Retirement!$F$12:$F$79,1,FALSE) -> 469BC89253390002 | Q10: 469BC89253390002
A11: GST ON COMMISSION AND CHARGE | B11: 45 | C11: D | D11: 469BC89253390001 | E11: 46057 | F11: BHOWANIPORE | G11: -45 | H11: GST ON COMMISSION AND CHARGE | I11: GST | J11: 46138 | K11: =VLOOKUP(D11,Sales!$G$3:$G$45,1,FALSE) -> #N/A | M11: =VLOOKUP(D11,Charges!$D$8:$D$25,1,FALSE) -> #N/A | O11: =VLOOKUP(D11,Retirement!$F$12:$F$79,1,FALSE) -> 469BC89253390001 | Q11: 469BC89253390001
A12: LC ADVISING COMMISSION | B12: 1770 | C12: D | D12: 014LCEX260910002 | E12: 46057 | F12: CENTRALPLAZA-KOLKATA | G12: -1770 | H12: LC ADVISING COMMISSION | I12: Issuance | J12: 46138 | K12: =VLOOKUP(D12,Sales!$G$3:$G$45,1,FALSE) -> #N/A | M12: =VLOOKUP(D12,Charges!$D$8:$D$25,1,FALSE) -> 014LCEX260910002 | O12: =VLOOKUP(D12,Retirement!$F$12:$F$79,1,FALSE) -> #N/A | Q12: 014LCEX260910002
A13: LC ADVISING COMMISSION | B13: 1770 | C13: D | D13: 014LCEX260920001 | E13: 46057 | F13: CENTRALPLAZA-KOLKATA | G13: -1770 | H13: LC ADVISING COMMISSION | I13: Issuance | J13: 46138 | K13: =VLOOKUP(D13,Sales!$G$3:$G$45,1,FALSE) -> #N/A | M13: =VLOOKUP(D13,Charges!$D$8:$D$25,1,FALSE) -> 014LCEX260920001 | O13: =VLOOKUP(D13,Retirement!$F$12:$F$79,1,FALSE) -> #N/A | Q13: 014LCEX260920001
... A16: LIQUIDATION OF LOCAL BILL UNDER LC | B16: 3422672 | C16: D | D16: 469BC04260090002 | E16: 46057 | F16: BHOWANIPORE | G16: -3422672 | H16: LIQUIDATION OF LOCAL BILL UNDER LC | I16: Sales | J16: 46138 | K16: =VLOOKUP(D16,Sales!$G$3:$G$45,1,FALSE) -> #N/A | M16: =VLOOKUP(D16,Charges!$D$8:$D$25,1,FALSE) -> #N/A | O16: =VLOOKUP(D16,Retirement!$F$12:$F$79,1,FALSE) -> 469BC04260090002 | Q16: 469BC04260090002
A17: BILLS DISCOUNTED | B17: 16469530 | C17: C | D17: 469BC89260890006 | E17: 46057 | F17: BHOWANIPORE | G17: 16469530 | H17: BILLS DISCOUNTED | I17: Sales | J17: 46138 | K17: =VLOOKUP(D17,Sales!$G$3:$G$45,1,FALSE) -> 469BC89260890006 | L17: =VLOOKUP(D17,Sales!$G$3:$X60,18,FALSE) -> 137791.86 | M17: =VLOOKUP(D17,Charges!$D$8:$D$25,1,FALSE) -> #N/A | O17: =VLOOKUP(D17,Retirement!$F$12:$F$79,1,FALSE) -> #N/A | Q17: 469BC89260890006
A18: GST ON COMMISSION AND CHARGE | B18: 45 | C18: D | D18: 469BC89253430007 | E18: 46057 | F18: BHOWANIPORE | G18: -45 | H18: GST ON COMMISSION AND CHARGE | I18: GST | J18: 46138 | K18: =VLOOKUP(D18,Sales!$G$3:$G$45,1,FALSE) -> #N/A | M18: =VLOOKUP(D18,Charges!$D$8:$D$25,1,FALSE) -> #N/A | O18: =VLOOKUP(D18,Retirement!$F$12:$F$79,1,FALSE) -> 469BC89253430007 | Q18: 469BC89253430007
A19: GST ON COMMISSION AND CHARGE | B19: 45 | C19: D | D19: 469BC89253460001 | E19: 46057 | F19: BHOWANIPORE | G19: -45 | H19: GST ON COMMISSION AND CHARGE | I19: GST | J19: 46138 | K19: =VLOOKUP(D19,Sales!$G$3:$G$45,1,FALSE) -> #N/A | M19: =VLOOKUP(D19,Charges!$D$8:$D$25,1,FALSE) -> #N/A | O19: =VLOOKUP(D19,Retirement!$F$12:$F$79,1,FALSE) -> 469BC89253460001 | Q19: 469BC89253460001
A20: GST ON COMMISSION AND CHARGE | B20: 45 | C20: D | D20: 469BC89260350001 | E20: 46057 | F20: BHOWANIPORE | G20: -45 | H20: GST ON COMMISSION AND CHARGE | I20: GST | J20: 46138 | K20: =VLOOKUP(D20,Sales!$G$3:$G$45,1,FALSE) -> #N/A | M20: =VLOOKUP(D20,Charges!$D$8:$D$25,1,FALSE) -> #N/A | O20: =VLOOKUP(D20,Retirement!$F$12:$F$79,1,FALSE) -> 469BC89260350001 | Q20: 469BC89260350001
A21: LC ADVISING COMMISSION | B21: 1770 | C21: D | D21: 014LCEX260920018 | E21: 46116 | F21: CENTRALPLAZA-KOLKATA | G21: -1770 | H21: LC ADVISING COMMISSION | I21: Issuance | J21: 46138 | K21: =VLOOKUP(D21,Sales!$G$3:$G$45,1,FALSE) -> #N/A | M21: =VLOOKUP(D21,Charges!$D$8:$D$25,1,FALSE) -> 014LCEX260920018 | O21: =VLOOKUP(D21,Retirement!$F$12:$F$79,1,FALSE) -> #N/A | Q21: 014LCEX260920018
A22: COMM ON EXPORT LC AMENDMENT ADVISED | B22: 1180 | C22: D | D22: 014LCEX253590021 | E22: 46116 | F22: CENTRALPLAZA-KOLKATA | G22: -1180 | H22: COMM ON EXPORT LC AMENDMENT ADVISED | I22: Amendment | J22: 46138 | K22: =VLOOKUP(D22,Sales!$G$3:$G$45,1,FALSE) -> #N/A | M22: =VLOOKUP(D22,Charges!$D$8:$D$25,1,FALSE) -> 014LCEX253590021 | O22: =VLOOKUP(D22,Retirement!$F$12:$F$79,1,FALSE) -> #N/A | Q22: 014LCEX253590021
A23: LIQUIDATION OF LOCAL BILL UNDER LC | B23: 2164595 | C23: D | D23: 469BC04260090001 | E23: 46116 | F23: BHOWANIPORE | G23: -2164595 | H23: LIQUIDATION OF LOCAL BILL UNDER LC | I23: Sales | J23: 46138 | K23: =VLOOKUP(D23,Sales!$G$3:$G$45,1,FALSE) -> #N/A | M23: =VLOOKUP(D23,Charges!$D$8:$D$25,1,FALSE) -> #N/A | O23: =VLOOKUP(D23,Retirement!$F$12:$F$79,1,FALSE) -> 469BC04260090001 | Q23: 469BC04260090001
A24: BILLS DISCOUNTED | B24: 29114794 | C24: C | D24: 469BC89260860007 | E24: 46177 | F24: BHOWANIPORE | G24: 29114794 | H24: BILLS DISCOUNTED | I24: Sales | J24: 46138 | K24: =VLOOKUP(D24,Sales!$G$3:$G$45,1,FALSE) -> 469BC89260860007 | L24: =VLOOKUP(D24,Sales!$G$3:$X67,18,FALSE) -> 351388.21 | M24: =VLOOKUP(D24,Charges!$D$8:$D$25,1,FALSE) -> #N/A | O24: =VLOOKUP(D24,Retirement!$F$12:$F$79,1,FALSE) -> #N/A | Q24: 469BC89260860007
A25: COMM ON EXPORT COLL BILL | B25: 2360 | C25: D | D25: 469BC73260940004 | E25: 46177 | F25: BHOWANIPORE | G25: -2360 | H25: COMM ON EXPORT COLL BILL | I25: Sales | J25: 46138 | K25: =VLOOKUP(D25,Sales!$G$3:$G$45,1,FALSE) -> #N/A | M25: =VLOOKUP(D25,Charges!$D$8:$D$25,1,FALSE) -> #N/A | O25: =VLOOKUP(D25,Retirement!$F$12:$F$79,1,FALSE) -> 469BC73260940004 | Q25: 469BC73260940004
A26: LIQUIDATION OF LOCAL BILL UNDER LC | B26: 2409160 | C26: D | D26: 469BC04260150002 | E26: 46177 | F26: BHOWANIPORE | G26: -2409160 | H26: LIQUIDATION OF LOCAL BILL UNDER LC | I26: Sales | J26: 46138 | K26: =VLOOKUP(D26,Sales!$G$3:$G$45,1,FALSE) -> #N/A | M26: =VLOOKUP(D26,Charges!$D$8:$D$25,1,FALSE) -> #N/A | O26: =VLOOKUP(D26,Retirement!$F$12:$F$79,1,FALSE) -> 469BC04260150002 | Q26: 469BC04260150002
A27: INTEREST ON LOCAL BILL DISCOUNTING | B27: 41645.14 | C27: C | D27: 469BC89260090006 | E27: 46207 | F27: BHOWANIPORE | G27: 41645.14 | H27: INTEREST ON LOCAL BILL DISCOUNTING | I27: Sales | J27: 46138 | K27: =VLOOKUP(D27,Sales!$G$3:$G$45,1,FALSE) -> #N/A | M27: =VLOOKUP(D27,Charges!$D$8:$D$25,1,FALSE) -> #N/A | O27: =VLOOKUP(D27,Retirement!$F$12:$F$79,1,FALSE) -> 469BC89260090006 | T27: =G27 -> 41645.14
A28: CORRESPONDENT BANK CHARGES | B28: 7205.9 | C28: D | D28: 469BC89260090006 | E28: 46207 | F28: BHOWANIPORE | G28: -7205.9 | H28: CORRESPONDENT BANK CHARGES | I28: Sales | J28: 46138 | K28: =VLOOKUP(D28,Sales!$G$3:$G$45,1,FALSE) -> #N/A | M28: =VLOOKUP(D28,Charges!$D$8:$D$25,1,FALSE) -> #N/A | O28: =VLOOKUP(D28,Retirement!$F$12:$F$79,1,FALSE) -> 469BC89260090006
A29: CORRESPONDENT BANK CHARGES | B29: 25497.8 | C29: D | D29: 469BC89260500003 | E29: 46207 | F29: BHOWANIPORE | G29: -25497.8 | H29: CORRESPONDENT BANK CHARGES | I29: Sales | J29: 46138 | K29: =VLOOKUP(D29,Sales!$G$3:$G$45,1,FALSE) -> #N/A | M29: =VLOOKUP(D29,Charges!$D$8:$D$25,1,FALSE) -> #N/A | O29: =VLOOKUP(D29,Retirement!$F$12:$F$79,1,FALSE) -> 469BC89260500003 | Q29: 469BC89260500003
A30: COMM ON EXPORT COLL BILL | B30: 2360 | C30: D | D30: 469BC73260970007 | E30: 46207 | F30: BHOWANIPORE | G30: -2360 | H30: COMM ON EXPORT COLL BILL | I30: Sales | J30: 46138 | K30: =VLOOKUP(D30,Sales!$G$3:$G$45,1,FALSE) -> #N/A | M30: =VLOOKUP(D30,Charges!$D$8:$D$25,1,FALSE) -> #N/A | O30: =VLOOKUP(D30,Retirement!$F$12:$F$79,1,FALSE) -> 469BC73260970007 | Q30: 469BC73260970007
A31: LIQUIDATION OF LOCAL BILL UNDER LC | B31: 2592392 | C31: D | D31: 469BC04260150003 | E31: 46207 | F31: BHOWANIPORE | G31: -2592392 | H31: LIQUIDATION OF LOCAL BILL UNDER LC | I31: Sales | J31: 46138 | K31: =VLOOKUP(D31,Sales!$G$3:$G$45,1,FALSE) -> #N/A | M31: =VLOOKUP(D31,Charges!$D$8:$D$25,1,FALSE) -> #N/A | O31: =VLOOKUP(D31,Retirement!$F$12:$F$79,1,FALSE) -> 469BC04260150003 | Q31: 469BC04260150003
A32: GST ON COMMISSION AND CHARGE | B32: 45 | C32: D | D32: 469BC89260500003 | E32: 46238 | F32: BHOWANIPORE | G32: -45 | H32: GST ON COMMISSION AND CHARGE | I32: GST | J32: 46138 | K32: =VLOOKUP(D32,Sales!$G$3:$G$45,1,FALSE) -> #N/A | M32: =VLOOKUP(D32,Charges!$D$8:$D$25,1,FALSE) -> #N/A | O32: =VLOOKUP(D32,Retirement!$F$12:$F$79,1,FALSE) -> 469BC89260500003 | Q32: 469BC89260500003
A33: GST ON COMMISSION AND CHARGE | B33: 45 | C33: D | D33: 469BC89260090006 | E33: 46238 | F33: BHOWANIPORE | G33: -45 | H33: GST ON COMMISSION AND CHARGE | I33: GST | J33: 46138 | K33: =VLOOKUP(D33,Sales!$G$3:$G$45,1,FALSE) -> #N/A | M33: =VLOOKUP(D33,Charges!$D$8:$D$25,1,FALSE) -> #N/A | O33: =VLOOKUP(D33,Retirement!$F$12:$F$79,1,FALSE) -> 469BC89260090006
A34: LIQUIDATION OF LOCAL BILL UNDER LC | B34: 7619134 | C34: D | D34: 469BC04260150013 | E34: 46238 | F34: BHOWANIPORE | G34: -7619134 | H34: LIQUIDATION OF LOCAL BILL UNDER LC | I34: Sales | J34: 46138 | K34: =VLOOKUP(D34,Sales!$G$3:$G$45,1,FALSE) -> #N/A | M34: =VLOOKUP(D34,Charges!$D$8:$D$25,1,FALSE) -> #N/A | O34: =VLOOKUP(D34,Retirement!$F$12:$F$79,1,FALSE) -> 469BC04260150013
A35: LIQUIDATION OF LOCAL BILL UNDER LC | B35: 10202035 | C35: D | D35: 469BC04260190010 | E35: 46269 | F35: BHOWANIPORE | G35: -10202035 | H35: LIQUIDATION OF LOCAL BILL UNDER LC | I35: Sales | J35: 46138 | K35: =VLOOKUP(D35,Sales!$G$3:$G$45,1,FALSE) -> #N/A | M35: =VLOOKUP(D35,Charges!$D$8:$D$25,1,FALSE) -> #N/A | O35: =VLOOKUP(D35,Retirement!$F$12:$F$79,1,FALSE) -> 469BC04260190010 | Q35: 469BC04260190010
A36: COMM ON EXPORT COLL BILL | B36: 2360 | C36: D | D36: 469BC63260990003 | E36: 46269 | F36: BHOWANIPORE | G36: -2360 | H36: COMM ON EXPORT COLL BILL | I36: Sales | J36: 46138 | K36: =VLOOKUP(D36,Sales!$G$3:$G$45,1,FALSE) -> #N/A | M36: =VLOOKUP(D36,Charges!$D$8:$D$25,1,FALSE) -> #N/A | O36: =VLOOKUP(D36,Retirement!$F$12:$F$79,1,FALSE) -> 469BC63260990003 | Q36: 469BC63260990003
A37: COMM ON EXPORT COLL BILL | B37: 2360 | C37: D | D37: 469BC73260990003 | E37: 46269 | F37: BHOWANIPORE | G37: -2360 | H37: COMM ON EXPORT COLL BILL | I37: Sales | J37: 46138 | K37: =VLOOKUP(D37,Sales!$G$3:$G$45,1,FALSE) -> #N/A | M37: =VLOOKUP(D37,Charges!$D$8:$D$25,1,FALSE) -> #N/A | O37: =VLOOKUP(D37,Retirement!$F$12:$F$79,1,FALSE) -> 469BC73260990003 | Q37: 469BC73260990003
A38: COMM ON EXPORT COLL BILL | B38: 2360 | C38: D | D38: 469BC63260990002 | E38: 46269 | F38: BHOWANIPORE | G38: -2360 | H38: COMM ON EXPORT COLL BILL | I38: Sales | J38: 46138 | K38: =VLOOKUP(D38,Sales!$G$3:$G$45,1,FALSE) -> #N/A | M38: =VLOOKUP(D38,Charges!$D$8:$D$25,1,FALSE) -> #N/A | O38: =VLOOKUP(D38,Retirement!$F$12:$F$79,1,FALSE) -> 469BC63260990002 | Q38: 469BC63260990002
A39: LIQUIDATION OF LOCAL BILL UNDER LC | B39: 2617891 | C39: D | D39: 469BC04260150005 | E39: 46299 | F39: BHOWANIPORE | G39: -2617891 | H39: LIQUIDATION OF LOCAL BILL UNDER LC | I39: Sales | J39: 46138 | K39: =VLOOKUP(D39,Sales!$G$3:$G$45,1,FALSE) -> #N/A | M39: =VLOOKUP(D39,Charges!$D$8:$D$25,1,FALSE) -> #N/A | O39: =VLOOKUP(D39,Retirement!$F$12:$F$79,1,FALSE) -> 469BC04260150005 | Q39: 469BC04260150005
A40: LIQUIDATION OF LOCAL BILL UNDER LC | B40: 14435766 | C40: D | D40: 469BC04260150007 | E40: 46299 | F40: BHOWANIPORE | G40: -14435766 | H40: LIQUIDATION OF LOCAL BILL UNDER LC | I40: Sales | J40: 46138 | K40: =VLOOKUP(D40,Sales!$G$3:$G$45,1,FALSE) -> #N/A | M40: =VLOOKUP(D40,Charges!$D$8:$D$25,1,FALSE) -> #N/A | O40: =VLOOKUP(D40,Retirement!$F$12:$F$79,1,FALSE) -> 469BC04260150007 | Q40: 469BC04260150007
A41: LIQUIDATION OF LOCAL BILL UNDER LC | B41: 1996972 | C41: D | D41: 469BC04260150009 | E41: 46299 | F41: BHOWANIPORE | G41: -1996972 | H41: LIQUIDATION OF LOCAL BILL UNDER LC | I41: Sales | J41: 46138 | K41: =VLOOKUP(D41,Sales!$G$3:$G$45,1,FALSE) -> #N/A | M41: =VLOOKUP(D41,Charges!$D$8:$D$25,1,FALSE) -> #N/A | O41: =VLOOKUP(D41,Retirement!$F$12:$F$79,1,FALSE) -> 469BC04260150009 | Q41: 469BC04260150009
A42: LIQUIDATION OF LOCAL BILL UNDER LC | B42: 5137822 | C42: D | D42: 469BC04260150011 | E42: 46299 | F42: BHOWANIPORE | G42: -5137822 | H42: LIQUIDATION OF LOCAL BILL UNDER LC | I42: Sales | J42: 46138 | K42: =VLOOKUP(D42,Sales!$G$3:$G$45,1,FALSE) -> #N/A | M42: =VLOOKUP(D42,Charges!$D$8:$D$25,1,FALSE) -> #N/A | O42: =VLOOKUP(D42,Retirement!$F$12:$F$79,1,FALSE) -> 469BC04260150011 | Q42: 469BC04260150011
A43: COURIER CHARGES ON EXPORT BILLS | B43: 5310 | C43: D | D43: 469BC89261030010 | E43: 13/04/2026 | F43: BHOWANIPORE | G43: -5310 | H43: COURIER CHARGES ON EXPORT BILLS | I43: Issuance | J43: 46138 | K43: =VLOOKUP(D43,Sales!$G$3:$G$45,1,FALSE) -> 469BC89261030010 | L43: =VLOOKUP(D43,Sales!$G$3:$X86,18,FALSE) -> 67942.58 | M43: =VLOOKUP(D43,Charges!$D$8:$D$25,1,FALSE) -> #N/A | O43: =VLOOKUP(D43,Retirement!$F$12:$F$79,1,FALSE) -> #N/A | Q43: 469BC89261030010
A44: COURIER CHARGES ON EXPORT BILLS | B44: 5310 | C44: D | D44: 469BC89261030011 | E44: 13/04/2026 | F44: BHOWANIPORE | G44: -5310 | H44: COURIER CHARGES ON EXPORT BILLS | I44: Issuance | J44: 46138 | K44: =VLOOKUP(D44,Sales!$G$3:$G$45,1,FALSE) -> 469BC89261030011 | L44: =VLOOKUP(D44,Sales!$G$3:$X87,18,FALSE) -> 166407.02 | M44: =VLOOKUP(D44,Charges!$D$8:$D$25,1,FALSE) -> #N/A | O44: =VLOOKUP(D44,Retirement!$F$12:$F$79,1,FALSE) -> #N/A | Q44: 469BC89261030011
A45: COURIER CHARGES ON EXPORT BILLS | B45: 5310 | C45: D | D45: 469BC89261030007 | E45: 13/04/2026 | F45: BHOWANIPORE | G45: -5310 | H45: COURIER CHARGES ON EXPORT BILLS | I45: Issuance | J45: 46138 | K45: =VLOOKUP(D45,Sales!$G$3:$G$45,1,FALSE) -> 469BC89261030007 | L45: =VLOOKUP(D45,Sales!$G$3:$X88,18,FALSE) -> 67407.5 | M45: =VLOOKUP(D45,Charges!$D$8:$D$25,1,FALSE) -> #N/A | O45: =VLOOKUP(D45,Retirement!$F$12:$F$79,1,FALSE) -> #N/A | Q45: 469BC89261030007
A46: BILLS DISCOUNTED | B46: 2112211.9 | C46: C | D46: 469BC89261030003 | E46: 13/04/2026 | F46: BHOWANIPORE | G46: 2112211.9 | H46: BILLS DISCOUNTED | I46: Sales | J46: 46138 | K46: =VLOOKUP(D46,Sales!$G$3:$G$45,1,FALSE) -> 469BC89261030003 | L46: =VLOOKUP(D46,Sales!$G$3:$X89,18,FALSE) -> 16727.49 | M46: =VLOOKUP(D46,Charges!$D$8:$D$25,1,FALSE) -> #N/A | O46: =VLOOKUP(D46,Retirement!$F$12:$F$79,1,FALSE) -> #N/A | Q46: 469BC89261030003
A47: CORRESPONDENT BANK CHARGES | B47: 5656.5 | C47: D | D47: 469BC89260470003 | E47: 13/04/2026 | F47: BHOWANIPORE | G47: -5656.5 | H47: CORRESPONDENT BANK CHARGES | I47: Sales | J47: 46138 | K47: =VLOOKUP(D47,Sales!$G$3:$G$45,1,FALSE) -> #N/A | M47: =VLOOKUP(D47,Charges!$D$8:$D$25,1,FALSE) -> #N/A | O47: =VLOOKUP(D47,Retirement!$F$12:$F$79,1,FALSE) -> 469BC89260470003 | Q47: 469BC89260470003
A48: CORRESPONDENT BANK CHARGES | B48: 5656.5 | C48: D | D48: 469BC89260470004 | E48: 13/04/2026 | F48: BHOWANIPORE | G48: -5656.5 | H48: CORRESPONDENT BANK CHARGES | I48: Sales | J48: 46138 | K48: =VLOOKUP(D48,Sales!$G$3:$G$45,1,FALSE) -> #N/A | M48: =VLOOKUP(D48,Charges!$D$8:$D$25,1,FALSE) -> #N/A | O48: =VLOOKUP(D48,Retirement!$F$12:$F$79,1,FALSE) -> 469BC89260470004
A49: BILLS DISCOUNTED | B49: 2262884 | C49: C | D49: 469BC89261030001 | E49: 13/04/2026 | F49: BHOWANIPORE | G49: 2262884 | H49: BILLS DISCOUNTED | I49: Sales | J49: 46138 | K49: =VLOOKUP(D49,Sales!$G$3:$G$45,1,FALSE) -> 469BC89261030001 | L49: =VLOOKUP(D49,Sales!$G$3:$X92,18,FALSE) -> 16894.2 | M49: =VLOOKUP(D49,Charges!$D$8:$D$25,1,FALSE) -> #N/A | O49: =VLOOKUP(D49,Retirement!$F$12:$F$79,1,FALSE) -> #N/A | Q49: 469BC89261030001
A50: LIQUIDATION OF LOCAL BILL UNDER LC | B50: 7204547 | C50: D | D50: 469BC04260200003 | E50: 13/04/2026 | F50: BHOWANIPORE | G50: -7204547 | H50: LIQUIDATION OF LOCAL BILL UNDER LC | I50: Sales | J50: 46138 | K50: =VLOOKUP(D50,Sales!$G$3:$G$45,1,FALSE) -> #N/A | M50: =VLOOKUP(D50,Charges!$D$8:$D$25,1,FALSE) -> #N/A | O50: =VLOOKUP(D50,Retirement!$F$12:$F$79,1,FALSE) -> 469BC04260200003 | Q50: 469BC04260200003
A51: INTEREST ON EXPORT BILL PURCHASE | B51: 10245.7 | C51: D | D51: 469BC89253540002 | E51: 13/04/2026 | F51: BHOWANIPORE | G51: -10245.7 | H51: INTEREST ON EXPORT BILL PURCHASE | I51: Issuance | J51: 46138 | K51: =VLOOKUP(D51,Sales!$G$3:$G$45,1,FALSE) -> #N/A | M51: =VLOOKUP(D51,Charges!$D$8:$D$25,1,FALSE) -> #N/A | O51: =VLOOKUP(D51,Retirement!$F$12:$F$79,1,FALSE) -> 469BC89253540002
A52: COURIER CHARGES ON EXPORT BILLS | B52: 5310 | C52: D | D52: 469BC89261030003 | E52: 13/04/2026 | F52: BHOWANIPORE | G52: -5310 | H52: COURIER CHARGES ON EXPORT BILLS | I52: Issuance | J52: 46138 | K52: =VLOOKUP(D52,Sales!$G$3:$G$45,1,FALSE) -> 469BC89261030003 | L52: =VLOOKUP(D52,Sales!$G$3:$X95,18,FALSE) -> 16727.49 | M52: =VLOOKUP(D52,Charges!$D$8:$D$25,1,FALSE) -> #N/A | O52: =VLOOKUP(D52,Retirement!$F$12:$F$79,1,FALSE) -> #N/A | Q52: 469BC89261030003
A53: COURIER CHARGES ON EXPORT BILLS | B53: 5310 | C53: D | D53: 469BC89261030001 | E53: 13/04/2026 | F53: BHOWANIPORE | G53: -5310 | H53: COURIER CHARGES ON EXPORT BILLS | I53: Issuance | J53: 46138 | K53: =VLOOKUP(D53,Sales!$G$3:$G$45,1,FALSE) -> 469BC89261030001 | L53: =VLOOKUP(D53,Sales!$G$3:$X96,18,FALSE) -> 16894.2 | M53: =VLOOKUP(D53,Charges!$D$8:$D$25,1,FALSE) -> #N/A | O53: =VLOOKUP(D53,Retirement!$F$12:$F$79,1,FALSE) -> #N/A | Q53: 469BC89261030001
A54: LC ADVISING COMMISSION | B54: 1770 | C54: D | D54: 014LCEX261010002 | E54: 13/04/2026 | F54: CENTRALPLAZA-KOLKATA | G54: -1770 | H54: LC ADVISING COMMISSION | I54: Issuance | J54: 46138 | K54: =VLOOKUP(D54,Sales!$G$3:$G$45,1,FALSE) -> #N/A | M54: =VLOOKUP(D54,Charges!$D$8:$D$25,1,FALSE) -> 014LCEX261010002 | O54: =VLOOKUP(D54,Retirement!$F$12:$F$79,1,FALSE) -> #N/A | Q54: 014LCEX261010002
A55: LIQUIDATION OF LOCAL BILL UNDER LC | B55: 1978624 | C55: D | D55: 469BC04260170003 | E55: 13/04/2026 | F55: BHOWANIPORE | G55: -1978624 | H55: LIQUIDATION OF LOCAL BILL UNDER LC | I55: Sales | J55: 46138 | K55: =VLOOKUP(D55,Sales!$G$3:$G$45,1,FALSE) -> #N/A | M55: =VLOOKUP(D55,Charges!$D$8:$D$25,1,FALSE) -> #N/A | O55: =VLOOKUP(D55,Retirement!$F$12:$F$79,1,FALSE) -> 469BC04260170003 | Q55: 469BC04260170003
A56: LIQUIDATION OF LOCAL BILL UNDER LC | B56: 5015964 | C56: D | D56: 469BC04260200005 | E56: 13/04/2026 | F56: BHOWANIPORE | G56: -5015964 | H56: LIQUIDATION OF LOCAL BILL UNDER LC | I56: Sales | J56: 46138 | K56: =VLOOKUP(D56,Sales!$G$3:$G$45,1,FALSE) -> #N/A | M56: =VLOOKUP(D56,Charges!$D$8:$D$25,1,FALSE) -> #N/A | O56: =VLOOKUP(D56,Retirement!$F$12:$F$79,1,FALSE) -> 469BC04260200005 | Q56: 469BC04260200005
A57: INTEREST ON EXPORT BILL PURCHASE | B57: 3590.12 | C57: D | D57: 469BC89253560001 | E57: 13/04/2026 | F57: BHOWANIPORE | G57: -3590.12 | H57: INTEREST ON EXPORT BILL PURCHASE | I57: Issuance | J57: 46138 | K57: =VLOOKUP(D57,Sales!$G$3:$G$45,1,FALSE) -> #N/A | M57: =VLOOKUP(D57,Charges!$D$8:$D$25,1,FALSE) -> #N/A | O57: =VLOOKUP(D57,Retirement!$F$12:$F$79,1,FALSE) -> 469BC89253560001 | Q57: 469BC89253560001
A58: CORRESPONDENT BANK CHARGES | B58: 18666.45 | C58: D | D58: 469BC89260190002 | E58: 14/04/2026 | F58: BHOWANIPORE | G58: -18666.45 | H58: CORRESPONDENT BANK CHARGES | I58: Sales | J58: 46138 | K58: =VLOOKUP(D58,Sales!$G$3:$G$45,1,FALSE) -> #N/A | M58: =VLOOKUP(D58,Charges!$D$8:$D$25,1,FALSE) -> #N/A | O58: =VLOOKUP(D58,Retirement!$F$12:$F$79,1,FALSE) -> 469BC89260190002 | Q58: 469BC89260190002
A59: CORRESPONDENT BANK CHARGES | B59: 15838.2 | C59: D | D59: 469BC89253560001 | E59: 14/04/2026 | F59: BHOWANIPORE | G59: -15838.2 | H59: CORRESPONDENT BANK CHARGES | I59: Sales | J59: 46138 | K59: =VLOOKUP(D59,Sales!$G$3:$G$45,1,FALSE) -> #N/A | M59: =VLOOKUP(D59,Charges!$D$8:$D$25,1,FALSE) -> #N/A | O59: =VLOOKUP(D59,Retirement!$F$12:$F$79,1,FALSE) -> 469BC89253560001 | Q59: 469BC89253560001
A60: CORRESPONDENT BANK CHARGES | B60: 3959.55 | C60: D | D60: 469BC89260220005 | E60: 15/04/2026 | F60: BHOWANIPORE | G60: -3959.55 | H60: CORRESPONDENT BANK CHARGES | I60: Sales | J60: 46138 | K60: =VLOOKUP(D60,Sales!$G$3:$G$45,1,FALSE) -> #N/A | M60: =VLOOKUP(D60,Charges!$D$8:$D$25,1,FALSE) -> #N/A | O60: =VLOOKUP(D60,Retirement!$F$12:$F$79,1,FALSE) -> 469BC89260220005 | Q60: 469BC89260220005
A61: LIQUIDATION OF LOCAL BILL UNDER LC | B61: 5014639 | C61: D | D61: 469BC04260210002 | E61: 16/04/2026 | F61: BHOWANIPORE | G61: -5014639 | H61: LIQUIDATION OF LOCAL BILL UNDER LC | I61: Sales | J61: 46138 | K61: =VLOOKUP(D61,Sales!$G$3:$G$45,1,FALSE) -> #N/A | M61: =VLOOKUP(D61,Charges!$D$8:$D$25,1,FALSE) -> #N/A | O61: =VLOOKUP(D61,Retirement!$F$12:$F$79,1,FALSE) -> 469BC04260210002 | Q61: 469BC04260210002
A62: GST ON COMMISSION AND CHARGE | B62: 45 | C62: D | D62: 469BC89260470004 | E62: 16/04/2026 | F62: BHOWANIPORE | G62: -45 | H62: GST ON COMMISSION AND CHARGE | I62: GST | J62: 46138 | K62: =VLOOKUP(D62,Sales!$G$3:$G$45,1,FALSE) -> #N/A | M62: =VLOOKUP(D62,Charges!$D$8:$D$25,1,FALSE) -> #N/A | O62: =VLOOKUP(D62,Retirement!$F$12:$F$79,1,FALSE) -> 469BC89260470004
A63: BILLS DISCOUNTED | B63: 44452780 | C63: C | D63: 469BC89261060003 | E63: 16/04/2026 | F63: BHOWANIPORE | G63: 44452780 | H63: BILLS DISCOUNTED | I63: Sales | J63: 46138 | K63: =VLOOKUP(D63,Sales!$G$3:$G$45,1,FALSE) -> 469BC89261060003 | M63: =VLOOKUP(D63,Charges!$D$8:$D$25,1,FALSE) -> #N/A | O63: =VLOOKUP(D63,Retirement!$F$12:$F$79,1,FALSE) -> #N/A | Q63: 469BC89261060003
A64: GST ON COMMISSION AND CHARGE | B64: 45 | C64: D | D64: 469BC89260220005 | E64: 16/04/2026 | F64: BHOWANIPORE | G64: -45 | H64: GST ON COMMISSION AND CHARGE | I64: GST | J64: 46138 | K64: =VLOOKUP(D64,Sales!$G$3:$G$45,1,FALSE) -> #N/A | M64: =VLOOKUP(D64,Charges!$D$8:$D$25,1,FALSE) -> #N/A | O64: =VLOOKUP(D64,Retirement!$F$12:$F$79,1,FALSE) -> 469BC89260220005 | Q64: 469BC89260220005
A65: INTEREST ON LOCAL BILL DISCOUNTING | B65: 12141.61 | C65: C | D65: 469BC89260560004 | E65: 16/04/2026 | F65: BHOWANIPORE | G65: 12141.61 | H65: INTEREST ON LOCAL BILL DISCOUNTING | I65: Sales | J65: 46138 | K65: =VLOOKUP(D65,Sales!$G$3:$G$45,1,FALSE) -> #N/A | M65: =VLOOKUP(D65,Charges!$D$8:$D$25,1,FALSE) -> #N/A | O65: =VLOOKUP(D65,Retirement!$F$12:$F$79,1,FALSE) -> 469BC89260560004
A66: CORRESPONDENT BANK CHARGES | B66: 11233 | C66: D | D66: 469BC89260510001 | E66: 16/04/2026 | F66: BHOWANIPORE | G66: -11233 | H66: CORRESPONDENT BANK CHARGES | I66: Sales | J66: 46138 | K66: =VLOOKUP(D66,Sales!$G$3:$G$45,1,FALSE) -> #N/A | M66: =VLOOKUP(D66,Charges!$D$8:$D$25,1,FALSE) -> #N/A | O66: =VLOOKUP(D66,Retirement!$F$12:$F$79,1,FALSE) -> 469BC89260510001
A67: GST ON COMMISSION AND CHARGE | B67: 45 | C67: D | D67: 469BC89253560001 | E67: 16/04/2026 | F67: BHOWANIPORE | G67: -45 | H67: GST ON COMMISSION AND CHARGE | I67: GST | J67: 46138 | K67: =VLOOKUP(D67,Sales!$G$3:$G$45,1,FALSE) -> #N/A | M67: =VLOOKUP(D67,Charges!$D$8:$D$25,1,FALSE) -> #N/A | O67: =VLOOKUP(D67,Retirement!$F$12:$F$79,1,FALSE) -> 469BC89253560001 | Q67: 469BC89253560001
A68: GST ON COMMISSION AND CHARGE | B68: 45 | C68: D | D68: 469BC89260470003 | E68: 16/04/2026 | F68: BHOWANIPORE | G68: -45 | H68: GST ON COMMISSION AND CHARGE | I68: GST | J68: 46138 | K68: =VLOOKUP(D68,Sales!$G$3:$G$45,1,FALSE) -> #N/A | M68: =VLOOKUP(D68,Charges!$D$8:$D$25,1,FALSE) -> #N/A | O68: =VLOOKUP(D68,Retirement!$F$12:$F$79,1,FALSE) -> 469BC89260470003 | Q68: 469BC89260470003
A69: GST ON COMMISSION AND CHARGE | B69: 45 | C69: D | D69: 469BC89260190002 | E69: 16/04/2026 | F69: BHOWANIPORE | G69: -45 | H69: GST ON COMMISSION AND CHARGE | I69: GST | J69: 46138 | K69: =VLOOKUP(D69,Sales!$G$3:$G$45,1,FALSE) -> #N/A | M69: =VLOOKUP(D69,Charges!$D$8:$D$25,1,FALSE) -> #N/A | O69: =VLOOKUP(D69,Retirement!$F$12:$F$79,1,FALSE) -> 469BC89260190002 | Q69: 469BC89260190002
A70: COURIER CHARGES ON EXPORT BILLS | B70: 5310 | C70: D | D70: 469BC89261060003 | E70: 16/04/2026 | F70: BHOWANIPORE | G70: -5310 | H70: COURIER CHARGES ON EXPORT BILLS | I70: Issuance | J70: 46138 | K70: =VLOOKUP(D70,Sales!$G$3:$G$45,1,FALSE) -> 469BC89261060003 | M70: =VLOOKUP(D70,Charges!$D$8:$D$25,1,FALSE) -> #N/A | O70: =VLOOKUP(D70,Retirement!$F$12:$F$79,1,FALSE) -> #N/A | Q70: 469BC89261060003
A71: BILLS DISCOUNTED | B71: 9041390.2 | C71: C | D71: 469BC89261030010 | E71: 16/04/2026 | F71: BHOWANIPORE | G71: 9041390.2 | H71: BILLS DISCOUNTED | I71: Sales | J71: 46138 | K71: =VLOOKUP(D71,Sales!$G$3:$G$45,1,FALSE) -> 469BC89261030010 | M71: =VLOOKUP(D71,Charges!$D$8:$D$25,1,FALSE) -> #N/A | O71: =VLOOKUP(D71,Retirement!$F$12:$F$79,1,FALSE) -> #N/A | Q71: 469BC89261030010
A72: COURIER CHARGES ON EXPORT BILLS | B72: 5310 | C72: D | D72: 469BC89261060002 | E72: 16/04/2026 | F72: BHOWANIPORE | G72: -5310 | H72: COURIER CHARGES ON EXPORT BILLS | I72: Issuance | J72: 46138 | K72: =VLOOKUP(D72,Sales!$G$3:$G$45,1,FALSE) -> 469BC89261060002 | M72: =VLOOKUP(D72,Charges!$D$8:$D$25,1,FALSE) -> #N/A | O72: =VLOOKUP(D72,Retirement!$F$12:$F$79,1,FALSE) -> #N/A | Q72: 469BC89261060002
A73: COURIER CHARGES ON EXPORT BILLS | B73: 5310 | C73: D | D73: 469BC89261060001 | E73: 16/04/2026 | F73: BHOWANIPORE | G73: -5310 | H73: COURIER CHARGES ON EXPORT BILLS | I73: Issuance | J73: 46138 | K73: =VLOOKUP(D73,Sales!$G$3:$G$45,1,FALSE) -> 469BC89261060001 | M73: =VLOOKUP(D73,Charges!$D$8:$D$25,1,FALSE) -> #N/A | O73: =VLOOKUP(D73,Retirement!$F$12:$F$79,1,FALSE) -> #N/A | Q73: 469BC89261060001
A74: LIQUIDATION OF LOCAL BILL UNDER LC | B74: 7344466 | C74: D | D74: 469BC04260210003 | E74: 16/04/2026 | F74: BHOWANIPORE | G74: -7344466 | H74: LIQUIDATION OF LOCAL BILL UNDER LC | I74: Sales | J74: 46138 | K74: =VLOOKUP(D74,Sales!$G$3:$G$45,1,FALSE) -> #N/A | M74: =VLOOKUP(D74,Charges!$D$8:$D$25,1,FALSE) -> #N/A | O74: =VLOOKUP(D74,Retirement!$F$12:$F$79,1,FALSE) -> 469BC04260210003 | Q74: 469BC04260210003
A75: BILLS DISCOUNTED | B75: 23158321 | C75: C | D75: 469BC89261060001 | E75: 16/04/2026 | F75: BHOWANIPORE | G75: 23158321 | H75: BILLS DISCOUNTED | I75: Sales | J75: 46138 | K75: =VLOOKUP(D75,Sales!$G$3:$G$45,1,FALSE) -> 469BC89261060001 | M75: =VLOOKUP(D75,Charges!$D$8:$D$25,1,FALSE) -> #N/A | O75: =VLOOKUP(D75,Retirement!$F$12:$F$79,1,FALSE) -> #N/A | Q75: 469BC89261060001
A76: BILLS DISCOUNTED | B76: 8554366.9 | C76: C | D76: 469BC89261060002 | E76: 16/04/2026 | F76: BHOWANIPORE | G76: 8554366.9 | H76: BILLS DISCOUNTED | I76: Sales | J76: 46138 | K76: =VLOOKUP(D76,Sales!$G$3:$G$45,1,FALSE) -> 469BC89261060002 | M76: =VLOOKUP(D76,Charges!$D$8:$D$25,1,FALSE) -> #N/A | O76: =VLOOKUP(D76,Retirement!$F$12:$F$79,1,FALSE) -> #N/A | Q76: 469BC89261060002
A77: BILLS DISCOUNTED | B77: 24550550 | C77: C | D77: 469BC89261030011 | E77: 16/04/2026 | F77: BHOWANIPORE | G77: 24550550 | H77: BILLS DISCOUNTED | I77: Sales | J77: 46138 | K77: =VLOOKUP(D77,Sales!$G$3:$G$45,1,FALSE) -> 469BC89261030011 | M77: =VLOOKUP(D77,Charges!$D$8:$D$25,1,FALSE) -> #N/A | O77: =VLOOKUP(D77,Retirement!$F$12:$F$79,1,FALSE) -> #N/A | Q77: 469BC89261030011
A78: BILLS DISCOUNTED | B78: 12281910 | C78: C | D78: 469BC89261030007 | E78: 16/04/2026 | F78: BHOWANIPORE | G78: 12281910 | H78: BILLS DISCOUNTED | I78: Sales | J78: 46138 | K78: =VLOOKUP(D78,Sales!$G$3:$G$45,1,FALSE) -> 469BC89261030007 | M78: =VLOOKUP(D78,Charges!$D$8:$D$25,1,FALSE) -> #N/A | O78: =VLOOKUP(D78,Retirement!$F$12:$F$79,1,FALSE) -> #N/A | Q78: 469BC89261030007
A79: GST ON COMMISSION AND CHARGE | B79: 45 | C79: D | D79: 469BC89260510001 | E79: 17/04/2026 | F79: BHOWANIPORE | G79: -45 | H79: GST ON COMMISSION AND CHARGE | I79: GST | J79: 46138 | K79: =VLOOKUP(D79,Sales!$G$3:$G$45,1,FALSE) -> #N/A | M79: =VLOOKUP(D79,Charges!$D$8:$D$25,1,FALSE) -> #N/A | O79: =VLOOKUP(D79,Retirement!$F$12:$F$79,1,FALSE) -> 469BC89260510001
A80: BILLS DISCOUNTED | B80: 4775105.5 | C80: C | D80: 469BC89261070002 | E80: 17/04/2026 | F80: BHOWANIPORE | G80: 4775105.5 | H80: BILLS DISCOUNTED | I80: Sales | J80: 46138 | K80: =VLOOKUP(D80,Sales!$G$3:$G$45,1,FALSE) -> 469BC89261070002 | M80: =VLOOKUP(D80,Charges!$D$8:$D$25,1,FALSE) -> #N/A | O80: =VLOOKUP(D80,Retirement!$F$12:$F$79,1,FALSE) -> #N/A
A81: CORRESPONDENT BANK CHARGES | B81: 101756.49 | C81: D | D81: 469BC89260280004 | E81: 17/04/2026 | F81: BHOWANIPORE | G81: -101756.49 | H81: CORRESPONDENT BANK CHARGES | I81: Sales | J81: 46138 | K81: =VLOOKUP(D81,Sales!$G$3:$G$45,1,FALSE) -> #N/A | M81: =VLOOKUP(D81,Charges!$D$8:$D$25,1,FALSE) -> #N/A | O81: =VLOOKUP(D81,Retirement!$F$12:$F$79,1,FALSE) -> 469BC89260280004 | Q81: 469BC89260280004
A82: BILLS DISCOUNTED | B82: 13422713 | C82: C | D82: 469BC89261070001 | E82: 17/04/2026 | F82: BHOWANIPORE | G82: 13422713 | H82: BILLS DISCOUNTED | I82: Sales | J82: 46138 | K82: =VLOOKUP(D82,Sales!$G$3:$G$45,1,FALSE) -> 469BC89261070001 | M82: =VLOOKUP(D82,Charges!$D$8:$D$25,1,FALSE) -> #N/A | O82: =VLOOKUP(D82,Retirement!$F$12:$F$79,1,FALSE) -> 469BC89261070001
A83: COURIER CHARGES ON EXPORT BILLS | B83: 5310 | C83: D | D83: 469BC89261070001 | E83: 17/04/2026 | F83: BHOWANIPORE | G83: -5310 | H83: COURIER CHARGES ON EXPORT BILLS | I83: Issuance | J83: 46138 | K83: =VLOOKUP(D83,Sales!$G$3:$G$45,1,FALSE) -> 469BC89261070001 | M83: =VLOOKUP(D83,Charges!$D$8:$D$25,1,FALSE) -> #N/A | O83: =VLOOKUP(D83,Retirement!$F$12:$F$79,1,FALSE) -> 469BC89261070001
A84: COMM ON LOCAL LC ISSUED | B84: 13264.38 | C84: D | D84: 469LC03261070002 | E84: 17/04/2026 | F84: BHOWANIPORE | G84: -13264.38 | H84: COMM ON LOCAL LC ISSUED | I84: Issuance | J84: 46138 | K84: =VLOOKUP(D84,Sales!$G$3:$G$45,1,FALSE) -> #N/A | M84: =VLOOKUP(D84,Charges!$D$8:$D$25,1,FALSE) -> 469LC03261070002 | O84: =VLOOKUP(D84,Retirement!$F$12:$F$79,1,FALSE) -> #N/A
A85: LIQUIDATION OF LOCAL BILL UNDER LC | B85: 5156929 | C85: D | D85: 469BC04260210004 | E85: 17/04/2026 | F85: BHOWANIPORE | G85: -5156929 | H85: LIQUIDATION OF LOCAL BILL UNDER LC | I85: Sales | J85: 46138 | K85: =VLOOKUP(D85,Sales!$G$3:$G$45,1,FALSE) -> #N/A | M85: =VLOOKUP(D85,Charges!$D$8:$D$25,1,FALSE) -> #N/A | O85: =VLOOKUP(D85,Retirement!$F$12:$F$79,1,FALSE) -> 469BC04260210004
A86: COURIER CHARGES ON EXPORT BILLS | B86: 5310 | C86: D | D86: 469BC89261070002 | E86: 17/04/2026 | F86: BHOWANIPORE | G86: -5310 | H86: COURIER CHARGES ON EXPORT BILLS | I86: Issuance | J86: 46138 | K86: =VLOOKUP(D86,Sales!$G$3:$G$45,1,FALSE) -> 469BC89261070002 | M86: =VLOOKUP(D86,Charges!$D$8:$D$25,1,FALSE) -> #N/A | O86: =VLOOKUP(D86,Retirement!$F$12:$F$79,1,FALSE) -> #N/A
A87: LIQUIDATION OF LOCAL BILL UNDER LC | B87: 2444683 | C87: D | D87: 469BC04260270003 | E87: 18/04/2026 | F87: BHOWANIPORE | G87: -2444683 | H87: LIQUIDATION OF LOCAL BILL UNDER LC | I87: Sales | J87: 46138 | K87: =VLOOKUP(D87,Sales!$G$3:$G$45,1,FALSE) -> #N/A | M87: =VLOOKUP(D87,Charges!$D$8:$D$25,1,FALSE) -> #N/A | O87: =VLOOKUP(D87,Retirement!$F$12:$F$79,1,FALSE) -> 469BC04260270003
A88: LIQUIDATION OF LOCAL BILL UNDER LC | B88: 4897308 | C88: D | D88: 469BC04260270002 | E88: 18/04/2026 | F88: BHOWANIPORE | G88: -4897308 | H88: LIQUIDATION OF LOCAL BILL UNDER LC | I88: Sales | J88: 46138 | K88: =VLOOKUP(D88,Sales!$G$3:$G$45,1,FALSE) -> #N/A | M88: =VLOOKUP(D88,Charges!$D$8:$D$25,1,FALSE) -> #N/A | O88: =VLOOKUP(D88,Retirement!$F$12:$F$79,1,FALSE) -> 469BC04260270002
A89: INTEREST ON EXPORT BILL PURCHASE | B89: 220.26 | C89: D | D89: 469BC89261030003 | E89: 18/04/2026 | F89: BHOWANIPORE | G89: -220.26 | H89: INTEREST ON EXPORT BILL PURCHASE | I89: Issuance | J89: 46138 | K89: =VLOOKUP(D89,Sales!$G$3:$G$45,1,FALSE) -> 469BC89261030003 | M89: =VLOOKUP(D89,Charges!$D$8:$D$25,1,FALSE) -> #N/A | O89: =VLOOKUP(D89,Retirement!$F$12:$F$79,1,FALSE) -> #N/A | Q89: 469BC89261030003
A90: INTEREST ON EXPORT BILL PURCHASE | B90: 704.6 | C90: D | D90: 469BC89261030001 | E90: 18/04/2026 | F90: BHOWANIPORE | G90: -704.6 | H90: INTEREST ON EXPORT BILL PURCHASE | I90: Issuance | J90: 46138 | K90: =VLOOKUP(D90,Sales!$G$3:$G$45,1,FALSE) -> 469BC89261030001 | M90: =VLOOKUP(D90,Charges!$D$8:$D$25,1,FALSE) -> #N/A | O90: =VLOOKUP(D90,Retirement!$F$12:$F$79,1,FALSE) -> #N/A | Q90: 469BC89261030001
A91: LIQUIDATION OF LOCAL BILL UNDER LC | B91: 4976514 | C91: D | D91: 469BC04260280004 | E91: 20/04/2026 | F91: BHOWANIPORE | G91: -4976514 | H91: LIQUIDATION OF LOCAL BILL UNDER LC | I91: Sales | J91: 46138 | K91: =VLOOKUP(D91,Sales!$G$3:$G$45,1,FALSE) -> #N/A | M91: =VLOOKUP(D91,Charges!$D$8:$D$25,1,FALSE) -> #N/A | O91: =VLOOKUP(D91,Retirement!$F$12:$F$79,1,FALSE) -> 469BC04260280004
A92: COURIER CHARGES ON EXPORT BILLS | B92: 5310 | C92: D | D92: 469BC89261100007 | E92: 20/04/2026 | F92: BHOWANIPORE | G92: -5310 | H92: COURIER CHARGES ON EXPORT BILLS | I92: Issuance | J92: 46138 | K92: =VLOOKUP(D92,Sales!$G$3:$G$45,1,FALSE) -> 469BC89261100007 | M92: =VLOOKUP(D92,Charges!$D$8:$D$25,1,FALSE) -> #N/A | O92: =VLOOKUP(D92,Retirement!$F$12:$F$79,1,FALSE) -> #N/A | Q92: 469BC89261100007
A93: GST ON COMMISSION AND CHARGE | B93: 181.58 | C93: D | D93: 469BC89260280004 | E93: 20/04/2026 | F93: BHOWANIPORE | G93: -181.58 | H93: GST ON COMMISSION AND CHARGE | I93: GST | J93: 46138 | K93: =VLOOKUP(D93,Sales!$G$3:$G$45,1,FALSE) -> #N/A | M93: =VLOOKUP(D93,Charges!$D$8:$D$25,1,FALSE) -> #N/A | O93: =VLOOKUP(D93,Retirement!$F$12:$F$79,1,FALSE) -> 469BC89260280004 | Q93: 469BC89260280004
A94: COURIER CHARGES ON EXPORT BILLS | B94: 5310 | C94: D | D94: 469BC89261100006 | E94: 20/04/2026 | F94: BHOWANIPORE | G94: -5310 | H94: COURIER CHARGES ON EXPORT BILLS | I94: Issuance | J94: 46138 | K94: =VLOOKUP(D94,Sales!$G$3:$G$45,1,FALSE) -> 469BC89261100006 | M94: =VLOOKUP(D94,Charges!$D$8:$D$25,1,FALSE) -> #N/A | O94: =VLOOKUP(D94,Retirement!$F$12:$F$79,1,FALSE) -> #N/A
A95: COURIER CHARGES ON EXPORT BILLS | B95: 5310 | C95: D | D95: 469BC89261100003 | E95: 20/04/2026 | F95: BHOWANIPORE | G95: -5310 | H95: COURIER CHARGES ON EXPORT BILLS | I95: Issuance | J95: 46138 | K95: =VLOOKUP(D95,Sales!$G$3:$G$45,1,FALSE) -> 469BC89261100003 | M95: =VLOOKUP(D95,Charges!$D$8:$D$25,1,FALSE) -> #N/A | O95: =VLOOKUP(D95,Retirement!$F$12:$F$79,1,FALSE) -> #N/A
A96: COURIER CHARGES ON EXPORT BILLS | B96: 5310 | C96: D | D96: 469BC89261100002 | E96: 20/04/2026 | F96: BHOWANIPORE | G96: -5310 | H96: COURIER CHARGES ON EXPORT BILLS | I96: Issuance | J96: 46138 | K96: =VLOOKUP(D96,Sales!$G$3:$G$45,1,FALSE) -> 469BC89261100002 | M96: =VLOOKUP(D96,Charges!$D$8:$D$25,1,FALSE) -> #N/A | O96: =VLOOKUP(D96,Retirement!$F$12:$F$79,1,FALSE) -> #N/A | Q96: 469BC89261100002
A97: COURIER CHARGES ON EXPORT BILLS | B97: 5310 | C97: D | D97: 469BC89261100005 | E97: 20/04/2026 | F97: BHOWANIPORE | G97: -5310 | H97: COURIER CHARGES ON EXPORT BILLS | I97: Issuance | J97: 46138 | K97: =VLOOKUP(D97,Sales!$G$3:$G$45,1,FALSE) -> 469BC89261100005 | M97: =VLOOKUP(D97,Charges!$D$8:$D$25,1,FALSE) -> #N/A | O97: =VLOOKUP(D97,Retirement!$F$12:$F$79,1,FALSE) -> #N/A | Q97: 469BC89261100005
A98: COURIER CHARGES ON EXPORT BILLS | B98: 5310 | C98: D | D98: 469BC89261100004 | E98: 20/04/2026 | F98: BHOWANIPORE | G98: -5310 | H98: COURIER CHARGES ON EXPORT BILLS | I98: Issuance | J98: 46138 | K98: =VLOOKUP(D98,Sales!$G$3:$G$45,1,FALSE) -> 469BC89261100004 | M98: =VLOOKUP(D98,Charges!$D$8:$D$25,1,FALSE) -> #N/A | O98: =VLOOKUP(D98,Retirement!$F$12:$F$79,1,FALSE) -> #N/A | Q98: 469BC89261100004
A99: LIQUIDATION OF LOCAL BILL UNDER LC | B99: 2508904 | C99: D | D99: 469BC04260280003 | E99: 21/04/2026 | F99: BHOWANIPORE | G99: -2508904 | H99: LIQUIDATION OF LOCAL BILL UNDER LC | I99: Sales | J99: 46138 | K99: =VLOOKUP(D99,Sales!$G$3:$G$45,1,FALSE) -> #N/A | M99: =VLOOKUP(D99,Charges!$D$8:$D$25,1,FALSE) -> #N/A | O99: =VLOOKUP(D99,Retirement!$F$12:$F$79,1,FALSE) -> 469BC04260280003 | Q99: 469BC04260280003
A100: LIQUIDATION OF LOCAL BILL UNDER LC | B100: 10336202 | C100: D | D100: 469BC04260280002 | E100: 21/04/2026 | F100: BHOWANIPORE | G100: -10336202 | H100: LIQUIDATION OF LOCAL BILL UNDER LC | I100: Sales | J100: 46138 | K100: =VLOOKUP(D100,Sales!$G$3:$G$45,1,FALSE) -> #N/A | M100: =VLOOKUP(D100,Charges!$D$8:$D$25,1,FALSE) -> #N/A | O100: =VLOOKUP(D100,Retirement!$F$12:$F$79,1,FALSE) -> 469BC04260280002 | Q100: 469BC04260280002
A101: CORRESPONDENT BANK CHARGES | B101: 4518 | C101: D | D101: 469BC89260290005 | E101: 21/04/2026 | F101: BHOWANIPORE | G101: -4518 | H101: CORRESPONDENT BANK CHARGES | I101: Sales | J101: 46138 | K101: =VLOOKUP(D101,Sales!$G$3:$G$45,1,FALSE) -> #N/A | M101: =VLOOKUP(D101,Charges!$D$8:$D$25,1,FALSE) -> #N/A | O101: =VLOOKUP(D101,Retirement!$F$12:$F$79,1,FALSE) -> 469BC89260290005 | Q101: 469BC89260290005
A102: COURIER CHARGES ON EXPORT BILLS | B102: 5310 | C102: D | D102: 469BC89261110008 | E102: 21/04/2026 | F102: BHOWANIPORE | G102: -5310 | H102: COURIER CHARGES ON EXPORT BILLS | I102: Issuance | J102: 46138 | K102: =VLOOKUP(D102,Sales!$G$3:$G$45,1,FALSE) -> 469BC89261110008 | M102: =VLOOKUP(D102,Charges!$D$8:$D$25,1,FALSE) -> #N/A | O102: =VLOOKUP(D102,Retirement!$F$12:$F$79,1,FALSE) -> #N/A | Q102: 469BC89261110008
...

Sheet Charges
F1: LC Charges - Summary - Apr'26 | J1: Amount in INR
F2: Bank | G2: Total LC Value | H2: Total Charges by Bank | I2: Total Charges Calculated | J2: Excess/(Short) (Incl. Penal Charge if any)
F3: HDFC | G3: =SUMIFS(O:O,C:C,F3) -> 13625650 | H3: =SUMIFS(AC:AC,C:C,F3) -> 21241 | I3: =SUMIFS(AJ:AJ,C:C,F3) -> 21241 | J3: =H3-I3 -> 0
F4: Indian | G4: =SUMIFS(O:O,C:C,F4) -> 3073043.9 | H4: =SUMIFS(AC:AC,C:C,F4) -> 564690 | I4: =SUMIFS(AJ:AJ,C:C,F4) -> 465106.19 | J4: =H4-I4 -> 99583.811
F5: UBI | G5: =SUMIFS(O:O,C:C,F5) -> 7575741.3 | H5: =SUMIFS(AC:AC,C:C,F5) -> 656388.49 | I5: =SUMIFS(AJ:AJ,C:C,F5) -> 1298288.1 | J5: =H5-I5 -> -641899.64
F6: TOTAL | G6: =SUM(G3:G5) -> 24274435 | H6: =SUM(H3:H5) -> 1242319.5 | I6: =SUM(I3:I5) -> 1784635.3 | J6: =SUM(J3:J5) -> -542315.83
S7: As per Bank | AF7: As per Auditor
C8: Bank Name | D8: LC No | E8: User Reference No | F8: Beneficiary | G8: Value Date | H8: LC Open Date | I8: LC Expiry Date | J8: LC Amendment Date | K8: Validity | L8: Usance | M8: Total Days | N8: LC Amount | O8: LC Amount inc Tolerance | P8: Currency | Q8: Exchange Rate | R8: LC Amount (INR) | S8: LC Issuance Charge | T8: LC Usance Charges | U8: Commitment Charges | V8: Amendment Charges | W8: LC Advising Commission | X8: SWIFT/SFMS Charges | Y8: GST | Z8: Total Charges | AA8: Opening/Usuance Charge % | AB8: Amendment Charge % | AC8: Total chgs as per Bank(Excl GST) | AD8: Total chgs as per SAP(Excl GST) | AE8: Difference | AF8: Issuance /Amendment chgs Calculated | AG8: Commitment Chgs | AH8: SWIFT /SFMS Charges | AI8: Advising commission charges | AJ8: Total Charges Calculated (Excl GST) | AK8: Excess (Shortfall) | AL8: Management Remarks | AM8: Auditor Remarks
B9: 2027/01 | C9: HDFC | D9: 014LCEX253590021 | E9: I099891 | F9: TOPANEL PRODUCTION PANELS S.A. | G9: 04-APR-2026 | H9: 23-DEC-2025 | I9: 21-APR-2026 | K9: =I9-H9 -> 119 | L9: =IF(P9="INR",90,180) -> 180 | M9: =K9+L9 -> 299 | N9: 1448400 | O9: =N9 -> 1448400 | P9: EUR | R9: =O9*Q9 -> 0 | V9: 1000 | Y9: =V9*0.18 -> 180 | Z9: =SUM(S9:Y9) -> 1180 | AA9: 0.005 | AB9: 0.005 | AC9: =SUM(S9:X9) -> 1000 | AD9: =SUMIFS(SAP!H:H,SAP!L:L,Charges!D9,SAP!V:V,Charges!B9) -> 1000 | AE9: =ROUND(AC9-AD9,0) -> 0 | AF9: =V9 -> 1000 | AJ9: =SUM(AF9:AI9) -> 1000 | AK9: =ROUND(T9+U9+V9-AJ9+W9+X9,0) -> 0
B10: 2027/01 | C10: HDFC | D10: 014LCEX260920018 | E10: 39010380011215 | F10: PERFICHAPA S.A. | G10: 04-APR-2026 | H10: 01-APR-2026 | I10: 21-JUL-2026 | K10: =I10-H10 -> 111 | L10: =IF(P10="INR",90,180) -> 180 | M10: =K10+L10 -> 291 | N10: 259000 | O10: =N10 -> 259000 | P10: EUR | R10: =O10*Q10 -> 0 | U10: 1500 | Y10: =U10*0.18 -> 270 | Z10: =SUM(S10:Y10) -> 1770 | AA10: 0.005 | AB10: 0.005 | AC10: =SUM(S10:X10) -> 1500 | AD10: =SUMIFS(SAP!H:H,SAP!L:L,Charges!D10,SAP!V:V,Charges!B10) -> 1500 | AE10: =ROUND(AC10-AD10,0) -> 0 | AF10: =U10 -> 1500 | AJ10: =SUM(AF10:AI10) -> 1500 | AK10: =ROUND(T10+U10+V10-AJ10+W10+X10,0) -> 0
B11: 2027/01 | C11: HDFC | D11: 014LCEX260910002 | E11: CDI26700237 | F11: FERPAINEL S.A | G11: 02-APR-2026 | H11: 31-MAR-2026 | I11: 21-JUL-2026 | K11: =I11-H11 -> 112 | L11: =IF(P11="INR",90,180) -> 180 | M11: =K11+L11 -> 292 | N11: 599000 | O11: =N11 -> 599000 | P11: EUR | R11: =O11*Q11 -> 0 | U11: 1500 | Y11: =U11*0.18 -> 270 | Z11: =SUM(S11:Y11) -> 1770 | AA11: 0.005 | AB11: 0.005 | AC11: =SUM(S11:X11) -> 1500 | AD11: =SUMIFS(SAP!H:H,SAP!L:L,Charges!D11,SAP!V:V,Charges!B11) -> 1500 | AE11: =ROUND(AC11-AD11,0) -> 0 | AF11: =U11 -> 1500 | AJ11: =SUM(AF11:AI11) -> 1500 | AK11: =ROUND(T11+U11+V11-AJ11+W11+X11,0) -> 0
B12: 2027/01 | C12: HDFC | D12: 014LCEX260920001 | E12: 10905I0194085387 | F12: METECNO ITALIA SRL | G12: 02-APR-2026 | H12: 01-APR-2026 | I12: 21-JUL-2026 | K12: =I12-H12 -> 111 | L12: =IF(P12="INR",90,180) -> 180 | M12: =K12+L12 -> 291 | N12: 69000 | O12: =N12 -> 69000 | P12: EUR | R12: =O12*Q12 -> 0 | W12: 1500 | Y12: =W12*0.18 -> 270 | Z12: =SUM(S12:Y12) -> 1770 | AA12: 0.005 | AB12: 0.005 | AC12: =SUM(S12:X12) -> 1500 | AD12: =SUMIFS(SAP!H:H,SAP!L:L,Charges!D12,SAP!V:V,Charges!B12) -> 1500 | AE12: =ROUND(AC12-AD12,0) -> 0 | AF12: =U12 -> 0 | AI12: 1500 | AJ12: =SUM(AF12:AI12) -> 1500 | AK12: =ROUND(T12+U12+V12-AJ12+W12+X12,0) -> 0
B13: 2027/01 | C13: HDFC | D13: 014LCEX261010002 | E13: 10907I0194415387 | F13: IDROCENTRO S.P.A. | G13: 13-APR-2026 | H13: 10-APR-2026 | I13: 21-JUL-2026 | K13: =I13-H13 -> 102 | L13: =IF(P13="INR",90,180) -> 180 | M13: =K13+L13 -> 282 | N13: 735000 | O13: =N13 -> 735000 | P13: EUR | R13: =O13*Q13 -> 0 | U13: 1500 | Y13: =U13*0.18 -> 270 | Z13: =SUM(S13:Y13) -> 1770 | AA13: 0.005 | AB13: 0.005 | AC13: =SUM(S13:X13) -> 1500 | AD13: =SUMIFS(SAP!H:H,SAP!L:L,Charges!D13,SAP!V:V,Charges!B13) -> 1500 | AE13: =ROUND(AC13-AD13,0) -> 0 | AF13: =U13 -> 1500 | AJ13: =SUM(AF13:AI13) -> 1500 | AK13: =ROUND(T13+U13+V13-AJ13+W13+X13,0) -> 0
B14: 2027/01 | C14: HDFC | D14: 014LCEX261130002 | E14: CI35863100098037 | F14: ITALPANNELLI IBERICA S.A. | G14: 23-APR-2026 | H14: 22-APR-2026 | I14: 10-SEP-2026 | K14: =I14-H14 -> 141 | L14: =IF(P14="INR",90,180) -> 180 | M14: =K14+L14 -> 321 | N14: 1879000 | O14: =N14 -> 1879000 | P14: EUR | R14: =O14*Q14 -> 0 | U14: 1500 | Y14: =U14*0.18 -> 270 | Z14: =SUM(S14:Y14) -> 1770 | AA14: 0.005 | AB14: 0.005 | AC14: =SUM(S14:X14) -> 1500 | AD14: =SUMIFS(SAP!H:H,SAP!L:L,Charges!D14,SAP!V:V,Charges!B14) -> 1500 | AE14: =ROUND(AC14-AD14,0) -> 0 | AF14: =U14 -> 1500 | AJ14: =SUM(AF14:AI14) -> 1500 | AK14: =ROUND(T14+U14+V14-AJ14+W14+X14,0) -> 0
B15: 2027/01 | C15: HDFC | D15: 014LCEX261180044 | E15: 10905I0201745387 | F15: LATTONEDIL SPA MILANO | G15: 29-APR-2026 | H15: 28-APR-2026 | I15: 31-AUG-2026 | K15: =I15-H15 -> 125 | L15: =IF(P15="INR",90,180) -> 180 | M15: =K15+L15 -> 305 | N15: 1991250 | O15: =N15 -> 1991250 | P15: EUR | R15: =O15*Q15 -> 0 | U15: 1500 | Y15: =U15*0.18 -> 270 | Z15: =SUM(S15:Y15) -> 1770 | AA15: 0.005 | AB15: 0.005 | AC15: =SUM(S15:X15) -> 1500 | AD15: =SUMIFS(SAP!H:H,SAP!L:L,Charges!D15,SAP!V:V,Charges!B15) -> 1500 | AE15: =ROUND(AC15-AD15,0) -> 0 | AF15: =U15 -> 1500 | AJ15: =SUM(AF15:AI15) -> 1500 | AK15: =ROUND(T15+U15+V15-AJ15+W15+X15,0) -> 0
C16: HDFC | D16: 469LC03261070002 | F16: JINDAL STEEL ODISHA LIMITED | G16: 46129 | H16: 46129 | I16: 46157 | K16: =I16-H16 -> 28 | L16: =IF(P16="INR",90,180) -> 90 | M16: =K16+L16 -> 118 | N16: 6645000 | O16: 6645000 | P16: INR | R16: 6645000 | S16: 10741 | X16: 500 | Y16: =S16*0.18+X16*0.18 -> 2023.38 | Z16: =SUM(S16:Y16) -> 13264.38 | AA16: 0.005 | AC16: =SUM(S16:X16) -> 11241 | AD16: =SUMIFS(SAP!H:H,SAP!L:L,Charges!D16,SAP!V:V,"2027/01") -> 11241 | AE16: =ROUND(AC16-AD16,0) -> 0 | AF16: =S16 -> 10741 | AH16: =X16 -> 500 | AJ16: =SUM(AF16:AI16) -> 11241 | AK16: =ROUND(T16+U16+V16-AJ16+W16+X16+S16,0) -> 0
B17: 2027/01 | C17: INDIAN | D17: 0571026FBU000228 | F17: BAOSTEEL SINGAPORE PTE LTD | G17: 46133 | K17: =I17-H17 -> 0 | L17: =IF(P17="INR",90,180) -> 180 | M17: =K17+L17 -> 180 | N17: 600899.22 | O17: =N17 -> 600899.22 | P17: USD | R17: =O17*Q17 -> 0 | X17: 550 | Y17: 99 | Z17: =SUM(S17:Y17) -> 649 | AA17: 0.005 | AC17: =SUM(S17:X17) -> 550 | AD17: =SUMIFS(SAP!H:H,SAP!L:L,Charges!D17,SAP!V:V,Charges!B17) -> 550 | AE17: =ROUND(AC17-AD17,0) -> 0 | AF17: 0 | AH17: =X17 -> 550 | AJ17: =SUM(AF17:AI17) -> 550 | AK17: =ROUND(T17+U17+V17-AJ17+W17+X17,0) -> 0
B18: 2027/01 | C18: INDIAN | D18: 0571026FBU000229 | F18: HONORS COMMODITY HONG KONG COMPANY | G18: 46133 | K18: =I18-H18 -> 0 | L18: =IF(P18="INR",90,180) -> 180 | M18: =K18+L18 -> 180 | N18: 305150.74 | O18: =N18 -> 305150.74 | P18: USD | R18: =O18*Q18 -> 0 | X18: 550 | Y18: 99 | Z18: =SUM(S18:Y18) -> 649 | AA18: 0.005 | AC18: =SUM(S18:X18) -> 550 | AD18: =SUMIFS(SAP!H:H,SAP!L:L,Charges!D18,SAP!V:V,Charges!B18) -> 550 | AE18: =ROUND(AC18-AD18,0) -> 0 | AF18: 0 | AH18: =X18 -> 550 | AJ18: =SUM(AF18:AI18) -> 550 | AK18: =ROUND(T18+U18+V18-AJ18+W18+X18,0) -> 0
B19: 2027/01 | C19: INDIAN | D19: 0571026FBU000230 | F19: HONORS COMMODITY HONG KONG COMPANY | G19: 46142 | K19: =I19-H19 -> 0 | L19: =IF(P19="INR",90,180) -> 180 | M19: =K19+L19 -> 180 | N19: 342714.41 | O19: =N19 -> 342714.41 | P19: USD | R19: =O19*Q19 -> 0 | X19: 550 | Y19: 99 | Z19: =SUM(S19:Y19) -> 649 | AA19: 0.005 | AC19: =SUM(S19:X19) -> 550 | AD19: =SUMIFS(SAP!H:H,SAP!L:L,Charges!D19,SAP!V:V,Charges!B19) -> 550 | AE19: =ROUND(AC19-AD19,0) -> 0 | AF19: 0 | AH19: =X19 -> 550 | AJ19: =SUM(AF19:AI19) -> 550 | AK19: =ROUND(T19+U19+V19-AJ19+W19+X19,0) -> 0
B20: 2027/01 | C20: INDIAN | D20: 0571026FLU000185 | F20: BAOSTEEL SINGAPORE PTE LTD | G20: 46121 | H20: 46121 | J20: 46128 | L20: =IF(P20="INR",90,180) -> 180 | M20: =K20+L20 -> 180 | N20: 1625000 | O20: 1824279.5 | P20: USD | Q20: 93.58 | R20: =O20*Q20 -> 1.7071608e+08 | T20: 426790 | U20: 99584 | V20: 35566 | X20: =550*2 -> 1100 | Y20: =17925+76822+99 -> 94846 | Z20: =SUM(S20:Y20) -> 657886 | AA20: 0.005 | AB20: 0.001 | AC20: =SUM(S20:X20) -> 563040 | AD20: =SUMIFS(SAP!H:H,SAP!L:L,Charges!D20,SAP!V:V,Charges!B20) -> 563039.82 | AE20: =ROUND(AC20-AD20,0) -> 0 | AF20: =(R20*AA20*M20/360)+V20 -> 462356.19 | AH20: =X20 -> 1100 | AJ20: =SUM(AF20:AI20) -> 463456.19 | AK20: =ROUND(T20+U20+V20-AJ20+W20+X20,0) -> 99584
B21: 2027/01 | C21: UBI | D21: 68840M11F0258226-CLM002 | F21: HONORS COMMODITY HONG KONG COMPANY | G21: 46140 | H21: 46140 | I21: 46294 | K21: =I21-H21 -> 154 | L21: =IF(P21="INR",90,180) -> 180 | M21: =K21+L21 -> 334 | N21: 1756215.9 | O21: =N21 -> 1756215.9 | P21: USD | R21: =O21*Q21 -> 0 | X21: 1000 | Y21: 180 | Z21: =SUM(S21:Y21) -> 1180 | AA21: 0.005 | AC21: =SUM(S21:X21) -> 1000 | AD21: =SUMIFS(SAP!H:H,SAP!M:M,Charges!D21,SAP!V:V,Charges!B21) -> 1000 | AE21: =ROUND(AC21-AD21,0) -> 0 | AF21: 0 | AH21: =X21 -> 1000 | AJ21: =SUM(AF21:AI21) -> 1000 | AK21: =ROUND(T21+U21+V21-AJ21+W21+X21,0) -> 0
B22: 2027/01 | C22: UBI | D22: 68840M11F0258226-CLM001 | F22: HONORS COMMODITY HONG KONG COMPANY | G22: 46133 | H22: 46133 | I22: 46294 | K22: =I22-H22 -> 161 | L22: =IF(P22="INR",90,180) -> 180 | M22: =K22+L22 -> 341 | N22: 2316248.2 | O22: =N22 -> 2316248.2 | P22: USD | R22: =O22*Q22 -> 0 | X22: 1000 | Y22: 180 | Z22: =SUM(S22:Y22) -> 1180 | AA22: 0.005 | AC22: =SUM(S22:X22) -> 1000 | AD22: =SUMIFS(SAP!H:H,SAP!M:M,Charges!D22,SAP!V:V,Charges!B22) -> 1000 | AE22: =ROUND(AC22-AD22,0) -> 0 | AF22: 0 | AH22: =X22 -> 1000 | AJ22: =SUM(AF22:AI22) -> 1000 | AK22: =ROUND(T22+U22+V22-AJ22+W22+X22,0) -> 0
B23: 2027/01 | C23: UBI | D23: 68840M11F0351126 | F23: BAOSTEEL SINGAPORE PTE LTD | G23: 46118 | H23: 46118 | I23: 46163 | K23: =I23-H23 -> 45 | L23: =IF(P23="INR",90,180) -> 180 | M23: =K23+L23 -> 225 | N23: 1040000 | O23: 1167759.1 | P23: USD | Q23: 93.25 | R23: =O23*Q23 -> 1.0889353e+08 | T23: 187837.2 | U23: 46959.09 | X23: 2500 | Y23: =33810.7+8452.64+450 -> 42713.34 | Z23: =SUM(S23:Y23) -> 280009.63 | AA23: 0.005 | AB23: 0.001 | AC23: =SUM(S23:X23) -> 237296.29 | AD23: =SUMIFS(SAP!H:H,SAP!M:M,Charges!D23,SAP!V:V,Charges!B23) -> 237296.29 | AE23: =ROUND(AC23-AD23,0) -> 0 | AF23: =K32 -> 331230.7 | AG23: =K36 -> 99365.348 | AH23: =X23 -> 2500 | AJ23: =SUM(AF23:AI23) -> 433096.04 | AK23: =AC23-AJ23 -> -195799.75
B24: 2027/01 | C24: UBI | D24: 68840M11F0351126 - AMD001 | F24: BAOSTEEL SINGAPORE PTE LTD | G24: 46118 | H24: 46118 | I24: 46163 | J24: 46130 | K24: =I24-H24 -> 45 | L24: =IF(P24="INR",90,180) -> 180 | M24: =K24+L24 -> 225 | N24: 1040000 | O24: 1167759.1 | P24: USD | Q24: 93.25 | R24: =O24*Q24 -> 1.0889353e+08 | T24: 242165.89 | U24: 60541.47 | X24: 1000 | Y24: =180+43589.86+10897.46 -> 54667.32 | Z24: =SUM(S24:Y24) -> 358374.68 | AA24: 0.005 | AB24: 0.001 | AC24: =SUM(S24:X24) -> 303707.36 | AD24: =SUMIFS(SAP!H:H,SAP!M:M,Charges!D24,SAP!V:V,Charges!B24) -> 303707.36 | AE24: =ROUND(AC24-AD24,0) -> 0 | AF24: =K32 -> 331230.7 | AG24: =K36 -> 99365.348 | AH24: =X24 -> 1000 | AJ24: =SUM(AF24:AI24) -> 431596.04 | AK24: =AC24-AJ24 -> -127888.68
B25: 2027/01 | C25: UBI | D25: 68840M11F0351126 - AMD002 | F25: BAOSTEEL SINGAPORE PTE LTD | G25: 46118 | H25: 46118 | I25: 46163 | J25: 46136 | K25: =I25-H25 -> 45 | L25: =IF(P25="INR",90,180) -> 180 | M25: =K25+L25 -> 225 | N25: 1040000 | O25: 1167759.1 | P25: USD | Q25: 93.25 | R25: =O25*Q25 -> 1.0889353e+08 | T25: 89907.87 | U25: 22476.97 | X25: 1000 | Y25: =180+4045.85+16183.42 -> 20409.27 | Z25: =SUM(S25:Y25) -> 133794.11 | AA25: 0.005 | AB25: 0.001 | AC25: =SUM(S25:X25) -> 113384.84 | AD25: =SUMIFS(SAP!H:H,SAP!M:M,Charges!D25,SAP!V:V,Charges!B25) -> 113384.83 | AE25: =ROUND(AC25-AD25,0) -> 0 | AF25: =K32 -> 331230.7 | AG25: =K36 -> 99365.348 | AH25: =X25 -> 1000 | AJ25: =SUM(AF25:AI25) -> 431596.04 | AK25: =AC25-AJ25 -> -318211.2
C26: TOTAL | N26: =SUM(N9:N25) -> 23691879 | O26: =SUM(O9:O25) -> 24274435 | R26: =SUM(R9:R25) -> 5.0404167e+08 | S26: =SUM(S9:S25) -> 10741 | T26: =SUM(T9:T25) -> 946700.96 | U26: =SUM(U9:U25) -> 237061.53 | V26: =SUM(V9:V25) -> 36566 | W26: =SUM(W9:W25) -> 1500 | X26: =SUM(X9:X25) -> 9750 | Y26: =SUM(Y9:Y25) -> 217116.31 | Z26: =SUM(Z9:Z25) -> 1459435.8 | AC26: =SUM(AC9:AC25) -> 1242319.5 | AD26: =SUM(AD9:AD25) -> 1242319.3 | AE26: =SUM(AE9:AE25) -> 0 | AF26: =SUM(AF9:AF25) -> 1475289.3 | AG26: =SUM(AG9:AG25) -> 298096.04 | AH26: =SUM(AH9:AH25) -> 9750 | AJ26: =SUM(AJ9:AJ25) -> 1784635.3 | AK26: =SUM(AK9:AK25) -> -542315.64 | AL26: =SUM(AL9:AL25) -> 0 | AM26: =SUM(AM9:AM25) -> 0
H29: Issuance Chgs | I29: 0.0053 | J29: 50000000 | K29: =I29*J29*6/12 -> 132500
I30: 0.0073 | J30: 50000000 | K30: =I30*J30*6/12 -> 182500
I31: 0.00365 | J31: 8893532 | K31: =I31*J31*6/12 -> 16230.696 | M31: 108893532 | N31: 100000000 | O31: =M31-N31 -> 8893532
K32: =SUBTOTAL(9,K29:K31) -> 331230.7
H33: Commitment Chgs | J33: 50000000
I34: 0.00365 | J34: 50000000 | K34: =J34*I34*6/12 -> 91250
I35: 0.001825 | J35: 8893532 | K35: =J35*I35*6/12 -> 8115.348
K36: =SUBTOTAL(9,K34:K35) -> 99365.348

Sheet Retirement
D2: Retirement Charges - Summary - Apr'26 | H2: Amount in INR
D3: Bank Name | E3: BOE Amount | F3: Total Charges by Bank | G3: LC Retirement Charges by Auditor (As per Sanction) | H3: Excess/(Shortfall)
D4: HDFC | E4: =SUMIFS(L:L,D:D,D4) -> 9.2203814e+08 | F4: =SUMIFS(X:X,D:D,D4) -> 2203200.2 | G4: =SUMIFS(AC:AC,D:D,D4) -> 2203200.2 | H4: =F4-G4 -> 0
D5: UBI | E5: =SUMIFS(L:L,D:D,D5) -> 1.3123005e+08 | F5: =SUMIFS(X:X,D:D,D5) -> 2269757.8 | G5: =SUMIFS(AC:AC,D:D,D5) -> 2269757.8 | H5: =F5-G5 -> 0
D6: KOTAK | E6: =SUMIFS(L:L,D:D,D6) -> 68582864 | F6: =SUMIFS(X:X,D:D,D6) -> 8750 | G6: =SUMIFS(AC:AC,D:D,D6) -> 8750 | H6: =F6-G6 -> 0
D7: INDIAN | E7: =SUMIFS(L:L,D:D,D7) -> 1.538478e+08 | F7: =SUMIFS(X:X,D:D,D7) -> 2435541.5 | G7: =SUMIFS(AC:AC,D:D,D7) -> 2435541.5 | H7: =F7-G7 -> 0
D8: UCO | E8: =SUMIFS(L:L,D:D,D8) -> 124000000 | F8: =SUMIFS(X:X,D:D,D8) -> -64667 | G8: =SUMIFS(AC:AC,D:D,D8) -> -64667 | H8: =F8-G8 -> 0
D9: Total | E9: =SUM(E4:E8) -> 1.3996989e+09 | F9: =SUM(F4:F8) -> 6852582.5 | G9: =SUM(G4:G8) -> 6852582.5 | H9: =SUM(H4:H8) -> 0
M11: As per Bank | AA11: As per Auditor
C12: Sales Type | D12: Bank Name | E12: Particulars | F12: Reference Number | G12: Invoice Number | H12: Date | I12: Amount | J12: Currency | K12: Exchange Rate | L12: Amt (INR) | M12: Correspondant Bank Charges | N12: Bill Commission | O12: Bill / Retirement Charges | P12: Interest on bill maturity extension | Q12: Interest Received | R12: Reversal | S12: Penal Interest | T12: Postage/ Courier | U12: Swift Charges | V12: GST | W12: % of Correspondent charges Deduction | X12: Total chgs by Bank (Excl GST) | Y12: Total chgs Booked in SAP (Excl GST) | Z12: Difference (G-N) | AA12: Commission / CBC Charges Calculated | AB12: Retirement Charges Calculated | AC12: Total Charges Calculated (Excl GST) | AD12: Excess/(short) (AE-AF) | AE12: Penal Interest on LC | AF12: Management Remarks | AG12: Auditor Remarks
B13: 2027/01 | C13: Export | D13: HDFC | E13: HONORS COMMODITY HONG KONG | F13: 469BC02253100001 | H13: 13-APR-2026 | I13: 710629.92 | J13: USD | K13: 92.7825 | L13: =I13*K13 -> 65934021 | M13: 1323545.1 | N13: 2500 | O13: 0 | P13: 0 | Q13: 0 | R13: 0 | S13: 0 | T13: 0 | U13: 0 | V13: 11250 | W13: =IFERROR(N13/L13*100,0) -> 0.0037916693 | X13: =SUM(M13:U13)-O13 -> 1326045.1 | Y13: =SUMIFS(SAP!H:H,SAP!L:L,Retirement!F13,SAP!V:V,Retirement!B13) -> 1326045.1 | Z13: =ROUND(Y13-X13,0) -> 0 | AA13: =N13+M13 -> 1326045.1 | AB13: 0 | AC13: =AA13+AB13 -> 1326045.1 | AD13: =X13-AC13 -> 0 | AE13: =S13 -> 0
B14: 2027/01 | C14: Export | D14: HDFC | E14: HONORS COMMODITY HONG KONG | F14: 469BC02253100002 | H14: 13-APR-2026 | I14: 214156.8 | J14: USD | K14: 92.7825 | L14: =I14*K14 -> 19870003 | M14: 398866.4 | N14: 2500 | O14: 0 | P14: 0 | Q14: 0 | R14: 0 | S14: 0 | T14: 0 | U14: 0 | V14: 4836.6 | W14: =IFERROR(N14/L14*100,0) -> 0.012581779 | X14: =SUM(M14:U14)-O14 -> 401366.4 | Y14: =SUMIFS(SAP!H:H,SAP!L:L,Retirement!F14,SAP!V:V,Retirement!B14) -> 401366.4 | Z14: =ROUND(Y14-X14,0) -> 0 | AA14: =N14+M14 -> 401366.4 | AB14: 0 | AC14: =AA14+AB14 -> 401366.4 | AD14: =X14-AC14 -> 0 | AE14: =S14 -> 0
B15: 2027/01 | C15: Domestic | D15: HDFC | E15: JINDAL STEEL ODISHA LIMITED | F15: 469BC04260090001 | G15: RV8110055834 | H15: 04-APR-2026 | I15: 2161527 | J15: INR | K15: 0 | L15: =I15 -> 2161527 | M15: 0 | N15: 2500 | O15: 0 | P15: 0 | Q15: 0 | R15: 0 | S15: 0 | T15: 100 | U15: 0 | V15: 468 | W15: =IFERROR(N15/L15*100,0) -> 0.11565898 | X15: =SUM(M15:U15) -> 2600 | Y15: =SUMIFS(SAP!H:H,SAP!L:L,Retirement!F15,SAP!V:V,Retirement!B15) -> 2600 | Z15: =ROUND(Y15-X15,0) -> 0 | AA15: =N15 -> 2500 | AB15: =T15 -> 100 | AC15: =AA15+AB15 -> 2600 | AD15: =X15-AC15 -> 0 | AE15: =S15 -> 0
B16: 2027/01 | C16: Domestic | D16: HDFC | E16: JINDAL STEEL ODISHA LIMITED | F16: 469BC04260090002 | G16: RV8110055425 | H16: 02-APR-2026 | I16: 3419604 | J16: INR | K16: 0 | L16: =I16 -> 3419604 | M16: 0 | N16: 2500 | O16: 0 | P16: 0 | Q16: 0 | R16: 0 | S16: 0 | T16: 100 | U16: 0 | V16: 468 | W16: =IFERROR(N16/L16*100,0) -> 0.07310788 | X16: =SUM(M16:U16) -> 2600 | Y16: =SUMIFS(SAP!H:H,SAP!L:L,Retirement!F16,SAP!V:V,Retirement!B16) -> 2600 | Z16: =ROUND(Y16-X16,0) -> 0 | AA16: =N16 -> 2500 | AB16: =T16 -> 100 | AC16: =AA16+AB16 -> 2600 | AD16: =X16-AC16 -> 0 | AE16: =S16 -> 0
B17: 2027/01 | C17: Domestic | D17: HDFC | E17: JINDAL STEEL ODISHA LIMITED | F17: 469BC04260150002 | G17: RV8110056318/19 | H17: 06-APR-2026 | I17: 2406092 | J17: INR | K17: 0 | L17: =I17 -> 2406092 | M17: 0 | N17: 2500 | O17: 0 | P17: 0 | Q17: 0 | R17: 0 | S17: 0 | T17: 100 | U17: 0 | V17: 468 | W17: =IFERROR(N17/L17*100,0) -> 0.10390293 | X17: =SUM(M17:U17) -> 2600 | Y17: =SUMIFS(SAP!H:H,SAP!L:L,Retirement!F17,SAP!V:V,Retirement!B17) -> 2600 | Z17: =ROUND(Y17-X17,0) -> 0 | AA17: =N17 -> 2500 | AB17: =T17 -> 100 | AC17: =AA17+AB17 -> 2600 | AD17: =X17-AC17 -> 0 | AE17: =S17 -> 0
B18: 2027/01 | C18: Domestic | D18: HDFC | E18: JINDAL STEEL ODISHA LIMITED | F18: 469BC04260150003 | G18: RV8110056582 | H18: 07-APR-2026 | I18: 2589324 | J18: INR | K18: 0 | L18: =I18 -> 2589324 | M18: 0 | N18: 2500 | O18: 0 | P18: 0 | Q18: 0 | R18: 0 | S18: 0 | T18: 100 | U18: 0 | V18: 468 | W18: =IFERROR(N18/L18*100,0) -> 0.096550297 | X18: =SUM(M18:U18) -> 2600 | Y18: =SUMIFS(SAP!H:H,SAP!L:L,Retirement!F18,SAP!V:V,Retirement!B18) -> 2600 | Z18: =ROUND(Y18-X18,0) -> 0 | AA18: =N18 -> 2500 | AB18: =T18 -> 100 | AC18: =AA18+AB18 -> 2600 | AD18: =X18-AC18 -> 0 | AE18: =S18 -> 0
B19: 2027/01 | C19: Domestic | D19: HDFC | E19: JINDAL STEEL ODISHA LIMITED | F19: 469BC04260150005 | G19: RV8110057520/21 | H19: 10-APR-2026 | I19: 2614823 | J19: INR | K19: 0 | L19: =I19 -> 2614823 | M19: 0 | N19: 2500 | O19: 0 | P19: 0 | Q19: 0 | R19: 0 | S19: 0 | T19: 100 | U19: 0 | V19: 468 | W19: =IFERROR(N19/L19*100,0) -> 0.095608766 | X19: =SUM(M19:U19) -> 2600 | Y19: =SUMIFS(SAP!H:H,SAP!L:L,Retirement!F19,SAP!V:V,Retirement!B19) -> 2600 | Z19: =ROUND(Y19-X19,0) -> 0 | AA19: =N19 -> 2500 | AB19: =T19 -> 100 | AC19: =AA19+AB19 -> 2600 | AD19: =X19-AC19 -> 0 | AE19: =S19 -> 0
B20: 2027/01 | C20: Domestic | D20: HDFC | E20: JINDAL STEEL ODISHA LIMITED | F20: 469BC04260150007 | G20: RV8110057587 | H20: 10-APR-2026 | I20: 14432698 | J20: INR | K20: 0 | L20: =I20 -> 14432698 | M20: 0 | N20: 2500 | O20: 0 | P20: 0 | Q20: 0 | R20: 0 | S20: 0 | T20: 100 | U20: 0 | V20: 468 | W20: =IFERROR(N20/L20*100,0) -> 0.017321779 | X20: =SUM(M20:U20) -> 2600 | Y20: =SUMIFS(SAP!H:H,SAP!L:L,Retirement!F20,SAP!V:V,Retirement!B20) -> 2600 | Z20: =ROUND(Y20-X20,0) -> 0 | AA20: =N20 -> 2500 | AB20: =T20 -> 100 | AC20: =AA20+AB20 -> 2600 | AD20: =X20-AC20 -> 0 | AE20: =S20 -> 0
B21: 2027/01 | C21: Domestic | D21: HDFC | E21: JINDAL STEEL ODISHA LIMITED | F21: 469BC04260150009 | G21: RV8110058007/8 | H21: 10-APR-2026 | I21: 1993904 | J21: INR | K21: 0 | L21: =I21 -> 1993904 | M21: 0 | N21: 2500 | O21: 0 | P21: 0 | Q21: 0 | R21: 0 | S21: 0 | T21: 100 | U21: 0 | V21: 468 | W21: =IFERROR(N21/L21*100,0) -> 0.12538216 | X21: =SUM(M21:U21) -> 2600 | Y21: =SUMIFS(SAP!H:H,SAP!L:L,Retirement!F21,SAP!V:V,Retirement!B21) -> 2600 | Z21: =ROUND(Y21-X21,0) -> 0 | AA21: =N21 -> 2500 | AB21: =T21 -> 100 | AC21: =AA21+AB21 -> 2600 | AD21: =X21-AC21 -> 0 | AE21: =S21 -> 0
B22: 2027/01 | C22: Domestic | D22: HDFC | E22: JINDAL STEEL ODISHA LIMITED | F22: 469BC04260150011 | G22: RV8110057476 | H22: 10-APR-2026 | I22: 5134754 | J22: INR | K22: 0 | L22: =I22 -> 5134754 | M22: 0 | N22: 2500 | O22: 0 | P22: 0 | Q22: 0 | R22: 0 | S22: 0 | T22: 100 | U22: 0 | V22: 468 | W22: =IFERROR(N22/L22*100,0) -> 0.048687824 | X22: =SUM(M22:U22) -> 2600 | Y22: =SUMIFS(SAP!H:H,SAP!L:L,Retirement!F22,SAP!V:V,Retirement!B22) -> 2600 | Z22: =ROUND(Y22-X22,0) -> 0 | AA22: =N22 -> 2500 | AB22: =T22 -> 100 | AC22: =AA22+AB22 -> 2600 | AD22: =X22-AC22 -> 0 | AE22: =S22 -> 0
B23: 2027/01 | C23: Domestic | D23: HDFC | E23: JINDAL STEEL ODISHA LIMITED | F23: 469BC04260170003 | H23: 13-APR-2026 | I23: 1975556 | J23: INR | K23: 0 | L23: =I23 -> 1975556 | M23: 0 | N23: 2500 | O23: 0 | P23: 0 | Q23: 0 | R23: 0 | S23: 0 | T23: 100 | U23: 0 | V23: 468 | W23: =IFERROR(N23/L23*100,0) -> 0.12654665 | X23: =SUM(M23:U23) -> 2600 | Y23: =SUMIFS(SAP!H:H,SAP!L:L,Retirement!F23,SAP!V:V,Retirement!B23) -> 2600 | Z23: =ROUND(Y23-X23,0) -> 0 | AA23: =N23 -> 2500 | AB23: =T23 -> 100 | AC23: =AA23+AB23 -> 2600 | AD23: =X23-AC23 -> 0 | AE23: =S23 -> 0
B24: 2027/01 | C24: Domestic | D24: HDFC | E24: JINDAL STEEL ODISHA LIMITED | F24: 469BC04260190010 | G24: RV8110056963 | H24: 09-APR-2026 | I24: 10198967 | J24: INR | K24: 0 | L24: =I24 -> 10198967 | M24: 0 | N24: 2500 | O24: 0 | P24: 0 | Q24: 0 | R24: 0 | S24: 0 | T24: 100 | U24: 0 | V24: 468 | W24: =IFERROR(N24/L24*100,0) -> 0.024512286 | X24: =SUM(M24:U24) -> 2600 | Y24: =SUMIFS(SAP!H:H,SAP!L:L,Retirement!F24,SAP!V:V,Retirement!B24) -> 2600 | Z24: =ROUND(Y24-X24,0) -> 0 | AA24: =N24 -> 2500 | AB24: =T24 -> 100 | AC24: =AA24+AB24 -> 2600 | AD24: =X24-AC24 -> 0 | AE24: =S24 -> 0
B25: 2027/01 | C25: Domestic | D25: HDFC | E25: JINDAL STEEL ODISHA LIMITED | F25: 469BC04260200003 | G25: RV8110058689 | H25: 13-APR-2026 | I25: 7201479 | J25: INR | K25: 0 | L25: =I25 -> 7201479 | M25: 0 | N25: 2500 | O25: 0 | P25: 0 | Q25: 0 | R25: 0 | S25: 0 | T25: 100 | U25: 0 | V25: 468 | W25: =IFERROR(N25/L25*100,0) -> 0.034715091 | X25: =SUM(M25:U25) -> 2600 | Y25: =SUMIFS(SAP!H:H,SAP!L:L,Retirement!F25,SAP!V:V,Retirement!B25) -> 2600 | Z25: =ROUND(Y25-X25,0) -> 0 | AA25: =N25 -> 2500 | AB25: =T25 -> 100 | AC25: =AA25+AB25 -> 2600 | AD25: =X25-AC25 -> 0 | AE25: =S25 -> 0
B26: 2027/01 | C26: Domestic | D26: HDFC | E26: JINDAL STEEL ODISHA LIMITED | F26: 469BC04260200005 | G26: RV8110058821 | H26: 13-APR-2026 | I26: 5012896 | J26: INR | K26: 0 | L26: =I26 -> 5012896 | M26: 0 | N26: 2500 | O26: 0 | P26: 0 | Q26: 0 | R26: 0 | S26: 0 | T26: 100 | U26: 0 | V26: 468 | W26: =IFERROR(N26/L26*100,0) -> 0.049871372 | X26: =SUM(M26:U26) -> 2600 | Y26: =SUMIFS(SAP!H:H,SAP!L:L,Retirement!F26,SAP!V:V,Retirement!B26) -> 2600 | Z26: =ROUND(Y26-X26,0) -> 0 | AA26: =N26 -> 2500 | AB26: =T26 -> 100 | AC26: =AA26+AB26 -> 2600 | AD26: =X26-AC26 -> 0 | AE26: =S26 -> 0
B27: 2027/01 | C27: Domestic | D27: HDFC | E27: JINDAL STEEL ODISHA LIMITED | F27: 469BC04260210002 | G27: RV8110059214 | H27: 16-APR-2026 | I27: 5011571 | J27: INR | K27: 0 | L27: =I27 -> 5011571 | M27: 0 | N27: 2500 | O27: 0 | P27: 0 | Q27: 0 | R27: 0 | S27: 0 | T27: 100 | U27: 0 | V27: 468 | W27: =IFERROR(N27/L27*100,0) -> 0.049884557 | X27: =SUM(M27:U27) -> 2600 | Y27: =SUMIFS(SAP!H:H,SAP!L:L,Retirement!F27,SAP!V:V,Retirement!B27) -> 2600 | Z27: =ROUND(Y27-X27,0) -> 0 | AA27: =N27 -> 2500 | AB27: =T27 -> 100 | AC27: =AA27+AB27 -> 2600 | AD27: =X27-AC27 -> 0 | AE27: =S27 -> 0
B28: 2027/01 | C28: Domestic | D28: HDFC | E28: JINDAL STEEL ODISHA LIMITED | F28: 469BC04260210003 | G28: RV8110059138 | H28: 16-APR-2026 | I28: 7341398 | J28: INR | K28: 0 | L28: =I28 -> 7341398 | M28: 0 | N28: 2500 | O28: 0 | P28: 0 | Q28: 0 | R28: 0 | S28: 0 | T28: 100 | U28: 0 | V28: 468 | W28: =IFERROR(N28/L28*100,0) -> 0.03405346 | X28: =SUM(M28:U28) -> 2600 | Y28: =SUMIFS(SAP!H:H,SAP!L:L,Retirement!F28,SAP!V:V,Retirement!B28) -> 2600 | Z28: =ROUND(Y28-X28,0) -> 0 | AA28: =N28 -> 2500 | AB28: =T28 -> 100 | AC28: =AA28+AB28 -> 2600 | AD28: =X28-AC28 -> 0 | AE28: =S28 -> 0
B29: 2027/01 | C29: Domestic | D29: HDFC | E29: JINDAL STEEL ODISHA LIMITED | F29: 469BC04260280002 | G29: RV8110060695 | H29: 21-APR-2026 | I29: 10333134 | J29: INR | K29: 0 | L29: =I29 -> 10333134 | M29: 0 | N29: 2500 | O29: 0 | P29: 0 | Q29: 0 | R29: 0 | S29: 0 | T29: 100 | U29: 0 | V29: 468 | W29: =IFERROR(N29/L29*100,0) -> 0.024194015 | X29: =SUM(M29:U29) -> 2600 | Y29: =SUMIFS(SAP!H:H,SAP!L:L,Retirement!F29,SAP!V:V,Retirement!B29) -> 2600 | Z29: =ROUND(Y29-X29,0) -> 0 | AA29: =N29 -> 2500 | AB29: =T29 -> 100 | AC29: =AA29+AB29 -> 2600 | AD29: =X29-AC29 -> 0 | AE29: =S29 -> 0
B30: 2027/01 | C30: Domestic | D30: HDFC | E30: JINDAL STEEL ODISHA LIMITED | F30: 469BC04260280003 | G30: RV8110060535 | H30: 21-APR-2026 | I30: 2505836 | J30: INR | K30: 0 | L30: =I30 -> 2505836 | M30: 0 | N30: 2500 | O30: 0 | P30: 0 | Q30: 0 | R30: 0 | S30: 0 | T30: 100 | U30: 0 | V30: 468 | W30: =IFERROR(N30/L30*100,0) -> 0.099767104 | X30: =SUM(M30:U30) -> 2600 | Y30: =SUMIFS(SAP!H:H,SAP!L:L,Retirement!F30,SAP!V:V,Retirement!B30) -> 2600 | Z30: =ROUND(Y30-X30,0) -> 0 | AA30: =N30 -> 2500 | AB30: =T30 -> 100 | AC30: =AA30+AB30 -> 2600 | AD30: =X30-AC30 -> 0 | AE30: =S30 -> 0
B31: 2027/01 | C31: Domestic | D31: HDFC | E31: JINDAL STEEL ODISHA LIMITED | F31: 469BC04260290006 | G31: RV8110061076 | H31: 23-APR-2026 | I31: 7351758 | J31: INR | K31: 0 | L31: =I31 -> 7351758 | M31: 0 | N31: 2500 | O31: 0 | P31: 0 | Q31: 0 | R31: 0 | S31: 0 | T31: 100 | U31: 0 | V31: 468 | W31: =IFERROR(N31/L31*100,0) -> 0.034005472 | X31: =SUM(M31:U31) -> 2600 | Y31: =SUMIFS(SAP!H:H,SAP!L:L,Retirement!F31,SAP!V:V,Retirement!B31) -> 2600 | Z31: =ROUND(Y31-X31,0) -> 0 | AA31: =N31 -> 2500 | AB31: =T31 -> 100 | AC31: =AA31+AB31 -> 2600 | AD31: =X31-AC31 -> 0 | AE31: =S31 -> 0
B32: 2027/01 | C32: Domestic | D32: HDFC | E32: JINDAL STEEL ODISHA LIMITED | F32: 469BC04260300009 | G32: RV8110061322 | H32: 24-APR-2026 | I32: 14341649 | J32: INR | K32: 0 | L32: =I32 -> 14341649 | M32: 0 | N32: 2500 | O32: 0 | P32: 0 | Q32: 0 | R32: 0 | S32: 0 | T32: 100 | U32: 0 | V32: 468 | W32: =IFERROR(N32/L32*100,0) -> 0.017431747 | X32: =SUM(M32:U32) -> 2600 | Y32: =SUMIFS(SAP!H:H,SAP!L:L,Retirement!F32,SAP!V:V,Retirement!B32) -> 2600 | Z32: =ROUND(Y32-X32,0) -> 0 | AA32: =N32 -> 2500 | AB32: =T32 -> 100 | AC32: =AA32+AB32 -> 2600 | AD32: =X32-AC32 -> 0 | AE32: =S32 -> 0
B33: 2027/01 | C33: Domestic | D33: HDFC | E33: JINDAL STEEL ODISHA LIMITED | F33: 469BC04260330001 | G33: RV8110062495 | H33: 28-APR-2026 | I33: 2593975 | J33: INR | K33: 0 | L33: =I33 -> 2593975 | M33: 0 | N33: 2500 | O33: 0 | P33: 0 | Q33: 0 | R33: 0 | S33: 0 | T33: 100 | U33: 0 | V33: 468 | W33: =IFERROR(N33/L33*100,0) -> 0.096377182 | X33: =SUM(M33:U33) -> 2600 | Y33: =SUMIFS(SAP!H:H,SAP!L:L,Retirement!F33,SAP!V:V,Retirement!B33) -> 2600 | Z33: =ROUND(Y33-X33,0) -> 0 | AA33: =N33 -> 2500 | AB33: =T33 -> 100 | AC33: =AA33+AB33 -> 2600 | AD33: =X33-AC33 -> 0 | AE33: =S33 -> 0
B34: 2027/01 | C34: Domestic | D34: HDFC | E34: JINDAL STEEL ODISHA LIMITED | F34: 469BC04260350004 | G34: RV8110062942 | H34: 28-APR-2026 | I34: 2592382 | J34: INR | K34: 0 | L34: =I34 -> 2592382 | M34: 0 | N34: 2500 | O34: 0 | P34: 0 | Q34: 0 | R34: 0 | S34: 0 | T34: 100 | U34: 0 | V34: 468 | W34: =IFERROR(N34/L34*100,0) -> 0.096436405 | X34: =SUM(M34:U34) -> 2600 | Y34: =SUMIFS(SAP!H:H,SAP!L:L,Retirement!F34,SAP!V:V,Retirement!B34) -> 2600 | Z34: =ROUND(Y34-X34,0) -> 0 | AA34: =N34 -> 2500 | AB34: =T34 -> 100 | AC34: =AA34+AB34 -> 2600 | AD34: =X34-AC34 -> 0 | AE34: =S34 -> 0
B35: 2027/01 | C35: Export | D35: HDFC | E35: BRAVO INTERNATIONAL CZ S R O | F35: 469BC89253390001 | G35: 5400513916 | H35: 01-APR-2026 | I35: 82280.67 | J35: EUR | K35: 109.87 | L35: =I35*K35 -> 9040177.2 | M35: 12964.66 | N35: 0 | O35: 0 | P35: 0 | Q35: 0 | R35: 0 | S35: 7185.18 | T35: 0 | U35: 0 | V35: 0 | W35: =IFERROR(M35/L35*100,0) -> 0.14341157 | X35: =SUM(M35:U35) -> 20149.84 | Y35: =SUMIFS(SAP!H:H,SAP!L:L,Retirement!F35,SAP!V:V,Retirement!B35) -> 20149.84 | Z35: =ROUND(Y35-X35,0) -> 0 | AA35: =M35 -> 12964.66 | AB35: =S35 -> 7185.18 | AC35: =AA35+AB35 -> 20149.84 | AD35: =X35-AC35 -> 0 | AE35: =S35 -> 7185.18
B36: 2027/01 | C36: Export | D36: HDFC | E36: BRAVO INTERNATIONAL CZ S R O | F36: 469BC89253390002 | G36: 5400513907 | H36: 01-APR-2026 | I36: 110947.04 | J36: EUR | K36: 109.87 | L36: =I36*K36 -> 12189751 | M36: 12964.66 | N36: 0 | O36: 0 | P36: 0 | Q36: 0 | R36: 0 | S36: 9688.2 | T36: 0 | U36: 0 | V36: 0 | W36: =IFERROR(M36/L36*100,0) -> 0.10635705 | X36: =SUM(M36:U36) -> 22652.86 | Y36: =SUMIFS(SAP!H:H,SAP!L:L,Retirement!F36,SAP!V:V,Retirement!B36) -> 22652.86 | Z36: =ROUND(Y36-X36,0) -> 0 | AA36: =M36 -> 12964.66 | AB36: =S36 -> 9688.2 | AC36: =AA36+AB36 -> 22652.86 | AD36: =X36-AC36 -> 0 | AE36: =S36 -> 9688.2
B37: 2027/01 | C37: Export | D37: HDFC | E37: BRAVO INTERNATIONAL CZ S R O | F37: 469BC89253430003 | G37: 5400513908 | H37: 01-APR-2026 | I37: 40032.91 | J37: EUR | K37: 109.87 | L37: =I37*K37 -> 4398415.8 | M37: 12964.66 | N37: 0 | O37: 0 | P37: 0 | Q37: 0 | R37: 0 | S37: 3516.45 | T37: 0 | U37: 0 | V37: 0 | W37: =IFERROR(M37/L37*100,0) -> 0.29475749 | X37: =SUM(M37:U37) -> 16481.11 | Y37: =SUMIFS(SAP!H:H,SAP!L:L,Retirement!F37,SAP!V:V,Retirement!B37) -> 16481.11 | Z37: =ROUND(Y37-X37,0) -> 0 | AA37: =M37 -> 12964.66 | AB37: =S37 -> 3516.45 | AC37: =AA37+AB37 -> 16481.11 | AD37: =X37-AC37 -> 0 | AE37: =S37 -> 3516.45
B38: 2027/01 | C38: Export | D38: HDFC | E38: BRAVO INTERNATIONAL CZ S R O | F38: 469BC89253450002 | G38: 5400513914 | H38: 01-APR-2026 | I38: 238014.1 | J38: EUR | K38: 109.87 | L38: =I38*K38 -> 26150609 | M38: 12964.66 | N38: 0 | O38: 0 | P38: 0 | Q38: 0 | R38: 0 | S38: 20979.65 | T38: 0 | U38: 0 | V38: 0 | W38: =IFERROR(M38/L38*100,0) -> 0.049576895 | X38: =SUM(M38:U38) -> 33944.31 | Y38: =SUMIFS(SAP!H:H,SAP!L:L,Retirement!F38,SAP!V:V,Retirement!B38) -> 33944.31 | Z38: =ROUND(Y38-X38,0) -> 0 | AA38: =M38 -> 12964.66 | AB38: =S38 -> 20979.65 | AC38: =AA38+AB38 -> 33944.31 | AD38: =X38-AC38 -> 0 | AE38: =S38 -> 20979.65
B39: 2027/01 | C39: Export | D39: HDFC | E39: BRAVO INTERNATIONAL CZ S R O | F39: 469BC89253430007 | G39: 5400513913 | H39: 01-APR-2026 | I39: 32599.25 | J39: EUR | K39: 109.87 | L39: =I39*K39 -> 3581679.6 | M39: 12964.66 | N39: 0 | O39: 0 | P39: 0 | Q39: 0 | R39: 0 | S39: 2863.35 | T39: 0 | U39: 0 | V39: 0 | W39: =IFERROR(M39/L39*100,0) -> 0.36197152 | X39: =SUM(M39:U39) -> 15828.01 | Y39: =SUMIFS(SAP!H:H,SAP!L:L,Retirement!F39,SAP!V:V,Retirement!B39) -> 15828.01 | Z39: =ROUND(Y39-X39,0) -> 0 | AA39: =M39 -> 12964.66 | AB39: =S39 -> 2863.35 | AC39: =AA39+AB39 -> 15828.01 | AD39: =X39-AC39 -> 0 | AE39: =S39 -> 2863.35
B40: 2027/01 | C40: Export | D40: HDFC | E40: TOPANEL PRODUCTION PANELS S.A | F40: 469BC89253460001 | G40: 5400513924 | H40: 01-APR-2026 | I40: 170906.2 | J40: EUR | K40: 109.87 | L40: =I40*K40 -> 18777464 | M40: 15381.8 | N40: 0 | O40: 0 | P40: 0 | Q40: 0 | R40: 0 | S40: 0 | T40: 0 | U40: 0 | V40: 0 | W40: =IFERROR(M40/L40*100,0) -> 0.081916279 | X40: =SUM(M40:U40) -> 15381.8 | Y40: =SUMIFS(SAP!H:H,SAP!L:L,Retirement!F40,SAP!V:V,Retirement!B40) -> 15381.8 | Z40: =ROUND(Y40-X40,0) -> 0 | AA40: =M40 -> 15381.8 | AB40: =U40 -> 0 | AC40: =AA40+AB40 -> 15381.8 | AD40: =X40-AC40 -> 0 | AE40: =S40 -> 0
B41: 2027/01 | C41: Export | D41: HDFC | E41: TOPANEL PRODUCTION PANELS S.A | F41: 469BC89253560001 | G41: 5400513926 | H41: 14-APR-2026 | I41: 76750.82 | J41: EUR | K41: 113.13 | L41: =I41*K41 -> 8682820.3 | M41: 15838.2 | N41: 0 | O41: 0 | P41: 0 | Q41: 0 | R41: 0 | S41: 0 | T41: 0 | U41: 0 | V41: 0 | W41: =IFERROR(M41/L41*100,0) -> 0.18240847 | X41: =SUM(M41:U41) -> 15838.2 | Y41: =SUMIFS(SAP!H:H,SAP!L:L,Retirement!F41,SAP!V:V,Retirement!B41,SAP!P:P, "Retirement Chgs") -> 15838.2 | Z41: =ROUND(Y41-X41,0) -> 0 | AA41: =M41 -> 15838.2 | AB41: =U41 -> 0 | AC41: =AA41+AB41 -> 15838.2 | AD41: =X41-AC41 -> 0 | AE41: =S41 -> 0
B42: 2027/01 | C42: Export | D42: HDFC | E42: ITALPANNELLI IBERICA, S.A. | F42: 469BC89260190002 | G42: 5400513944 | H42: 14-APR-2026 | I42: 104306.16 | J42: EUR | K42: 113.13 | L42: =I42*K42 -> 11800156 | M42: 18666.45 | N42: 0 | O42: 0 | P42: 0 | Q42: 0 | R42: 0 | S42: 1763.73 | T42: 0 | U42: 0 | V42: 0 | W42: =IFERROR(M42/L42*100,0) -> 0.15818816 | X42: =SUM(M42:U42) -> 20430.18 | Y42: =SUMIFS(SAP!H:H,SAP!L:L,Retirement!F42,SAP!V:V,Retirement!B42) -> 20430.18 | Z42: =ROUND(Y42-X42,0) -> 0 | AA42: =M42 -> 18666.45 | AB42: =S42 -> 1763.73 | AC42: =AA42+AB42 -> 20430.18 | AD42: =X42-AC42 -> 0 | AE42: =S42 -> 1763.73
B43: 2027/01 | C43: Export | D43: HDFC | E43: KAMARIDIS GLOBAL WIRE S A | F43: 469BC89260220005 | G43: 5400513953 | H43: 15-APR-2026 | I43: 255325.54 | J43: EUR | K43: 113.13 | L43: =I43*K43 -> 28884978 | M43: 3959.55 | N43: 0 | O43: 0 | P43: 0 | Q43: 0 | R43: 0 | S43: 0 | T43: 0 | U43: 0 | V43: 0 | W43: =IFERROR(M43/L43*100,0) -> 0.01370799 | X43: =SUM(M43:U43) -> 3959.55 | Y43: =SUMIFS(SAP!H:H,SAP!L:L,Retirement!F43,SAP!V:V,Retirement!B43) -> 3959.55 | Z43: =ROUND(Y43-X43,0) -> 0 | AA43: =M43 -> 3959.55 | AB43: =U43 -> 0 | AC43: =AA43+AB43 -> 3959.55 | AD43: =X43-AC43 -> 0 | AE43: =S43 -> 0
B44: 2027/01 | C44: Export | D44: HDFC | E44: TOPANEL PRODUCTION PANELS S.A | F44: 469BC89260290005 | G44: 5400513963 | H44: 21-APR-2026 | I44: 547919.68 | J44: EUR | K44: 112.95 | L44: =I44*K44 -> 61887528 | M44: 4518 | N44: 0 | O44: 0 | P44: 0 | Q44: 0 | R44: 0 | S44: 0 | T44: 0 | U44: 0 | V44: 0 | W44: =IFERROR(M44/L44*100,0) -> 0.0073003401 | X44: =SUM(M44:U44) -> 4518 | Y44: =SUMIFS(SAP!H:H,SAP!L:L,Retirement!F44,SAP!V:V,Retirement!B44) -> 4518 | Z44: =ROUND(Y44-X44,0) -> 0 | AA44: =M44 -> 4518 | AB44: =U44 -> 0 | AC44: =AA44+AB44 -> 4518 | AD44: =X44-AC44 -> 0 | AE44: =S44 -> 0
B45: 2027/01 | C45: Export | D45: HDFC | E45: BRAVO INTERNATIONAL CZ S R O | F45: 469BC89260350001 | G45: 5400513904 | H45: 01-APR-2026 | I45: 188650.1 | J45: EUR | K45: 109.87 | L45: =I45*K45 -> 20726986 | M45: 12964.66 | N45: 0 | O45: 0 | P45: 0 | Q45: 0 | R45: 0 | S45: 6746.76 | T45: 0 | U45: 0 | V45: 0 | W45: =IFERROR(M45/L45*100,0) -> 0.062549662 | X45: =SUM(M45:U45) -> 19711.42 | Y45: =SUMIFS(SAP!H:H,SAP!L:L,Retirement!F45,SAP!V:V,Retirement!B45) -> 19711.42 | Z45: =ROUND(Y45-X45,0) -> 0 | AA45: =M45 -> 12964.66 | AB45: =S45 -> 6746.76 | AC45: =AA45+AB45 -> 19711.42 | AD45: =X45-AC45 -> 0 | AE45: =S45 -> 6746.76
B46: 2027/01 | C46: Export | D46: HDFC | E46: KAMARIDIS GLOBAL WIRE S A | F46: 469BC89260360013 | G46: 5400513977 | H46: 28-APR-2026 | I46: 240712.5 | J46: EUR | K46: 113.9 | L46: =I46*K46 -> 27417154 | M46: 6264.5 | N46: 0 | O46: 0 | P46: 0 | Q46: 0 | R46: 0 | S46: 0 | T46: 0 | U46: 0 | V46: 0 | W46: =IFERROR(M46/L46*100,0) -> 0.022848834 | X46: =SUM(M46:U46) -> 6264.5 | Y46: =SUMIFS(SAP!H:H,SAP!L:L,Retirement!F46,SAP!V:V,Retirement!B46) -> 6264.5 | Z46: =ROUND(Y46-X46,0) -> 0 | AA46: =M46 -> 6264.5 | AB46: =U46 -> 0 | AC46: =AA46+AB46 -> 6264.5 | AD46: =X46-AC46 -> 0 | AE46: =S46 -> 0
B47: 2027/01 | C47: Export | D47: HDFC | E47: LATTONEDIL S P A MILANO | F47: 469BC89260370003 | G47: 5400513966 | H47: 01-APR-2026 | I47: 406021.91 | J47: EUR | K47: 109.0298 | L47: =I47*K47 -> 44268488 | N47: 0 | O47: 0 | P47: 0 | Q47: 0 | R47: 0 | S47: =6762.03 -> 6762.03 | T47: 0 | U47: 0 | V47: 0 | W47: =IFERROR(S47/L47*100,0) -> 0.015275042 | X47: =SUM(M47:U47) -> 6762.03 | Y47: =SUMIFS(SAP!H:H,SAP!L:L,Retirement!F47,SAP!V:V,Retirement!B47,SAP!P:P, "penal interest") -> 6762.03 | Z47: =ROUND(Y47-X47,0) -> 0 | AA47: =O47 -> 0 | AB47: =S47 -> 6762.03 | AC47: =AA47+AB47 -> 6762.03 | AD47: =X47-AC47 -> 0 | AE47: =S47 -> 6762.03
B48: 2027/01 | C48: Export | D48: HDFC | E48: LATTONEDIL S P A MILANO | F48: 469BC89260470003 | G48: 5400514002 | H48: 13-APR-2026 | I48: 250827.2 | J48: EUR | K48: 113.13 | L48: =I48*K48 -> 28376081 | M48: 5656.5 | N48: 0 | O48: 0 | P48: 0 | Q48: 0 | R48: 0 | S48: 0 | T48: 0 | U48: 0 | V48: 0 | W48: =IFERROR(M48/L48*100,0) -> 0.019934042 | X48: =SUM(M48:U48) -> 5656.5 | Y48: =SUMIFS(SAP!H:H,SAP!L:L,Retirement!F48,SAP!V:V,Retirement!B48) -> 5656.5 | Z48: =ROUND(Y48-X48,0) -> 0 | AA48: =M48 -> 5656.5 | AB48: =U48 -> 0 | AC48: =AA48+AB48 -> 5656.5 | AD48: =X48-AC48 -> 0 | AE48: =S48 -> 0
B49: 2027/01 | C49: Export | D49: HDFC | E49: LATTONEDIL ROMANIA SRL | F49: 469BC89260500003 | G49: 5400513983 | H49: 07-APR-2026 | I49: 543960.24 | J49: EUR | K49: 110.86 | L49: =I49*K49 -> 60303432 | M49: 25497.8 | N49: 0 | O49: 0 | P49: 0 | Q49: 0 | R49: 0 | S49: 0 | T49: 0 | U49: 0 | V49: 0 | W49: =IFERROR(M49/L49*100,0) -> 0.042282502 | X49: =SUM(M49:U49) -> 25497.8 | Y49: =SUMIFS(SAP!H:H,SAP!L:L,Retirement!F49,SAP!V:V,Retirement!B49) -> 25497.8 | Z49: =ROUND(Y49-X49,0) -> 0 | AA49: =M49 -> 25497.8 | AB49: =U49 -> 0 | AC49: =AA49+AB49 -> 25497.8 | AD49: =X49-AC49 -> 0 | AE49: =S49 -> 0
B50: 2027/01 | C50: Export | D50: HDFC | E50: LATTONEDIL S P A MILANO | F50: 469BC89260630001 | G50: 5400513998 | H50: 27-APR-2026 | I50: 419473.6 | J50: EUR | K50: 113.56 | L50: =I50*K50 -> 47635422 | M50: 48407.22 | N50: 0 | O50: 0 | P50: 0 | Q50: 0 | R50: 0 | S50: 0 | T50: 0 | U50: 0 | V50: 0 | W50: =IFERROR(M50/L50*100,0) -> 0.10162022 | X50: =SUM(M50:U50) -> 48407.22 | Y50: =SUMIFS(SAP!H:H,SAP!L:L,Retirement!F50,SAP!V:V,Retirement!B50) -> 48407.22 | Z50: =ROUND(Y50-X50,0) -> 0 | AA50: =M50 -> 48407.22 | AB50: =U50 -> 0 | AC50: =AA50+AB50 -> 48407.22 | AD50: =X50-AC50 -> 0 | AE50: =S50 -> 0
B51: 2027/01 | C51: Export | D51: HDFC | E51: LATTONEDIL S P A MILANO | F51: 469BC89260650002 | G51: 5400514025 | H51: 27-APR-2026 | I51: 268709.6 | J51: EUR | K51: 113.56 | L51: =I51*K51 -> 30514662 | M51: 5678 | N51: 0 | O51: 0 | P51: 0 | Q51: 0 | R51: 0 | S51: 0 | T51: 0 | U51: 0 | V51: 0 | W51: =IFERROR(M51/L51*100,0) -> 0.018607448 | X51: =SUM(M51:U51) -> 5678 | Y51: =SUMIFS(SAP!H:H,SAP!L:L,Retirement!F51,SAP!V:V,Retirement!B51) -> 5678 | Z51: =ROUND(Y51-X51,0) -> 0 | AA51: =M51 -> 5678 | AB51: =U51 -> 0 | AC51: =AA51+AB51 -> 5678 | AD51: =X51-AC51 -> 0 | AE51: =S51 -> 0
B52: 2027/01 | C52: Export | D52: HDFC | E52: LATTONEDIL S P A MILANO | F52: 469BC89260650003 | G52: 5400514013 | H52: 23-APR-2026 | I52: 312104 | J52: EUR | K52: 112.98 | L52: =I52*K52 -> 35261510 | M52: 25049.93 | N52: 0 | O52: 0 | P52: 0 | Q52: 0 | R52: 0 | S52: 0 | T52: 0 | U52: 0 | V52: 0 | W52: =IFERROR(M52/L52*100,0) -> 0.071040435 | X52: =SUM(M52:U52) -> 25049.93 | Y52: =SUMIFS(SAP!H:H,SAP!L:L,Retirement!F52,SAP!V:V,Retirement!B52) -> 25049.93 | Z52: =ROUND(Y52-X52,0) -> 0 | AA52: =M52 -> 25049.93 | AB52: =U52 -> 0 | AC52: =AA52+AB52 -> 25049.93 | AD52: =X52-AC52 -> 0 | AE52: =S52 -> 0
B53: 2027/01 | C53: Export | D53: HDFC | E53: PAUL COM SRL | F53: 469BC63260990002 | G53: 5400513749 | H53: 09-APR-2026 | I53: 24998.3 | J53: EUR | K53: =L53/I53 -> 99.55 | L53: 2488580.8 | M53: 0 | N53: 2000 | O53: 0 | P53: 0 | Q53: 0 | R53: 0 | S53: 0 | T53: 0 | U53: 0 | V53: 360 | W53: =IFERROR(N53/L53*100,0) -> 0.080367092 | X53: =SUM(M53:U53) -> 2000 | Y53: =SUMIFS(SAP!H:H,SAP!L:L,Retirement!F53,SAP!V:V,Retirement!B53) -> 2000 | Z53: =ROUND(Y53-X53,0) -> 0 | AA53: =N53 -> 2000 | AB53: =U53 -> 0 | AC53: =AA53+AB53 -> 2000 | AD53: =X53-AC53 -> 0 | AE53: =S53 -> 0
B54: 2027/01 | C54: Export | D54: HDFC | E54: STEEL HUB LLC | F54: 469BC63260990003 | G54: 5400513932 | H54: 09-APR-2026 | I54: 238985.37 | J54: USD | L54: =I54*K54 -> 0 | M54: 0 | N54: 2000 | O54: 0 | P54: 0 | Q54: 0 | R54: 0 | S54: 0 | T54: 0 | U54: 0 | V54: 360 | W54: =IFERROR(N54/L54*100,0) -> 0 | X54: =SUM(M54:U54) -> 2000 | Y54: =SUMIFS(SAP!H:H,SAP!L:L,Retirement!F54,SAP!V:V,Retirement!B54) -> 2000 | Z54: =ROUND(Y54-X54,0) -> 0 | AA54: =N54 -> 2000 | AB54: =U54 -> 0 | AC54: =AA54+AB54 -> 2000 | AD54: =X54-AC54 -> 0 | AE54: =S54 -> 0
B55: 2027/01 | C55: Export | D55: HDFC | E55: MTC CONSTRUCT SRL | F55: 469BC73260920020 | G55: 5400513991 | H55: 02-APR-2026 | I55: 129009.24 | J55: EUR | K55: =L55/I55 -> 103.47973 | L55: 13349841 | M55: 0 | N55: 2000 | O55: 0 | P55: 0 | Q55: 0 | R55: 0 | S55: 0 | T55: 0 | U55: 0 | V55: 360 | W55: =IFERROR(N55/L55*100,0) -> 0.014981451 | X55: =SUM(M55:U55) -> 2000 | Y55: =SUMIFS(SAP!H:H,SAP!L:L,Retirement!F55,SAP!V:V,Retirement!B55) -> 2000 | Z55: =ROUND(Y55-X55,0) -> 0 | AA55: =N55 -> 2000 | AB55: =U55 -> 0 | AC55: =AA55+AB55 -> 2000 | AD55: =X55-AC55 -> 0 | AE55: =S55 -> 0
B56: 2027/01 | C56: Export | D56: HDFC | E56: OLIMP-IMPEX SRL | F56: 469BC73260940004 | G56: 5400513975 | H56: 06-APR-2026 | I56: 198384.05 | J56: EUR | K56: =L56/I56 -> 103.35 | L56: 20502992 | M56: 0 | N56: 2000 | O56: 0 | P56: 0 | Q56: 0 | R56: 0 | S56: 0 | T56: 0 | U56: 0 | V56: 360 | W56: =IFERROR(N56/L56*100,0) -> 0.0097546741 | X56: =SUM(M56:U56) -> 2000 | Y56: =SUMIFS(SAP!H:H,SAP!L:L,Retirement!F56,SAP!V:V,Retirement!B56) -> 2000 | Z56: =ROUND(Y56-X56,0) -> 0 | AA56: =N56 -> 2000 | AB56: =U56 -> 0 | AC56: =AA56+AB56 -> 2000 | AD56: =X56-AC56 -> 0 | AE56: =S56 -> 0
B57: 2027/01 | C57: Export | D57: HDFC | E57: 1/LPL DI GIOVANNI CURCELLI FIGLIO | F57: 469BC73260970007 | G57: MCEX12782122 | H57: 07-APR-2026 | I57: 25209.15 | J57: EUR | L57: =I57*K57 -> 0 | M57: 0 | N57: 2000 | O57: 0 | P57: 0 | Q57: 0 | R57: 0 | S57: 0 | T57: 0 | U57: 0 | V57: 360 | W57: =IFERROR(N57/L57*100,0) -> 0 | X57: =SUM(M57:U57) -> 2000 | Y57: =SUMIFS(SAP!H:H,SAP!L:L,Retirement!F57,SAP!V:V,Retirement!B57) -> 2000 | Z57: =ROUND(Y57-X57,0) -> 0 | AA57: =N57 -> 2000 | AB57: =U57 -> 0 | AC57: =AA57+AB57 -> 2000 | AD57: =X57-AC57 -> 0 | AE57: =S57 -> 0
B58: 2027/01 | C58: Export | D58: HDFC | E58: NODEN INTERNATIONAL LIMITED | F58: 469BC73260990003 | G58: 5400513748 | H58: 09-APR-2026 | I58: 147979.24 | J58: EUR | L58: =I58*K58 -> 0 | M58: 0 | N58: 2000 | O58: 0 | P58: 0 | Q58: 0 | R58: 0 | S58: 0 | T58: 0 | U58: 0 | V58: 360 | W58: =IFERROR(N58/L58*100,0) -> 0 | X58: =SUM(M58:U58) -> 2000 | Y58: =SUMIFS(SAP!H:H,SAP!L:L,Retirement!F58,SAP!V:V,Retirement!B58) -> 2000 | Z58: =ROUND(Y58-X58,0) -> 0 | AA58: =N58 -> 2000 | AB58: =U58 -> 0 | AC58: =AA58+AB58 -> 2000 | AD58: =X58-AC58 -> 0 | AE58: =S58 -> 0
B59: 2027/01 | C59: Export | D59: HDFC | E59: TOPANEL PRODUCTION PANELS S.A | F59: 469BC89260280004 | G59: 5400513958 | H59: 20-APR-2026 | I59: 455971.17 | J59: EUR | K59: =L59/I59 -> 103.7 | L59: 47284210 | M59: 101756 | N59: 0 | O59: 0 | P59: 0 | Q59: 0 | R59: 0 | S59: 0 | T59: 0 | U59: 0 | V59: =M59*0.18 -> 18316.08 | W59: =IFERROR(N59/L59*100,0) -> 0 | X59: =SUM(M59:U59) -> 101756 | Y59: =SUMIFS(SAP!H:H,SAP!L:L,Retirement!F59,SAP!V:V,Retirement!B59) -> 101756.49 | Z59: =ROUND(Y59-X59,0) -> 0 | AA59: =M59 -> 101756 | AB59: =U59 -> 0 | AC59: =AA59+AB59 -> 101756 | AD59: =X59-AC59 -> 0 | AE59: =S59 -> 0 | AG59: Advice not Available
B60: 2027/01 | C60: Domestic | D60: HDFC | E60: JINDAL STEEL ODISHA LIMITED | F60: 469BC04260150013 | G60: RV8110056659 | H60: 46120 | I60: 7616066 | J60: INR | L60: 7616066 | M60: 0 | N60: 2500 | O60: 0 | P60: 0 | Q60: 0 | R60: 0 | S60: 0 | T60: 100 | U60: 0 | V60: =N60*0.18+T60*0.18 -> 468 | W60: =IFERROR(N60/L60*100,0) -> 0.032825346 | X60: =SUM(M60:U60) -> 2600 | Y60: =SUMIFS(SAP!H:H,SAP!L:L,Retirement!F60,SAP!V:V,Retirement!B60) -> 2600 | Z60: =ROUND(Y60-X60,0) -> 0 | AA60: =N60 -> 2500 | AB60: =T60 -> 100 | AC60: =AA60+AB60 -> 2600 | AD60: =X60-AC60 -> 0 | AE60: =S60 -> 0
B61: 2027/01 | C61: Domestic | D61: HDFC | E61: JINDAL STEEL ODISHA LIMITED | F61: 469BC04260210004 | G61: RV8110059428 | H61: 46129 | I61: 5153861 | J61: INR | L61: 5153861 | M61: 0 | N61: 2500 | O61: 0 | P61: 0 | Q61: 0 | R61: 0 | S61: 0 | T61: 100 | U61: 0 | V61: =N61*0.18+T61*0.18 -> 468 | W61: =IFERROR(N61/L61*100,0) -> 0.048507323 | X61: =SUM(M61:U61) -> 2600 | Y61: =SUMIFS(SAP!H:H,SAP!L:L,Retirement!F61,SAP!V:V,Retirement!B61) -> 2600 | Z61: =ROUND(Y61-X61,0) -> 0 | AA61: =N61 -> 2500 | AB61: =T61 -> 100 | AC61: =AA61+AB61 -> 2600 | AD61: =X61-AC61 -> 0 | AE61: =S61 -> 0
B62: 2027/01 | C62: Domestic | D62: HDFC | E62: JINDAL STEEL ODISHA LIMITED | F62: 469BC04260270002 | G62: RV8110059713 | H62: 46130 | I62: 4894240 | J62: INR | L62: 4894240 | M62: 0 | N62: 2500 | O62: 0 | P62: 0 | Q62: 0 | R62: 0 | S62: 0 | T62: 100 | U62: 0 | V62: =N62*0.18+T62*0.18 -> 468 | W62: =IFERROR(N62/L62*100,0) -> 0.051080454 | X62: =SUM(M62:U62) -> 2600 | Y62: =SUMIFS(SAP!H:H,SAP!L:L,Retirement!F62,SAP!V:V,Retirement!B62) -> 2600 | Z62: =ROUND(Y62-X62,0) -> 0 | AA62: =N62 -> 2500 | AB62: =T62 -> 100 | AC62: =AA62+AB62 -> 2600 | AD62: =X62-AC62 -> 0 | AE62: =S62 -> 0
B63: 2027/01 | C63: Domestic | D63: HDFC | E63: JINDAL STEEL ODISHA LIMITED | F63: 469BC04260270003 | G63: RV8110059713 | H63: 46130 | I63: 2441615 | J63: INR | L63: 2441615 | M63: 0 | N63: 2500 | O63: 0 | P63: 0 | Q63: 0 | R63: 0 | S63: 0 | T63: 100 | U63: 0 | V63: =N63*0.18+T63*0.18 -> 468 | W63: =IFERROR(N63/L63*100,0) -> 0.10239125 | X63: =SUM(M63:U63) -> 2600 | Y63: =SUMIFS(SAP!H:H,SAP!L:L,Retirement!F63,SAP!V:V,Retirement!B63) -> 2600 | Z63: =ROUND(Y63-X63,0) -> 0 | AA63: =N63 -> 2500 | AB63: =T63 -> 100 | AC63: =AA63+AB63 -> 2600 | AD63: =X63-AC63 -> 0 | AE63: =S63 -> 0
B64: 2027/01 | C64: Domestic | D64: HDFC | E64: JINDAL STEEL ODISHA LIMITED | F64: 469BC04260280004 | G64: RV8110060329 | H64: 20-APR-2026 | I64: 4973446 | J64: INR | L64: 4973446 | M64: 0 | N64: 2500 | O64: 0 | P64: 0 | Q64: 0 | R64: 0 | S64: 0 | T64: 100 | U64: 0 | V64: =N64*0.18+T64*0.18 -> 468 | W64: =IFERROR(N64/L64*100,0) -> 0.050266958 | X64: =SUM(M64:U64) -> 2600 | Y64: =SUMIFS(SAP!H:H,SAP!L:L,Retirement!F64,SAP!V:V,Retirement!B64) -> 2600 | Z64: =ROUND(Y64-X64,0) -> 0 | AA64: =N64 -> 2500 | AB64: =T64 -> 100 | AC64: =AA64+AB64 -> 2600 | AD64: =X64-AC64 -> 0 | AE64: =S64 -> 0
B65: 2027/01 | C65: Export | D65: HDFC | E65: PAGOUNI SA | F65: 469BC89260090006 | G65: 5400513947 | H65: 07-APR-2026 | I65: 132350.78 | J65: EUR | K65: 110.86 | L65: =I65*K65 -> 14672407 | M65: 7205.9 | N65: 0 | O65: 0 | P65: 0 | Q65: -41645.14 | R65: 0 | S65: 0 | T65: 0 | U65: 0 | V65: =M65*0.18 -> 1297.062 | W65: =IFERROR(N65/L65*100,0) -> 0 | X65: =SUM(M65:U65) -> -34439.24 | Y65: =SUMIFS(SAP!H:H,SAP!L:L,Retirement!F65,SAP!V:V,Retirement!B65) -> -34439.24 | Z65: =ROUND(Y65-X65,0) -> 0 | AA65: =M65 -> 7205.9 | AB65: =Q65 -> -41645.14 | AC65: =AA65+AB65 -> -34439.24 | AD65: =X65-AC65 -> 0 | AE65: =S65 -> 0
B66: 2027/01 | C66: Export | D66: HDFC | E66: LATTONEDIL S P A MILANO | F66: 469BC89260470004 | G66: 5400514000 | H66: 46125 | I66: 274699.2 | J66: EUR | K66: 113.13 | L66: =I66*K66 -> 31076720 | M66: 5656.5 | N66: 0 | O66: 0 | P66: 0 | Q66: 0 | R66: 0 | S66: 0 | T66: 0 | U66: 0 | V66: =M66*0.18 -> 1018.17 | W66: =IFERROR(N66/L66*100,0) -> 0 | X66: =SUM(M66:U66) -> 5656.5 | Y66: =SUMIFS(SAP!H:H,SAP!L:L,Retirement!F66,SAP!V:V,Retirement!B66) -> 5656.5 | Z66: =ROUND(Y66-X66,0) -> 0 | AA66: =M66 -> 5656.5 | AB66: =Q66 -> 0 | AC66: =AA66+AB66 -> 5656.5 | AD66: =X66-AC66 -> 0 | AE66: =S66 -> 0
B67: 2027/01 | C67: Export | D67: HDFC | E67: TOPANEL PRODUCTION PANELS S.A | F67: 469BC89253540002 | G67: 5400513927 | H67: 46126 | I67: 218980.7 | J67: EUR | N67: 0 | O67: 0 | P67: 10245.7 | Q67: 0 | R67: 0 | S67: 0 | T67: 0 | U67: 0 | V67: =M67*0.18 -> 0 | W67: =IFERROR(N67/L67*100,0) -> 0 | X67: =SUM(M67:U67) -> 10245.7 | Y67: =SUMIFS(SAP!H:H,SAP!L:L,Retirement!F67,SAP!V:V,Retirement!B67) -> 10245.7 | Z67: =ROUND(Y67-X67,0) -> 0 | AA67: =M67 -> 0 | AB67: =P67 -> 10245.7 | AC67: =AA67+AB67 -> 10245.7 | AD67: =X67-AC67 -> 0 | AE67: =S67 -> 0
B68: 2027/01 | C68: Export | D68: HDFC | E68: LATTONEDIL S P A MILANO | F68: 469BC89260510001 | G68: 5400514009 | H68: 46128 | I68: 412314.06 | J68: EUR | K68: 112.33 | L68: =I68*K68 -> 46315238 | M68: 11233 | N68: 0 | O68: 0 | P68: 0 | Q68: 0 | R68: 0 | S68: 0 | T68: 0 | U68: 0 | V68: =M68*0.18 -> 2021.94 | W68: =IFERROR(N68/L68*100,0) -> 0 | X68: =SUM(M68:U68) -> 11233 | Y68: =SUMIFS(SAP!H:H,SAP!L:L,Retirement!F68,SAP!V:V,Retirement!B68) -> 11233 | Z68: =ROUND(Y68-X68,0) -> 0 | AA68: =M68 -> 11233 | AB68: =Q68 -> 0 | AC68: =AA68+AB68 -> 11233 | AD68: =X68-AC68 -> 0 | AE68: =S68 -> 0
B69: 2027/01 | C69: Export | D69: HDFC | E69: LATTONEDIL S P A MILANO | F69: 469BC89260560004 | G69: 5400513981 | H69: 46128 | I69: 288044.11 | J69: EUR | K69: 107.135 | L69: =I69*K69 -> 30859606 | M69: 0 | N69: 0 | O69: 0 | P69: 0 | Q69: -12141.61 | R69: 0 | S69: 0 | T69: 0 | U69: 0 | V69: =M69*0.18 -> 0 | W69: =IFERROR(N69/L69*100,0) -> 0 | X69: =SUM(M69:U69) -> -12141.61 | Y69: =SUMIFS(SAP!H:H,SAP!L:L,Retirement!F69,SAP!V:V,Retirement!B69) -> -12141.61 | Z69: =ROUND(Y69-X69,0) -> 0 | AA69: =M69 -> 0 | AB69: =Q69 -> -12141.61 | AC69: =AA69+AB69 -> -12141.61 | AD69: =X69-AC69 -> 0 | AE69: =S69 -> 0
B70: 2027/01 | C70: Export | D70: HDFC | E70: LATTONEDIL ROMANIA SRL | F70: 469BC89261070001 | G70: 5400514099 | H70: 46129 | I70: 123340.16 | J70: EUR | K70: 109.41 | L70: =I70*K70 -> 13494647 | M70: 0 | N70: 0 | O70: 0 | P70: 4267.02 | Q70: 0 | R70: 0 | S70: 0 | T70: 0 | U70: 0 | V70: =M70*0.18 -> 0 | W70: =IFERROR(N70/L70*100,0) -> 0 | X70: =SUM(M70:U70) -> 4267.02 | Y70: =SUMIFS(SAP!H:H,SAP!L:L,Retirement!F70,SAP!V:V,Retirement!B70,SAP!P:P, "retirement chgs") -> 4267.02 | Z70: =ROUND(Y70-X70,0) -> 0 | AA70: =M70 -> 0 | AB70: =P70 -> 4267.02 | AC70: =AA70+AB70 -> 4267.02 | AD70: =X70-AC70 -> 0 | AE70: =S70 -> 0
B71: 2027/01 | C71: Export | D71: INDIAN | E71: HONORS COMMODITY HONG KONG COMPANY | F71: 0571025FBU000186 | H71: 02-04-2026 | I71: 1654544.3 | J71: USD | K71: 92.985 | L71: =I71*K71 -> 1.538478e+08 | M71: 0 | N71: 25000 | O71: 9298.5 | P71: 2400693 | Q71: 0 | R71: 0 | S71: 0 | T71: 0 | U71: 550 | V71: 4599 | W71: =IFERROR(N71/L71*100,0) -> 0.016249826 | X71: =SUM(M71:U71) -> 2435541.5 | Y71: =SUMIFS(SAP!H:H,SAP!L:L,Retirement!F71,SAP!V:V,Retirement!B71,SAP!P:P, "retirement chgs") -> 2435540.8 | Z71: =ROUND(Y71-X71,0) -> -1 | AA71: =N71 -> 25000 | AB71: =U71+O71+P71 -> 2410541.5 | AC71: =AA71+AB71 -> 2435541.5 | AD71: =X71-AC71 -> 0 | AE71: =S71 -> 0
B72: 2027/01 | C72: Domestic | D72: KOTAK | E72: JINDAL STEEL ODISHA LIMITED | F72: ILD261062308C001 | G72: JDM/13870 | H72: 27-Apr-2026 | I72: 9867685 | J72: INR | K72: 0 | L72: =I72 -> 9867685 | M72: 0 | N72: 1250 | O72: 0 | P72: 0 | Q72: 0 | R72: 0 | S72: 0 | T72: 0 | U72: 500 | V72: 315 | W72: =IFERROR(N72/L72*100,0) -> 0.012667612 | X72: =SUM(M72:U72) -> 1750 | Y72: =SUMIFS(SAP!H:H,SAP!M:M,Retirement!F72,SAP!V:V,Retirement!B72) -> 1750 | Z72: =ROUND(Y72-X72,0) -> 0 | AA72: =N72 -> 1250 | AB72: =U72 -> 500 | AC72: =AA72+AB72 -> 1750 | AD72: =X72-AC72 -> 0 | AE72: =S72 -> 0
B73: 2027/01 | C73: Domestic | D73: KOTAK | E73: JINDAL STEEL ODISHA LIMITED | F73: ILD261062308C002 | G73: RV8110062145 | H73: 27-Apr-2026 | I73: 5033690 | J73: INR | K73: 0 | L73: =I73 -> 5033690 | M73: 0 | N73: 1250 | O73: 0 | P73: 0 | Q73: 0 | R73: 0 | S73: 0 | T73: 0 | U73: 500 | V73: 315 | W73: =IFERROR(N73/L73*100,0) -> 0.024832677 | X73: =SUM(M73:U73) -> 1750 | Y73: =SUMIFS(SAP!H:H,SAP!M:M,Retirement!F73,SAP!V:V,Retirement!B73) -> 1750 | Z73: =ROUND(Y73-X73,0) -> 0 | AA73: =N73 -> 1250 | AB73: =U73 -> 500 | AC73: =AA73+AB73 -> 1750 | AD73: =X73-AC73 -> 0 | AE73: =S73 -> 0
B74: 2027/01 | C74: Domestic | D74: KOTAK | E74: JINDAL STEEL ODISHA LIMITED | F74: ILD261062308C003 | G74: RV8110061608 | H74: 27-Apr-2026 | I74: 14168342 | J74: INR | K74: 0 | L74: =I74 -> 14168342 | M74: 0 | N74: 1250 | O74: 0 | P74: 0 | Q74: 0 | R74: 0 | S74: 0 | T74: 0 | U74: 500 | V74: 315 | W74: =IFERROR(N74/L74*100,0) -> 0.0088224861 | X74: =SUM(M74:U74) -> 1750 | Y74: =SUMIFS(SAP!H:H,SAP!M:M,Retirement!F74,SAP!V:V,Retirement!B74) -> 1750 | Z74: =ROUND(Y74-X74,0) -> 0 | AA74: =N74 -> 1250 | AB74: =U74 -> 500 | AC74: =AA74+AB74 -> 1750 | AD74: =X74-AC74 -> 0 | AE74: =S74 -> 0
B75: 2027/01 | C75: Export | D75: KOTAK | E75: HONORS COMMODITY HONG KONG | F75: 0552AIR261537713 | G75: DLX2604009 | H75: 46136 | I75: 246400 | J75: USD | K75: 94.25 | L75: =I75*K75 -> 23223200 | M75: 0 | N75: 1250 | O75: 0 | P75: 0 | Q75: 0 | R75: 0 | S75: 0 | T75: 0 | U75: 500 | V75: =90+225+4990.18 -> 5305.18 | W75: =IFERROR(N75/L75*100,0) -> 0.0053825485 | X75: =SUM(M75:U75) -> 1750 | Y75: =SUMIFS(SAP!H:H,SAP!L:L,Retirement!F75,SAP!V:V,Retirement!B75) -> 1750 | Z75: =ROUND(Y75-X75,0) -> 0 | AA75: =N75 -> 1250 | AB75: =U75 -> 500 | AC75: =AA75+AB75 -> 1750 | AD75: =X75-AC75 -> 0 | AE75: =S75 -> 0
B76: 2027/01 | C76: Export | D76: KOTAK | E76: HONORS COMMODITY HONG KONG | F76: 0552AIR261530633 | G76: LY2604003 | H76: 46129 | I76: 174935 | J76: USD | K76: 93.12 | L76: =I76*K76 -> 16289947 | M76: 0 | N76: 1250 | O76: 0 | P76: 0 | Q76: 0 | R76: 0 | S76: 0 | T76: 0 | U76: 500 | V76: =90+225+3742.19 -> 4057.19 | W76: =IFERROR(N76/L76*100,0) -> 0.0076734441 | X76: =SUM(M76:U76) -> 1750 | Y76: =SUMIFS(SAP!H:H,SAP!L:L,Retirement!F76,SAP!V:V,Retirement!B76) -> 1750 | Z76: =ROUND(Y76-X76,0) -> 0 | AA76: =N76 -> 1250 | AB76: =U76 -> 500 | AC76: =AA76+AB76 -> 1750 | AD76: =X76-AC76 -> 0 | AE76: =S76 -> 0
B77: 2027/01 | C77: Export | D77: UBI | E77: HONORS COMMODITY HONG KONG COMPANY | F77: 68840M11F0878425 | H77: 46125 | I77: 229234.72 | J77: USD | K77: 93.37 | L77: =I77*K77 -> 21403646 | M77: 0 | N77: 0 | O77: =30000+9337 -> 39337 | P77: 362014.54 | Q77: 0 | R77: 0 | S77: 0 | T77: 0 | U77: 500 | V77: =5400+90+4729.5 -> 10219.5 | W77: =IFERROR(O77/L77*100,0) -> 0.18378645 | X77: =SUM(M77:U77) -> 401851.54 | Y77: =SUMIFS(SAP!H:H,SAP!L:L,Retirement!F77,SAP!V:V,Retirement!B77) -> 401851.16 | Z77: =ROUND(Y77-X77,0) -> 0 | AA77: =O77 -> 39337 | AB77: =U77+P77 -> 362514.54 | AC77: =AA77+AB77 -> 401851.54 | AD77: =X77-AC77 -> 0 | AE77: =S77 -> 0
B78: 2027/01 | C78: Export | D78: UBI | E78: HONORS COMMODITY HONG KONG COMPANY | F78: 68840M11F0258226 - COR006 | H78: 46122 | I78: 1756216 | J78: USD | K78: 0 | L78: =I78*K78 -> 0 | M78: 0 | N78: 0 | O78: 0 | P78: 0 | Q78: 0 | R78: 0 | S78: 0 | T78: 0 | U78: 500 | V78: 90 | W78: =IFERROR(N78/L78*100,0) -> 0 | X78: =SUM(M78:U78) -> 500 | Y78: =SUMIFS(SAP!H:H,SAP!M:M,Retirement!F78,SAP!V:V,Retirement!B78) -> 500 | Z78: =ROUND(Y78-X78,0) -> 0 | AA78: 0 | AB78: =U78 -> 500 | AC78: =AA78+AB78 -> 500 | AD78: =X78-AC78 -> 0 | AE78: =S78 -> 0
B79: 2027/01 | C79: Export | D79: UBI | E79: HONORS COMMODITY HONG KONG COMPANY | F79: 68840M11F0258226 - COR010 | H79: 46134 | I79: 1756216 | J79: USD | K79: 0 | L79: =I79*K79 -> 0 | M79: 0 | N79: 0 | O79: 0 | P79: 0 | Q79: 0 | R79: 0 | S79: 0 | T79: 0 | U79: 500 | V79: 90 | W79: =IFERROR(N79/L79*100,0) -> 0 | X79: =SUM(M79:U79) -> 500 | Y79: =SUMIFS(SAP!H:H,SAP!M:M,Retirement!F79,SAP!V:V,Retirement!B79) -> 500 | Z79: =ROUND(Y79-X79,0) -> 0 | AA79: 0 | AB79: =U79 -> 500 | AC79: =AA79+AB79 -> 500 | AD79: =X79-AC79 -> 0 | AE79: =S79 -> 0
B80: 2027/01 | C80: Export | D80: UBI | E80: MANAKSIA COATED METALS AND | F80: 68840M11F087842P | H80: 46125 | I80: 1176249.4 | J80: USD | K80: 93.37 | L80: =I80*K80 -> 1.098264e+08 | M80: 0 | N80: 0 | O80: 9337 | P80: 1857569.2 | Q80: 0 | R80: 0 | S80: 0 | T80: 0 | U80: 0 | V80: 0 | W80: =IFERROR(N80/L80*100,0) -> 0 | X80: =SUM(M80:U80) -> 1866906.2 | Y80: =SUMIFS(SAP!H:H,SAP!L:L,Retirement!F80,SAP!P:P, "retirement chgs",SAP!V:V, "2027/01") -> 1866906.1 | Z80: =ROUND(Y80-X80,0) -> 0 | AA80: =O80+P80 -> 1866906.2 | AB80: =U80 -> 0 | AC80: =AA80+AB80 -> 1866906.2 | AD80: =X80-AC80 -> 0 | AE80: =S80 -> 0
B81: 2027/01 | C81: Domestic | D81: UCO | E81: TATA STEEL LIMITED | F81: 0002ILCIS0024725 | G81: 2.5101304e+15 | H81: 46133 | I81: 20000000 | J81: INR | L81: 20000000 | M81: 0 | N81: 0 | O81: 0 | P81: 0 | Q81: 0 | R81: -8334 | S81: 0 | T81: 0 | U81: 0 | V81: =750*2 -> 1500 | W81: =IFERROR(N81/L81*100,0) -> 0 | X81: =SUM(M81:U81) -> -8334 | Y81: =SUMIFS(SAP!H:H,SAP!L:L,Retirement!F81,SAP!P:P, "reversal",SAP!V:V, "2027/01") -> -8333.33 | Z81: =ROUND(Y81-X81,0) -> 1 | AA81: =O81+P81 -> 0 | AB81: =R81 -> -8334 | AC81: =AA81+AB81 -> -8334 | AD81: =X81-AC81 -> 0 | AE81: =S81 -> 0
B82: 2027/01 | C82: Domestic | D82: UCO | E82: TATA STEEL LIMITED | F82: 0002ILCIS0025125 | G82: 2.5101504e+15 | H82: 46133 | I82: 30000000 | J82: INR | L82: 30000000 | M82: 0 | N82: 0 | O82: 0 | P82: 0 | Q82: 0 | R82: -12500 | S82: 0 | T82: 0 | U82: 0 | V82: 2250 | W82: =IFERROR(N82/L82*100,0) -> 0 | X82: =SUM(M82:U82) -> -12500 | Y82: =SUMIFS(SAP!H:H,SAP!L:L,Retirement!F82,SAP!P:P, "reversal",SAP!V:V, "2027/01") -> -12500 | Z82: =ROUND(Y82-X82,0) -> 0 | AA82: =O82+P82 -> 0 | AB82: =R82 -> -12500 | AC82: =AA82+AB82 -> -12500 | AD82: =X82-AC82 -> 0 | AE82: =S82 -> 0
B83: 2027/01 | C83: Domestic | D83: UCO | E83: TATA STEEL LIMITED | F83: 0002ILCIS0025225 | G83: 2.5101604e+15 | H83: 46133 | I83: 50000000 | J83: INR | L83: 50000000 | M83: 0 | N83: 0 | O83: 0 | P83: 0 | Q83: 0 | R83: -20833 | S83: 0 | T83: 0 | U83: 0 | V83: 3750 | W83: =IFERROR(N83/L83*100,0) -> 0 | X83: =SUM(M83:U83) -> -20833 | Y83: =SUMIFS(SAP!H:H,SAP!L:L,Retirement!F83,SAP!P:P, "reversal",SAP!V:V, "2027/01") -> -20833.33 | Z83: =ROUND(Y83-X83,0) -> 0 | AA83: =O83+P83 -> 0 | AB83: =R83 -> -20833 | AC83: =AA83+AB83 -> -20833 | AD83: =X83-AC83 -> 0 | AE83: =S83 -> 0
B84: 2027/01 | C84: Domestic | D84: UCO | E84: JINDAL STEEL ODISHA LIMITED | F84: 0002ILCIS0026625 | G84: 2.5103104e+15 | H84: 46121 | I84: 24000000 | J84: INR | L84: 24000000 | M84: 0 | N84: 0 | O84: 0 | P84: 0 | Q84: 0 | R84: -23000 | S84: 0 | T84: 0 | U84: 0 | V84: 4140 | W84: =IFERROR(N84/L84*100,0) -> 0 | X84: =SUM(M84:U84) -> -23000 | Y84: =SUMIFS(SAP!H:H,SAP!L:L,Retirement!F84,SAP!P:P, "reversal",SAP!V:V, "2027/01") -> -23000 | Z84: =ROUND(Y84-X84,0) -> 0 | AA84: =O84+P84 -> 0 | AB84: =R84 -> -23000 | AC84: =AA84+AB84 -> -23000 | AD84: =X84-AC84 -> 0 | AE84: =S84 -> 0
C85: TOTAL | I85: =SUM(I14:I84) -> 3.0353003e+08 | K85: =SUM(K14:K84) -> 3531.272 | L85: =SUM(L14:L84) -> 1.3337648e+09 | M85: =SUM(M14:M84) -> 777423.71 | N85: =SUM(N14:N84) -> 108250 | O85: =SUM(O14:O84) -> 57972.5 | P85: =SUM(P14:P84) -> 4634789.5 | Q85: =SUM(Q14:Q84) -> -53786.75 | R85: =SUM(R14:R84) -> -64667 | ... V85: =SUM(V14:V84) -> 78295.722 | X85: =SUM(X14:X84) -> 5526537.3 | Y85: =SUM(Y14:Y84) -> 5526536.9 | Z85: =SUM(Z14:Z84) -> 0 | AA85: =SUM(AA14:AA84) -> 2791916.9 | AB85: =SUM(AB14:AB84) -> 2734620.4 | AC85: =SUM(AC14:AC84) -> 5526537.3 | AD85: =SUM(AD14:AD84) -> 0 | AE85: =SUM(AE14:AE84) -> 59505.35
H120: 469BC63260990002 | I120: =VLOOKUP(H120,F:F,1,FALSE) -> 469BC63260990002
H121: 469BC63260990003 | I121: =VLOOKUP(H121,F:F,1,FALSE) -> 469BC63260990003
H122: 469BC73260920020 | I122: =VLOOKUP(H122,F:F,1,FALSE) -> 469BC73260920020
H123: 469BC73260940004 | I123: =VLOOKUP(H123,F:F,1,FALSE) -> 469BC73260940004
H124: 469BC73260970007 | I124: =VLOOKUP(H124,F:F,1,FALSE) -> 469BC73260970007
H125: 469BC73260990003 | I125: =VLOOKUP(H125,F:F,1,FALSE) -> 469BC73260990003
H126: 469BC89261030010 | I126: =VLOOKUP(H126,F:F,1,FALSE) -> #N/A

Sheet Sheet2
B2: Bank Name | C2: Particulars | D2: Reference Number | E2: Amount | F2: Currency
B3: HDFC | C3: PAUL COM SRL | D3: 469BC63260990002 | E3: 24998.3 | F3: EUR
B4: HDFC | C4: STEEL HUB LLC | D4: 469BC63260990003 | E4: 238985.37 | F4: USD
B5: HDFC | C5: MTC CONSTRUCT SRL | D5: 469BC73260920020 | E5: 129009.24 | F5: EUR
B6: HDFC | C6: OLIMP-IMPEX SRL | D6: 469BC73260940004 | E6: 198384.05 | F6: EUR
B7: HDFC | C7: 1/LPL DI GIOVANNI CURCELLI FIGLIO | D7: 469BC73260970007 | E7: 25209.15 | F7: EUR
B8: HDFC | C8: NODEN INTERNATIONAL LIMITED | D8: 469BC73260990003 | E8: 147979.24 | F8: EUR
B9: HDFC | C9: TOPANEL PRODUCTION PANELS S.A | D9: 469BC89260280004 | E9: 455971.17 | F9: EUR
B10: UBI | C10: HONORS COMMODITY HONG KONG COMPANY | D10: 68840M11F0258226 - COR006 | E10: 1756216 | F10: USD
B11: UBI | C11: HONORS COMMODITY HONG KONG COMPANY | D11: 68840M11F0258226 - COR010 | E11: 1756216 | F11: USD

Sheet SAP
A1: Cleared/open items symbol | B1: Assignment | C1: Document Number | D1: Business Area | E1: Document type | F1: Document Date | G1: Posting Key | H1: Amount in local currency | I1: Local Currency | J1: Tax Code | K1: Clearing Document | L1: Reference | N1: Profit Center | O1: Segment | P1: Category | Q1: Text | R1: BOE No. | T1: Offsett.account type | U1: Offsetting acct no. | V1: Year/month | W1: Account | X1: V LOOKUP
B2: 20260402 | C2: 100000178 | D2: KUTC | E2: SA | F2: 46057 | G2: 40 | H2: 15381.8 | I2: INR | L2: 469BC89253460001 | N2: 1021 | P2: Retirement Chgs | Q2: DISCREPANCY CHARGES AGST INV- 5400513924 TOPANEL | V2: 2027/01 | W2: 4501501 | X2: =VLOOKUP(L2,L:P,5,FALSE) -> Retirement Chgs
B3: 20260402 | C3: 100000179 | D3: KUTC | E3: SA | F3: 46057 | G3: 40 | H3: 12964.66 | I3: INR | L3: 469BC89253450002 | N3: 1021 | P3: Retirement Chgs | Q3: DISCREPANCY CHARGES AGST INV- 5400513914 BRAVO INT | V3: 2027/01 | W3: 4501501 | X3: =VLOOKUP(L3,L:P,5,FALSE) -> Retirement Chgs
B4: 20260402 | C4: 100000180 | D4: KUTC | E4: SA | F4: 46057 | G4: 40 | H4: 12964.66 | I4: INR | L4: 469BC89253430007 | N4: 1021 | P4: Retirement Chgs | Q4: DISCREPANCY CHARGES AGST INV- 5400513913 BRAVO INT | V4: 2027/01 | W4: 4501501 | X4: =VLOOKUP(L4,L:P,5,FALSE) -> Retirement Chgs
B5: 20260402 | C5: 100000181 | D5: KUTC | E5: SA | F5: 46057 | G5: 40 | H5: 12964.66 | I5: INR | L5: 469BC89253390001 | N5: 1021 | P5: Retirement Chgs | Q5: DISCREPANCY CHARGES AGST INV- 5400513916 BRAVO INT | V5: 2027/01 | W5: 4501501 | X5: =VLOOKUP(L5,L:P,5,FALSE) -> Retirement Chgs
B6: 20260402 | C6: 100000182 | D6: KUTC | E6: SA | F6: 46057 | G6: 40 | H6: 12964.66 | I6: INR | L6: 469BC89253390002 | N6: 1021 | P6: Retirement Chgs | Q6: DISCREPANCY CHARGES AGST INV- 5400513907 BRAVO INT | V6: 2027/01 | W6: 4501501 | X6: =VLOOKUP(L6,L:P,5,FALSE) -> Retirement Chgs
B7: 20260402 | C7: 100000183 | D7: KUTC | E7: SA | F7: 46057 | G7: 40 | H7: 12964.66 | I7: INR | L7: 469BC89253430003 | N7: 1021 | P7: Retirement Chgs | Q7: DISCREPANCY CHARGES AGST INV- 5400513908 BRAVO INT | V7: 2027/01 | W7: 4501501 | X7: =VLOOKUP(L7,L:P,5,FALSE) -> Retirement Chgs
B8: 20260402 | C8: 100000184 | D8: KUTC | E8: SA | F8: 16-04-2026 | G8: 40 | H8: 15838.2 | I8: INR | L8: 469BC89253560001 | N8: 1021 | P8: Retirement Chgs | Q8: DISCREPANCY CHARGES AGST INV- 5400513926 TOPANEL | V8: 2027/01 | W8: 4501501 | X8: =VLOOKUP(L8,L:P,5,FALSE) -> Retirement Chgs
B9: 20260402 | C9: 100000204 | D9: KUTC | E9: SA | F9: 46057 | G9: 40 | H9: 12964.66 | I9: INR | L9: 469BC89260350001 | N9: 1021 | P9: Retirement Chgs | Q9: DISCREPANCY CHG AGST INV- 5400513904 BRAVO INT | V9: 2027/01 | W9: 4501501 | X9: =VLOOKUP(L9,L:P,5,FALSE) -> Retirement Chgs
B10: 20260402 | C10: 100000495 | D10: KUTC | E10: SA | F10: 46057 | G10: 40 | H10: 9298.5 | I10: INR | L10: 0571025FBU000186 | N10: 1021 | P10: Retirement Chgs | Q10: FUNDING CHG | V10: 2027/01 | W10: 4501501 | X10: =VLOOKUP(L10,L:P,5,FALSE) -> Retirement Chgs
B11: 20260402 | C11: 1900000169 | D11: BEHC | E11: KR | F11: 46057 | G11: 40 | H11: 2000 | I11: INR | J11: 1 | L11: 469BC73260920020 | N11: 3010 | P11: LC Chgs | Q11: BILL COMM AGST INV- 5400513991 MTC CONSTRUCT | V11: 2027/01 | W11: 4501501 | X11: =VLOOKUP(L11,L:P,5,FALSE) -> LC Chgs
B12: 20260402 | C12: 1900000504 | D12: BEHC | E12: KR | F12: 46057 | G12: 40 | H12: 49.5 | I12: INR | J12: 13 | L12: RTGS CHG | N12: 3010 | P12: Others | Q12: RTGS CHG | V12: 2027/01 | W12: 4501501 | X12: =VLOOKUP(L12,L:P,5,FALSE) -> Others
B13: 20260402 | C13: 1900000505 | D13: BEHC | E13: KR | F13: 46057 | G13: 40 | H13: 49.5 | I13: INR | J13: 13 | L13: RTGS CHG | N13: 3010 | P13: Others | Q13: RTGS CHG | V13: 2027/01 | W13: 4501501 | X13: =VLOOKUP(L13,L:P,5,FALSE) -> Others
B14: 20260402 | C14: 1900000506 | D14: BEHC | E14: KR | F14: 46057 | G14: 40 | H14: 24.75 | I14: INR | J14: 1 | L14: NEFT CHG | N14: 3010 | P14: Others | Q14: NEFT CHARGES | V14: 2027/01 | W14: 4501501 | X14: =VLOOKUP(L14,L:P,5,FALSE) -> Others
B15: 20260402 | C15: 1900000537 | D15: BEHC | E15: KR | F15: 46057 | G15: 40 | H15: 550 | I15: INR | J15: 1 | L15: 0571025FBU000186 | N15: 3010 | P15: Retirement Chgs | Q15: SWIFT CHARGES | V15: 2027/01 | W15: 4501501 | X15: =VLOOKUP(L15,L:P,5,FALSE) -> Retirement Chgs
B16: 20260402 | C16: 1900000699 | D16: BEHC | E16: KR | F16: 46057 | G16: 40 | H16: 150 | I16: INR | J16: 1 | L16: BAL CERT CHG | N16: 3010 | P16: Others | Q16: BALANCE CERT CHG | V16: 2027/01 | W16: 4501501 | X16: =VLOOKUP(L16,L:P,5,FALSE) -> Others
B17: 20260403 | C17: 1900000461 | D17: KUTC | E17: KR | F17: 46085 | G17: 40 | H17: 443.04 | I17: INR | J17: 13 | L17: RFU2603311353359 | N17: 1021 | P17: Others | Q17: ACH D- RFU2603311353359-DRBUY5632794 | V17: 2027/01 | W17: 4501501 | X17: =VLOOKUP(L17,L:P,5,FALSE) -> Others
B18: 20260403 | C18: 1900000462 | D18: KUTC | E18: KR | F18: 46085 | G18: 40 | H18: 90.61 | I18: INR | J18: 13 | L18: RFU2603311353360 | N18: 1021 | P18: Others | Q18: ACH D- RFU2603311353360-DRBUY5632790 | V18: 2027/01 | W18: 4501501 | X18: =VLOOKUP(L18,L:P,5,FALSE) -> Others
B19: 20260403 | C19: 1900000464 | D19: KUTC | E19: KR | F19: 46085 | G19: 40 | H19: 209.19 | I19: INR | J19: 13 | L19: RFU2603311353361 | N19: 1021 | P19: Others | Q19: ACH D- RFU2603311353361-DRBUY5632705 | V19: 2027/01 | W19: 4501501 | X19: =VLOOKUP(L19,L:P,5,FALSE) -> Others
B20: 20260403 | C20: 1900000465 | D20: KUTC | E20: KR | F20: 46085 | G20: 40 | H20: 270.16 | I20: INR | J20: 13 | L20: RFU2603311353362 | N20: 1021 | P20: Others | Q20: ACH D- RFU2603311353362-DRBUY5632745 | V20: 2027/01 | W20: 4501501 | X20: =VLOOKUP(L20,L:P,5,FALSE) -> Others
B21: 20260403 | C21: 1900000467 | D21: KUTC | E21: KR | F21: 46085 | G21: 40 | H21: 142.46 | I21: INR | J21: 13 | L21: RFU2603311353363 | N21: 1021 | P21: Others | Q21: ACH D- RFU2603311353363-DRBUY5633246 | V21: 2027/01 | W21: 4501501 | X21: =VLOOKUP(L21,L:P,5,FALSE) -> Others
B22: 20260403 | C22: 1900000468 | D22: KUTC | E22: KR | F22: 46085 | G22: 40 | H22: 171.19 | I22: INR | J22: 13 | L22: RFU2603311353364 | N22: 1021 | P22: Others | Q22: ACH D- RFU2603311353364-DRBUY5633350 | V22: 2027/01 | W22: 4501501 | X22: =VLOOKUP(L22,L:P,5,FALSE) -> Others
... B26: 20260405 | C26: 1900000470 | D26: KUTC | E26: KR | F26: 46146 | G26: 40 | H26: 104.64 | I26: INR | J26: 13 | L26: RFU2604041357266 | N26: 1021 | P26: Others | Q26: ACH D- RFU2604041357266-DRBUY5684407 | V26: 2027/01 | W26: 4501501 | X26: =VLOOKUP(L26,L:P,5,FALSE) -> Others
B27: 20260406 | C27: 1700000054 | D27: BEHC | E27: KA | F27: 46177 | G27: 50 | H27: -211.87 | I27: INR | J27: 13 | L27: 24611381 | N27: 3010 | P27: Others | Q27: Booking Charges for 24611381 | V27: 2027/01 | W27: 4501501 | X27: =VLOOKUP(L27,L:P,5,FALSE) -> Others
B28: 20260406 | C28: 1700000054 | D28: BEHC | E28: KA | F28: 46177 | G28: 50 | H28: -134 | I28: INR | L28: 24611381 | N28: 3010 | P28: Others | Q28: Stamping Charges for 24611381 | V28: 2027/01 | W28: 4501501 | X28: =VLOOKUP(L28,L:P,5,FALSE) -> Others
B29: 20260406 | C29: 1700000055 | D29: BEHC | E29: KA | F29: 46177 | G29: 50 | H29: -211.87 | I29: INR | J29: 13 | L29: 24611382 | N29: 3010 | P29: Others | Q29: Booking Charges for 24611382 | V29: 2027/01 | W29: 4501501 | X29: =VLOOKUP(L29,L:P,5,FALSE) -> Others
B30: 20260406 | C30: 1700000055 | D30: BEHC | E30: KA | F30: 46177 | G30: 50 | H30: -153 | I30: INR | L30: 24611382 | N30: 3010 | P30: Others | Q30: Stamping Charges for 24611382 | V30: 2027/01 | W30: 4501501 | X30: =VLOOKUP(L30,L:P,5,FALSE) -> Others
B31: 20260406 | C31: 1700000064 | D31: BEHC | E31: KA | F31: 46177 | G31: 50 | H31: -24.75 | I31: INR | J31: 1 | L31: NEFT CHARGES | N31: 3010 | P31: Others | Q31: NEFT CHARGES | V31: 2027/01 | W31: 4501501 | X31: =VLOOKUP(L31,L:P,5,FALSE) -> Others
B32: 20260406 | C32: 1700000071 | D32: BEHC | E32: KA | F32: 46177 | G32: 50 | H32: -5900 | I32: INR | L32: IDIBN52026040636 | N32: 3010 | P32: Others | Q32: DOCUMENTATION CHARGES | V32: 2027/01 | W32: 4501501 | X32: =VLOOKUP(L32,L:P,5,FALSE) -> Others
B33: 20260406 | C33: 1900000137 | D33: BEHC | E33: KR | F33: 46177 | G33: 40 | H33: 211.87 | I33: INR | J33: 13 | L33: 24611381 | N33: 3010 | P33: Others | Q33: Booking Charges for 24611381 | V33: 2027/01 | W33: 4501501 | X33: =VLOOKUP(L33,L:P,5,FALSE) -> Others
B34: 20260406 | C34: 1900000137 | D34: BEHC | E34: KR | F34: 46177 | G34: 40 | H34: 134 | I34: INR | L34: 24611381 | N34: 3010 | P34: Others | Q34: Stamping Charges for 24611381 | V34: 2027/01 | W34: 4501501 | X34: =VLOOKUP(L34,L:P,5,FALSE) -> Others
B35: 20260406 | C35: 1900000138 | D35: BEHC | E35: KR | F35: 46177 | G35: 40 | H35: 211.87 | I35: INR | J35: 13 | L35: 24611382 | N35: 3010 | P35: Others | Q35: Booking Charges for 24611382 | V35: 2027/01 | W35: 4501501 | X35: =VLOOKUP(L35,L:P,5,FALSE) -> Others
B36: 20260406 | C36: 1900000138 | D36: BEHC | E36: KR | F36: 46177 | G36: 40 | H36: 153 | I36: INR | L36: 24611382 | N36: 3010 | P36: Others | Q36: Stamping Charges for 24611382 | V36: 2027/01 | W36: 4501501 | X36: =VLOOKUP(L36,L:P,5,FALSE) -> Others
B37: 20260406 | C37: 1900000386 | D37: BEHC | E37: KR | F37: 46177 | G37: 40 | H37: 2000 | I37: INR | J37: 1 | L37: 469BC73260940004 | N37: 3010 | P37: LC Chgs | Q37: BILL COMM AGST INV- 5400513975 OLIMP IMPEX | V37: 2027/01 | W37: 4501501 | X37: =VLOOKUP(L37,L:P,5,FALSE) -> LC Chgs
B38: 20260406 | C38: 1900000403 | D38: BEHC | E38: KR | F38: 46177 | G38: 40 | H38: 211.87 | I38: INR | J38: 13 | L38: 24611381 | N38: 3010 | P38: Others | Q38: Booking Charges for 24611381 | V38: 2027/01 | W38: 4501501 | X38: =VLOOKUP(L38,L:P,5,FALSE) -> Others
B39: 20260406 | C39: 1900000403 | D39: BEHC | E39: KR | F39: 46177 | G39: 40 | H39: 134 | I39: INR | L39: 24611381 | N39: 3010 | P39: Others | Q39: Stamping Charges for 24611381 | V39: 2027/01 | W39: 4501501 | X39: =VLOOKUP(L39,L:P,5,FALSE) -> Others
B40: 20260406 | C40: 1900000404 | D40: BEHC | E40: KR | F40: 46177 | G40: 40 | H40: 211.87 | I40: INR | J40: 13 | L40: 24611382 | N40: 3010 | P40: Others | Q40: Booking Charges for 24611382 | V40: 2027/01 | W40: 4501501 | X40: =VLOOKUP(L40,L:P,5,FALSE) -> Others
B41: 20260406 | C41: 1900000404 | D41: BEHC | E41: KR | F41: 46177 | G41: 40 | H41: 153 | I41: INR | L41: 24611382 | N41: 3010 | P41: Others | Q41: Stamping Charges for 24611382 | V41: 2027/01 | W41: 4501501 | X41: =VLOOKUP(L41,L:P,5,FALSE) -> Others
B42: 20260406 | C42: 1900000463 | D42: BEHC | E42: KR | F42: 46177 | G42: 40 | H42: 24.75 | I42: INR | J42: 1 | L42: NEFT CHG | N42: 3010 | P42: Others | Q42: NEFT CHG | V42: 2027/01 | W42: 4501501 | X42: =VLOOKUP(L42,L:P,5,FALSE) -> Others
B43: 20260406 | C43: 1900000562 | D43: BEHC | E43: KR | F43: 46177 | G43: 40 | H43: 5900 | I43: INR | L43: IDIBN52026040636 | N43: 3010 | P43: Others | Q43: DOCUMENTATION CHARGES | V43: 2027/01 | W43: 4501501 | X43: =VLOOKUP(L43,L:P,5,FALSE) -> Others
B44: 20260406 | C44: 1900000564 | D44: BEHC | E44: KR | F44: 46177 | G44: 40 | H44: 24.75 | I44: INR | J44: 1 | L44: NEFT CHARGES | N44: 3010 | P44: Others | Q44: NEFT CHARGES | V44: 2027/01 | W44: 4501501 | X44: =VLOOKUP(L44,L:P,5,FALSE) -> Others
B45: 20260406 | C45: 1900000658 | D45: BEHC | E45: KR | F45: 46177 | G45: 40 | H45: 2500 | I45: INR | J45: 1 | L45: 68840M11F0351126 | M45: 68840M11F0351126 | N45: 3010 | P45: LC Chgs | Q45: SWIFT CHARGES | V45: 2027/01 | W45: 4501501 | X45: =VLOOKUP(L45,L:P,5,FALSE) -> LC Chgs
B46: 20260406 | C46: 1900000744 | D46: HYDO | E46: KR | F46: 46177 | G46: 40 | H46: 5000 | I46: INR | J46: 1 | L46: IDIBN52026040636 | N46: 1021 | P46: Others | Q46: DOCUMENTATION CHARGES | V46: 2027/01 | W46: 4501501 | X46: =VLOOKUP(L46,L:P,5,FALSE) -> Others
B47: 20260407 | C47: 1900000387 | D47: BEHC | E47: KR | F47: 46207 | G47: 40 | H47: 2000 | I47: INR | J47: 1 | L47: 469BC73260970007 | N47: 3010 | P47: Others | Q47: BILL COMM AGST INV- MCEX12782122 1/LPL | V47: 2027/01 | W47: 4501501 | X47: =VLOOKUP(L47,L:P,5,FALSE) -> Others
B48: 20260407 | C48: 1900000459 | D48: BEHC | E48: KR | F48: 46207 | G48: 40 | H48: 49.5 | I48: INR | J48: 13 | L48: RTGS CHG | N48: 3010 | P48: Others | Q48: RTGS CHG | V48: 2027/01 | W48: 4501501 | X48: =VLOOKUP(L48,L:P,5,FALSE) -> Others
B49: 20260407 | C49: 1900000460 | D49: BEHC | E49: KR | F49: 46177 | G49: 40 | H49: 49.5 | I49: INR | J49: 13 | L49: RTGS CHG | N49: 3010 | P49: Others | Q49: RTGS CHG | V49: 2027/01 | W49: 4501501 | X49: =VLOOKUP(L49,L:P,5,FALSE) -> Others
B50: 20260407 | C50: 1900000472 | D50: KUTC | E50: KR | F50: 46207 | G50: 40 | H50: 1157.32 | I50: INR | J50: 13 | L50: RFU2604041357631 | N50: 1021 | P50: Others | Q50: ACH D- RFU2604041357631-DRBUY5739314 | V50: 2027/01 | W50: 4501501 | X50: =VLOOKUP(L50,L:P,5,FALSE) -> Others
B51: 20260407 | C51: 1900000650 | D51: BEHC | E51: KR | F51: 46207 | G51: 40 | H51: 3000 | I51: INR | J51: 1 | L51: 469FT01260970018 | N51: 3010 | P51: Others | Q51: COMMISSION ON FOREX PAYMENT OF NEOMAR | V51: 2027/01 | W51: 4501501 | X51: =VLOOKUP(L51,L:P,5,FALSE) -> Others
B52: 20260408 | C52: 100000305 | D52: KUTC | E52: SA | F52: 46238 | G52: 40 | H52: 25497.8 | I52: INR | L52: 469BC89260500003 | N52: 1021 | P52: Retirement Chgs | Q52: DISCREPANCY CHG AGST DISC CRED INV- 5400513983 LAT | V52: 2027/01 | W52: 4501501 | X52: =VLOOKUP(L52,L:P,5,FALSE) -> Retirement Chgs
B53: 20260408 | C53: 100000549 | D53: KUTC | E53: SA | F53: 46238 | G53: 40 | H53: 7205.9 | I53: INR | L53: 469BC89260090006 | N53: 1021 | P53: Retirement Chgs | Q53: DISCREPANCY CHG AGST DISC INV- 5400513947 PAGOUNI | V53: 2027/01 | W53: 4501501 | X53: =VLOOKUP(L53,L:P,5,FALSE) -> Retirement Chgs
B54: 20260408 | C54: 1900000456 | D54: BEHC | E54: KR | F54: 46238 | G54: 40 | H54: 49.5 | I54: INR | J54: 13 | L54: RTGS CHG | N54: 3010 | P54: Others | Q54: RTGS CHG | V54: 2027/01 | W54: 4501501 | X54: =VLOOKUP(L54,L:P,5,FALSE) -> Others
B55: 20260408 | C55: 1900000457 | D55: BEHC | E55: KR | F55: 46238 | G55: 40 | H55: 49.5 | I55: INR | J55: 13 | L55: RTGS CHG | N55: 3010 | P55: Others | Q55: RTGS CHG | V55: 2027/01 | W55: 4501501 | X55: =VLOOKUP(L55,L:P,5,FALSE) -> Others
B56: 20260408 | C56: 1900000458 | D56: BEHC | E56: KR | F56: 46238 | G56: 40 | H56: 4.75 | I56: INR | J56: 1 | L56: NEFT CHG | N56: 3010 | P56: Others | Q56: NEFT CHG | V56: 2027/01 | W56: 4501501 | X56: =VLOOKUP(L56,L:P,5,FALSE) -> Others
B57: 20260408 | C57: 1900000473 | D57: KUTC | E57: KR | F57: 46238 | G57: 40 | H57: 1037.31 | I57: INR | J57: 13 | L57: RFU2604071364125 | N57: 1021 | P57: Others | Q57: ACH D- RFU2604071364125-DRBUY5769384 | V57: 2027/01 | W57: 4501501 | X57: =VLOOKUP(L57,L:P,5,FALSE) -> Others
B58: 20260408 | C58: 1900000474 | D58: KUTC | E58: KR | F58: 46238 | G58: 40 | H58: 264.48 | I58: INR | J58: 13 | L58: RFU2604071364126 | N58: 1021 | P58: Others | Q58: ACH D- RFU2604071364126-DRBUY5769377 | V58: 2027/01 | W58: 4501501 | X58: =VLOOKUP(L58,L:P,5,FALSE) -> Others
B59: 20260408 | C59: 1900000475 | D59: KUTC | E59: KR | F59: 46238 | G59: 40 | H59: 28.38 | I59: INR | J59: 13 | L59: RFU2604071364127 | N59: 1021 | P59: Others | Q59: ACH D- RFU2604071364127-DRBUY5773079 | V59: 2027/01 | W59: 4501501 | X59: =VLOOKUP(L59,L:P,5,FALSE) -> Others
B60: 20260408 | C60: 1900000625 | D60: BEHC | E60: KR | F60: 46238 | G60: 40 | H60: 100 | I60: INR | J60: 1 | L60: 469BC04260150013 | N60: 3010 | P60: LC Chgs | Q60: BANK CHARGES | V60: 2027/01 | W60: 4501501 | X60: =VLOOKUP(L60,L:P,5,FALSE) -> LC Chgs
B61: 20260409 | C61: 1900000143 | D61: BEHC | E61: KR | F61: 46269 | G61: 40 | H61: 49.5 | I61: INR | J61: 13 | L61: RTGS CHG | N61: 3010 | P61: Others | Q61: RTGS CHG | V61: 2027/01 | W61: 4501501 | X61: =VLOOKUP(L61,L:P,5,FALSE) -> Others
B62: 20260409 | C62: 1900000144 | D62: BEHC | E62: KR | F62: 46269 | G62: 40 | H62: 49.5 | I62: INR | J62: 13 | L62: RTGS CHG | N62: 3010 | P62: Others | Q62: RTGS CHG | V62: 2027/01 | W62: 4501501 | X62: =VLOOKUP(L62,L:P,5,FALSE) -> Others
B63: 20260409 | C63: 1900000389 | D63: BEHC | E63: KR | F63: 46269 | G63: 40 | H63: 2000 | I63: INR | J63: 1 | L63: 469BC73260990003 | N63: 3010 | P63: LC Chgs | Q63: BILL COMM AGST INV- 5400513748 NODEN | V63: 2027/01 | W63: 4501501 | X63: =VLOOKUP(L63,L:P,5,FALSE) -> LC Chgs
B64: 20260409 | C64: 1900000390 | D64: BEHC | E64: KR | F64: 46269 | G64: 40 | H64: 2000 | I64: INR | J64: 1 | L64: 469BC63260990002 | N64: 3010 | P64: LC Chgs | Q64: BILL COMM AGST INV- 5400513749 PAUL COM | V64: 2027/01 | W64: 4501501 | X64: =VLOOKUP(L64,L:P,5,FALSE) -> LC Chgs
B65: 20260409 | C65: 1900000391 | D65: BEHC | E65: KR | F65: 46269 | G65: 40 | H65: 2000 | I65: INR | J65: 1 | L65: 469BC63260990003 | N65: 3010 | P65: LC Chgs | Q65: BILL COMM AGST INV- 5400513932 STEEL HUB LLC | V65: 2027/01 | W65: 4501501 | X65: =VLOOKUP(L65,L:P,5,FALSE) -> LC Chgs
B66: 20260409 | C66: 1900000478 | D66: KUTC | E66: KR | F66: 46269 | G66: 40 | H66: 336.05 | I66: INR | J66: 13 | L66: RFU2604071364743 | N66: 1021 | P66: Others | Q66: ACH D- RFU2604071364743-DRBUY5807084 | V66: 2027/01 | W66: 4501501 | X66: =VLOOKUP(L66,L:P,5,FALSE) -> Others | Y66: {=SUMIFS(SAP!H:H,SAP!L:L,SAP!L80:L461,SAP!V:V,Retirement!B77)} -> 401851.16
B67: 20260409 | C67: 1900000479 | D67: KUTC | E67: KR | F67: 46269 | G67: 40 | H67: 130.62 | I67: INR | J67: 13 | L67: RFU2604071364744 | N67: 1021 | P67: Others | Q67: ACH D- RFU2604071364744-DRBUY5807082 | V67: 2027/01 | W67: 4501501 | X67: =VLOOKUP(L67,L:P,5,FALSE) -> Others | Y67: 1866906.1
B68: 20260409 | C68: 1900000480 | D68: KUTC | E68: KR | F68: 46269 | G68: 40 | H68: 251.87 | I68: INR | J68: 13 | L68: RFU2604071364745 | N68: 1021 | P68: Others | Q68: ACH D- RFU2604071364745-DRBUY5807217 | V68: 2027/01 | W68: 4501501 | X68: =VLOOKUP(L68,L:P,5,FALSE) -> Others | Y68: 2202.5
B69: 20260409 | C69: 1900000481 | D69: KUTC | E69: KR | F69: 46269 | G69: 40 | H69: 350.92 | I69: INR | J69: 13 | L69: RFU2604071364746 | N69: 1021 | P69: Others | Q69: ACH D- RFU2604071364746-DRBUY5807089 | V69: 2027/01 | W69: 4501501 | X69: =VLOOKUP(L69,L:P,5,FALSE) -> Others | Y69: 67407.5
B70: 20260409 | C70: 1900000482 | D70: KUTC | E70: KR | F70: 46269 | G70: 40 | H70: 1141.16 | I70: INR | J70: 13 | L70: RFU2604081365966 | N70: 1021 | P70: Others | Q70: ACH D- RFU2604081365966-DRBUY5808579 | V70: 2027/01 | W70: 4501501 | X70: =VLOOKUP(L70,L:P,5,FALSE) -> Others | Y70: 166407.02
B71: 20260409 | C71: 1900000528 | D71: BEHC | E71: KR | F71: 46269 | G71: 40 | H71: 550 | I71: INR | J71: 1 | L71: 0571026FLU000185 | N71: 3010 | P71: LC Chgs | Q71: BANK CHARGES | V71: 2027/01 | W71: 4501501 | X71: =VLOOKUP(L71,L:P,5,FALSE) -> LC Chgs | Y71: 67942.58
B72: 20260410 | C72: 1900000145 | D72: BEHC | E72: KR | F72: 46299 | G72: 40 | H72: 49.5 | I72: INR | J72: 13 | L72: RTGS CHG | N72: 3010 | P72: Others | Q72: RTGS CHG | V72: 2027/01 | W72: 4501501 | X72: =VLOOKUP(L72,L:P,5,FALSE) -> Others | Y72: 17598.8
B73: 20260410 | C73: 1900000395 | D73: BEHC | E73: KR | F73: 46299 | G73: 40 | H73: 100 | I73: INR | J73: 1 | L73: 469BC04260150011 | N73: 3010 | P73: LC Chgs | Q73: BANK CHARGES | V73: 2027/01 | W73: 4501501 | X73: =VLOOKUP(L73,L:P,5,FALSE) -> LC Chgs | Y73: 16947.75
B74: 20260410 | C74: 1900000396 | D74: BEHC | E74: KR | F74: 46299 | G74: 40 | H74: 100 | I74: INR | J74: 1 | L74: 469BC04260150005 | N74: 3010 | P74: LC Chgs | Q74: BANK CHARGES | V74: 2027/01 | W74: 4501501 | X74: =VLOOKUP(L74,L:P,5,FALSE) -> LC Chgs | Y74: 445.87
B75: 20260410 | C75: 1900000397 | D75: BEHC | E75: KR | F75: 46299 | G75: 40 | H75: 100 | I75: INR | J75: 1 | L75: 469BC04260150007 | N75: 3010 | P75: Retirement chgs | Q75: BANK CHARGES | V75: 2027/01 | W75: 4501501 | X75: =VLOOKUP(L75,L:P,5,FALSE) -> Retirement chgs | Y75: 2202.5
B76: 20260410 | C76: 1900000660 | D76: BEHC | E76: KR | F76: 46299 | G76: 40 | H76: 500 | I76: INR | J76: 1 | L76: 68840M11F0258226 | M76: 68840M11F0258226 - COR006 | N76: 3010 | P76: retirement chgs | Q76: SWIFT CHARGES OF HONORS COMMODITY | V76: 2027/01 | W76: 4501501 | X76: =VLOOKUP(L76,L:P,5,FALSE) -> retirement chgs | Y76: 2202.5
B77: 20260411 | C77: 1900000668 | D77: BEHC | E77: KR | F77: 46330 | G77: 40 | H77: 0.49 | I77: INR | J77: 1 | L77: SMS CHG | N77: 3010 | P77: Others | Q77: SMS CHRG FOR:01-01-2026to31-03-2026 | V77: 2027/01 | W77: 4501501 | X77: =VLOOKUP(L77,L:P,5,FALSE) -> Others | Y77: 2202.5
B78: 20260411 | C78: 1900000696 | D78: BEHC | E78: KR | F78: 46330 | G78: 40 | H78: 15.46 | I78: INR | L78: BHOPAL PYMT | N78: 3010 | P78: Others | Q78: PORTAL CHARGES FOR PYMT | V78: 2027/01 | W78: 4501501 | X78: =VLOOKUP(L78,L:P,5,FALSE) -> Others | Y78: 2202.5
B79: 20260411 | C79: 1900000696 | D79: BEHC | E79: KR | F79: 46330 | G79: 40 | H79: 1.9 | I79: INR | J79: 1 | L79: BHOPAL PYMT | N79: 3010 | P79: Others | Q79: BANK CHARGES | V79: 2027/01 | W79: 4501501 | X79: =VLOOKUP(L79,L:P,5,FALSE) -> Others | Y79: 401851.16
B80: 20260413 | C80: 1500000871 | D80: KUTC | E80: KZ | F80: 13-04-2026 | G80: 40 | H80: 9337 | I80: INR | L80: 68840M11F0878425 | N80: 1021 | P80: Retirement Chgs | Q80: OTHER CHARGES OF LC PYMT OF HONORS | V80: 2027/01 | W80: 4501501 | X80: =VLOOKUP(L80,L:P,5,FALSE) -> Retirement Chgs | Y80: 30500
B81: 20260413 | C81: 1500000872 | D81: KUTC | E81: KZ | F81: 13-04-2026 | G81: 40 | H81: 9337 | I81: INR | L81: 68840M11F087842P | N81: 1021 | P81: Retirement Chgs | Q81: OTHER CHARGES OF LC PYMT OF HONORS | V81: 2027/01 | W81: 4501501 | X81: =VLOOKUP(L81,L:P,5,FALSE) -> Retirement Chgs | Y81: 26540.73
B82: 20260413 | C82: 1900000146 | D82: BEHC | E82: KR | F82: 13-04-2026 | G82: 40 | H82: 49.5 | I82: INR | J82: 13 | L82: RTGS CHG | N82: 3010 | P82: Others | Q82: RTGS CHG | V82: 2027/01 | W82: 4501501 | X82: =VLOOKUP(L82,L:P,5,FALSE) -> Others | Y82: 73.75
B83: 20260413 | C83: 1900000172 | D83: BEHC | E83: KR | F83: 13-04-2026 | G83: 40 | H83: 4500 | I83: INR | J83: 1 | L83: 469BC89261030007 | N83: 3010 | P83: LC Sales | Q83: BILL COMM AGST INV- 5400514083 LATTONEDIL | V83: 2027/01 | W83: 4501501 | X83: =VLOOKUP(L83,L:P,5,FALSE) -> LC Sales | Y83: 10000
B84: 20260413 | C84: 1900000173 | D84: BEHC | E84: KR | F84: 13-04-2026 | G84: 40 | H84: 4500 | I84: INR | J84: 1 | L84: 469BC89261030011 | N84: 3010 | P84: LC Sales | Q84: BILL COMM AGST INV- 5400514072 IDROCENTRO | V84: 2027/01 | W84: 4501501 | X84: =VLOOKUP(L84,L:P,5,FALSE) -> LC Sales | Y84: 100
B85: 20260413 | C85: 1900000181 | D85: BEHC | E85: KR | F85: 13-04-2026 | G85: 40 | H85: 4500 | I85: INR | J85: 1 | L85: 469BC89261030010 | N85: 3010 | P85: LC Sales | Q85: BILL COMM AGST INV- 5400154078 IDROCENTRO | V85: 2027/01 | W85: 4501501 | X85: =VLOOKUP(L85,L:P,5,FALSE) -> LC Sales | Y85: 20430.18
B86: 20260413 | C86: 1900000214 | D86: BEHC | E86: KR | F86: 13-04-2026 | G86: 40 | H86: 4500 | I86: INR | J86: 1 | L86: 469BC89261030001 | N86: 3010 | P86: LC Sales | Q86: BILL COMM AGST INV- 5400514090 LATTONEDIL | V86: 2027/01 | W86: 4501501 | X86: =VLOOKUP(L86,L:P,5,FALSE) -> LC Sales | Y86: 5656.5
B87: 20260413 | C87: 1900000215 | D87: BEHC | E87: KR | F87: 13-04-2026 | G87: 40 | H87: 4500 | I87: INR | J87: 1 | L87: 469BC89261030003 | N87: 3010 | P87: LC Sales | Q87: BILL COMM AGST INV- 5400514093 LATTONEDIL | V87: 2027/01 | W87: 4501501 | X87: =VLOOKUP(L87,L:P,5,FALSE) -> LC Sales | Y87: 3959.55
B88: 20260413 | C88: 1900000408 | D88: BEHC | E88: KR | F88: 13-04-2026 | G88: 40 | H88: 100 | I88: INR | J88: 13 | L88: 24611381 | N88: 3010 | P88: Others | Q88: CANC CHARGES ON FWD CANC 24611381 | V88: 2027/01 | W88: 4501501 | X88: =VLOOKUP(L88,L:P,5,FALSE) -> Others | Y88: 5656.5
B89: 20260413 | C89: 1900000451 | D89: BEHC | E89: KR | F89: 13-04-2026 | G89: 40 | H89: 49.5 | I89: INR | J89: 13 | L89: RTGS CHG | N89: 3010 | P89: Others | Q89: RTGS CHG | V89: 2027/01 | W89: 4501501 | X89: =VLOOKUP(L89,L:P,5,FALSE) -> Others | Y89: 124103.74
B90: 20260413 | C90: 1900000452 | D90: BEHC | E90: KR | F90: 13-04-2026 | G90: 40 | H90: 49.5 | I90: INR | J90: 13 | L90: RTGS CHG | N90: 3010 | P90: Others | Q90: RTGS CHG | V90: 2027/01 | W90: 4501501 | X90: =VLOOKUP(L90,L:P,5,FALSE) -> Others | Y90: 383.87
B91: 20260413 | C91: 1900000453 | D91: BEHC | E91: KR | F91: 13-04-2026 | G91: 40 | H91: 49.5 | I91: INR | J91: 13 | L91: RTGS CHG | N91: 3010 | P91: Others | Q91: RTGS CHG | V91: 2027/01 | W91: 4501501 | X91: =VLOOKUP(L91,L:P,5,FALSE) -> Others | Y91: 383.87
B92: 20260413 | C92: 1900000454 | D92: BEHC | E92: KR | F92: 13-04-2026 | G92: 40 | H92: 49.5 | I92: INR | J92: 13 | L92: RTGS CHG | N92: 3010 | P92: Others | Q92: RTGS CHG | V92: 2027/01 | W92: 4501501 | X92: =VLOOKUP(L92,L:P,5,FALSE) -> Others | Y92: 122177.03
B93: 20260413 | C93: 1900000661 | D93: BEHC | E93: KR | F93: 13-04-2026 | G93: 40 | H93: 500 | I93: INR | J93: 1 | L93: 68840M11F0878425 | N93: 3010 | P93: Retirement Chgs | Q93: SWIFT CHARGES | V93: 2027/01 | W93: 4501501 | X93: =VLOOKUP(L93,L:P,5,FALSE) -> Retirement Chgs | Y93: 124103.74
B94: 20260413 | C94: 1900000662 | D94: BEHC | E94: KR | F94: 13-04-2026 | G94: 40 | H94: 500 | I94: INR | J94: 1 | L94: 68840M11F087842 | N94: 3010 | P94: Retirement Chgs | Q94: SWIFT CHARGES | V94: 2027/01 | W94: 4501501 | X94: =VLOOKUP(L94,L:P,5,FALSE) -> Retirement Chgs | Y94: 383.87
B95: 20260414 | C95: 1900000334 | D95: KUTC | E95: KR | F95: 14-04-2026 | G95: 40 | H95: 758.31 | I95: INR | J95: 13 | L95: RFU2604131372833 | N95: 1021 | P95: Others | Q95: ACH D- RFU2604131372833-DRBUY5935643 | V95: 2027/01 | W95: 4501501 | X95: =VLOOKUP(L95,L:P,5,FALSE) -> Others | Y95: 383.87
B96: 20260414 | C96: 1900000450 | D96: BEHC | E96: KR | F96: 14-04-2026 | G96: 40 | H96: 4.75 | I96: INR | J96: 1 | L96: NEFT CHG | N96: 3010 | P96: Others | Q96: NEFT CHG | V96: 2027/01 | W96: 4501501 | X96: =VLOOKUP(L96,L:P,5,FALSE) -> Others | Y96: 122177.03
B97: 20260414 | C97: 1900000701 | D97: HYDO | E97: KR | F97: 14-04-2026 | G97: 40 | H97: 10000 | I97: INR | J97: 1 | L97: LOCKER RENT | N97: 1021 | P97: Others | Q97: LOCKER RENT- BRN 3860/MEDIUM/B01/7 50500004894474 | V97: 2027/01 | W97: 4501501 | X97: =VLOOKUP(L97,L:P,5,FALSE) -> Others | Y97: 2202.5
B98: 20260415 | C98: 1900000409 | D98: BEHC | E98: KR | F98: 15-04-2026 | G98: 40 | H98: 100 | I98: INR | J98: 13 | L98: 24240500 | N98: 3010 | P98: Others | Q98: CANC CHARGES ON FWD CANC 24240500 | V98: 2027/01 | W98: 4501501 | X98: =VLOOKUP(L98,L:P,5,FALSE) -> Others | Y98: 368025.25
B99: 20260416 | C99: 100000189 | D99: KUTC | E99: SA | F99: 16-04-2026 | G99: 40 | H99: 18666.45 | I99: INR | L99: 469BC89260190002 | N99: 1021 | P99: Retirement Chgs | Q99: DISCREPANCY CHARGES AGST INV- 5400513944 ITALPANEL | V99: 2027/01 | W99: 4501501 | X99: =VLOOKUP(L99,L:P,5,FALSE) -> Retirement Chgs | Y99: 74461.31
B100: 20260416 | C100: 100000190 | D100: KUTC | E100: SA | F100: 16-04-2026 | G100: 40 | H100: 5656.5 | I100: INR | L100: 469BC89260470003 | N100: 1021 | P100: Retirement Chgs | Q100: DISCREPANCY CHARGES AGST INV- 5400514002 LATTONED | V100: 2027/01 | W100: 4501501 | X100: =VLOOKUP(L100,L:P,5,FALSE) -> Retirement Chgs | Y100: 10493.71
B101: 20260416 | C101: 100000550 | D101: KUTC | E101: SA | F101: 16-04-2026 | G101: 40 | H101: 3959.55 | I101: INR | L101: 469BC89260220005 | N101: 1021 | P101: Retirement Chgs | Q101: DISCREPANCY CHG AGST DISC INV- 5400513953 KAMARID | V101: 2027/01 | W101: 4501501 | X101: =VLOOKUP(L101,L:P,5,FALSE) -> Retirement Chgs | Y101: 21205
B102: 20260416 | C102: 100000551 | D102: KUTC | E102: SA | F102: 16-04-2026 | G102: 40 | H102: 5656.5 | I102: INR | L102: 469BC89260470004 | N102: 1021 | P102: Retirement Chgs | Q102: DISCREPANCY CHG AGST DISC INV- 5400514000 LATTONED | V102: 2027/01 | W102: 4501501 | X102: =VLOOKUP(L102,L:P,5,FALSE) -> Retirement Chgs | Y102: 125573.49
B103: 20260416 | C103: 1700000057 | D103: BEHC | E103: KA | F103: 16-04-2026 | G103: 50 | H103: -1250 | I103: INR | J103: 13 | L103: 0822BDO266053336 | N103: 3010 | P103: LC Sales | Q103: BILL HANDLING CHG | V103: 2027/01 | W103: 4501501 | X103: =VLOOKUP(L103,L:P,5,FALSE) -> LC Sales | Y103: 383.87
...

Sheet Sheet1
C1: sales
B2: SAP | C2: SAP VS W | D2: W
B3: 469BC89261030007 | C3: =VLOOKUP(B3,D:D,1,FALSE) -> 469BC89261030007 | D3: 469BC89260860007
B4: 469BC89261030011 | C4: =VLOOKUP(B4,D:D,1,FALSE) -> 469BC89261030011 | D4: 469BC89260890006
B5: 469BC89261030010 | C5: =VLOOKUP(B5,D:D,1,FALSE) -> 469BC89261030010 | D5: 469BC89261030001
B6: 469BC89261030001 | C6: =VLOOKUP(B6,D:D,1,FALSE) -> 469BC89261030001 | D6: 469BC89261030003
B7: 469BC89261030003 | C7: =VLOOKUP(B7,D:D,1,FALSE) -> 469BC89261030003 | D7: 469BC89261030011
B8: 469BC89261060003 | C8: =VLOOKUP(B8,D:D,1,FALSE) -> 469BC89261060003 | D8: 469BC89261030007
B9: 469BC89261060002 | C9: =VLOOKUP(B9,D:D,1,FALSE) -> 469BC89261060002 | D9: 469BC89261030010
B10: 469BC89261060001 | C10: =VLOOKUP(B10,D:D,1,FALSE) -> 469BC89261060001 | D10: 469BC89261060001
B11: 469BC89261100002 | C11: =VLOOKUP(B11,D:D,1,FALSE) -> 469BC89261100002 | D11: 469BC89261060002
B12: 469BC89261100003 | C12: =VLOOKUP(B12,D:D,1,FALSE) -> #N/A | D12: 469BC89261060003
B13: 469BC89261100004 | C13: =VLOOKUP(B13,D:D,1,FALSE) -> 469BC89261100004 | D13: 469BC89261100007
B14: 469BC89261100005 | C14: =VLOOKUP(B14,D:D,1,FALSE) -> 469BC89261100005 | D14: 469BC89261100005
... B29: 469BC89261200004 | C29: =VLOOKUP(B29,D:D,1,FALSE) -> 469BC89261200004 | D29: 469BC89261200004
B30: 469BC89260890006 | C30: =VLOOKUP(B30,D:D,1,FALSE) -> 469BC89260890006
B31: 469BC89260860007 | C31: =VLOOKUP(B31,D:D,1,FALSE) -> 469BC89260860007
B32: 469BC89261030003 | C32: =VLOOKUP(B32,D:D,1,FALSE) -> 469BC89261030003
B33: 469BC89261030001 | C33: =VLOOKUP(B33,D:D,1,FALSE) -> 469BC89261030001
B34: 0822BDO266053336 | C34: =VLOOKUP(B34,D:D,1,FALSE) -> #N/A
B35: 0822BDO266053335 | C35: =VLOOKUP(B35,D:D,1,FALSE) -> #N/A
B36: 0822BDO266053336 | C36: =VLOOKUP(B36,D:D,1,FALSE) -> #N/A
B37: 0822BDO266053335 | C37: =VLOOKUP(B37,D:D,1,FALSE) -> #N/A
B38: 469BC89261030010 | C38: =VLOOKUP(B38,D:D,1,FALSE) -> 469BC89261030010
B39: 469BC89261030007 | C39: =VLOOKUP(B39,D:D,1,FALSE) -> 469BC89261030007
B40: 469BC89261030011 | C40: =VLOOKUP(B40,D:D,1,FALSE) -> 469BC89261030011
B41: 0822BDO266053336 | C41: =VLOOKUP(B41,D:D,1,FALSE) -> #N/A
... B67: 469BC89261200004 | C67: =VLOOKUP(B67,D:D,1,FALSE) -> 469BC89261200004
